Workbook

Sheet Start Here
A1: Start Here
A2: Starting roster for 2026-27: every campus of the five Area Offices (266, from the 26-27 SY Area Office Unit Assignments). The 11 campuses with a PTA on the Texas PTA roster are marked as having a PTO/PTA; every other campus shows "Nothing received yet" until it sends something.
A4: What this is
A5: One Google Sheet, one Google Form and one dashboard page. The person on the ParentOrgDocs inbox fills in the form for each email that arrives: the campus, whether it has a PTO or PTA, and the documents attached. A script files each document in that campus's Drive folder, marks the item Received in the Campus Register tab and adds a row to the Submission Log tab. The dashboard page reads the tabs every time it is opened, so it is always current. Officers come in a second way: you paste the Excel export of the HISD Parent Organization Officer Update Form into the Officer Form Paste tab and choose PTO/PTA Tracker > Import officers. The script lists each officer on the Officers tab under the campus the form names and marks Officer Information Accepted (it needs no review). On the dashboard, click a campus to see its checklist, what is pending, its recent activity and, for signed-in C1s and FACE staff, its officers. Everyone uses the same dashboard address. Leadership just opens it. C1 Coordinators and FACE staff choose Sign in on the page and type a passcode, which lets them open the files and mark each document Accepted or Needs correction.
A6: Definitions
A7: Registered: these three are accepted for the school year: training certificate, the organization's bylaws and the officer information form. A PTA counts the same way: it sends the training certificate and the officer information form, and its bylaws box is filled from the Texas PTA spreadsheet.
A8: Legalized: these are all accepted: training certificate, the organization's bylaws, the officer information form, annual budget report or meeting minutes showing budget approval, proof of 501(c) status and bank account verification letter from financial institution listing two authorized account signers. The dashboard calls this Can Fundraise. For a PTA, the bylaws, budget (SOA 990), 501(c) status (PTA status) and bank account (JoinPTA.org activation) boxes come from the Texas PTA spreadsheet each week. A reviewer can mark any document Not Needed for a PTO/PTA; it then counts as done.
A9: Item status: Not Received, Received (waiting for review), Accepted, Needs Correction, or Not Needed. Accepted and Not Needed count. An uploaded document is set to Received, and a reviewer checks it off on the dashboard (or in the Campus Register tab). The officer information form is set to Accepted as soon as it comes in: nobody reviews it.
A10: Has PTO or PTA: Yes, No, or Not Yet Confirmed (the default; the dashboard shows it as "Nothing received yet"). A campus becomes Yes by itself when it sends documents or an officer form, when a reviewer checks a document off, or when the Texas PTA roster lists it. A form answer of Not Yet Confirmed never overwrites a Yes or a No.
A11: Set it up once
A12: 1. Save this file to Google Drive, open it with Google Sheets and choose File > Save as Google Sheets. Keep it in the Google account that should own the documents (see Accounts, below).
A13: 2. Choose Extensions > Apps Script. Replace everything in Code.gs with the contents of the Code.gs file. Click + next to Files, choose HTML, name it Dashboard (exactly) and paste in the contents of Dashboard.html. Click Save.
... A86: 1. Only Articles of Incorporation is one-time and carries forward; everything else, including the bank and EIN letter and insurance, renews yearly. 2. The school year starts July 1 (Settings). 3. Campuses are the ones marked Yes (122) or Unsure (32) in the TB PTO/PTA Tracker; the campuses marked No are not included. Area Office comes from the 26-27 SY Area Office Unit Assignments workbook. 23 names are spelled differently in the two files (see Roster Match Notes) and 2 campuses have no Area Office yet. 4. The officer information form is the HISD Parent Organization Officer Update Form (Microsoft Forms). Its Excel export is pasted into Officer Form Paste and imported; one form covers one organization and names its school, so no guessing is needed. The importer ignores a leading asterisk when matching campus names (the register has *Kinder HSPVA). It has not been checked whether that form's school list uses exactly the register's spellings. A school that is not in the register, even after ignoring capitals, punctuation and High School / Middle School / Elementary wording, is added as a new campus, so check the Campus Register for a near-duplicate after an import; a campus name typed by hand that is not in the register is flagged, never added. 5. C1 review: C1s and FACE staff sign in on the dashboard with a passcode (kept only as a salted hash) instead of a Google sign-in, because Google tells a script who is looking only when they are in the sheet owner's organization. The log records the signed-in person's name. Who is a C1 for which campus comes only from the C1 Assignments tab; who is staff comes only from the Dashboard sign-ins tab. 6. Decided: FACE's What to Submit guide lists five documents plus the officer form for annual registration, but Registered counts only training, bylaws and officer information. The budget proof, 501(c) proof, bank and EIN letter and Articles count toward Legalized only. Insurance is optional and counts toward neither. 7. Booster clubs are not tracked: the officer import leaves their forms out entirely. 8. Changed on October 2, 2026: the Tax ID (EIN) letter and the bank letter are one item (Bank and EIN Letter), liability and property insurance is optional, and every document, bank letters included, is filed in the campus folder (there is no separate bank folder). 9. Changed on October 9, 2026: Registered and Legalized use FACE's wording, and Legalized means six documents (Articles of Incorporation is no longer needed). Reviewers check each document off on the dashboard (there, needs correction, not there, or not needed) with remarks that go into the email to the PTO/PTA. Every campus of every Area Office is listed; a campus counts as having a PTO/PTA once it sends something or is on the Texas PTA roster. 10. Changed on October 15, 2026: the officer information form counts as soon as it comes in; a PTA is tracked on the training certificate and the officer information form; Articles of Incorporation and Insurance are no longer asked for; files keep the name they were sent with; the dashboard has a My campus page and a Waiting on column.

Sheet Summary
A1: PTO/PTA Registration Summary
A2: Starting roster: every campus of the five Area Offices (266). 11 PTAs from the Texas PTA roster. No documents received yet.
A3: School year | C3: =Settings!$C$5 | D3: Change it on the Settings sheet.
A5: Milestones
A6: Measure | C6: Campuses | D6: % of confirmed PTO/PTA
A7: Campuses being tracked | C7: =COUNTIFS('Campus Register'!$A$2:$A$600,$C$3)
A8: Have a PTO/PTA (confirmed Yes) | C8: =COUNTIFS('Campus Register'!$A$2:$A$600,$C$3,'Campus Register'!$D$2:$D$600,"Yes")
A9: Confirmed no PTO/PTA | C9: =COUNTIFS('Campus Register'!$A$2:$A$600,$C$3,'Campus Register'!$D$2:$D$600,"No")
A10: Not yet confirmed | C10: =C7-C8-C9
A11: Started (at least one document received) | C11: =COUNTIFS('Campus Register'!$A$2:$A$600,$C$3,'Campus Register'!$D$2:$D$600,"Yes",'Campus Register'!$O$2:$O$600,">0") | D11: =IF($C$8=0,"",C11/$C$8)
A12: Registered (includes Legalized) | C12: =COUNTIFS('Campus Register'!$A$2:$A$600,$C$3,'Campus Register'!$D$2:$D$600,"Yes",'Campus Register'!$P$2:$P$600,">="&Settings!$C$12) | D12: =IF($C$8=0,"",C12/$C$8)
A13: Legalized | C13: =COUNTIFS('Campus Register'!$A$2:$A$600,$C$3,'Campus Register'!$D$2:$D$600,"Yes",'Campus Register'!$Q$2:$Q$600,">="&Settings!$C$13) | D13: =IF($C$8=0,"",C13/$C$8)
A16: Status of each campus (each counted once)
A17: Status | C17: Campuses
A18: Legalized | C18: =COUNTIFS('Campus Register'!$A$2:$A$600,$C$3,'Campus Register'!$R$2:$R$600,A18)
A19: Registered | C19: =COUNTIFS('Campus Register'!$A$2:$A$600,$C$3,'Campus Register'!$R$2:$R$600,A19)
A20: In Progress | C20: =COUNTIFS('Campus Register'!$A$2:$A$600,$C$3,'Campus Register'!$R$2:$R$600,A20)
A21: Not Started | C21: =COUNTIFS('Campus Register'!$A$2:$A$600,$C$3,'Campus Register'!$R$2:$R$600,A21)
A22: No PTO/PTA | C22: =COUNTIFS('Campus Register'!$A$2:$A$600,$C$3,'Campus Register'!$R$2:$R$600,A22)
A23: Not Yet Confirmed | C23: =COUNTIFS('Campus Register'!$A$2:$A$600,$C$3,'Campus Register'!$R$2:$R$600,A23)
A24: Total (should equal campuses being tracked) | C24: =SUM(C18:C23) | D24: =IF(C24=C7,"OK","Check: does not match roster")
A27: Documents (campuses with a PTO/PTA)
A28: Document | C28: Accepted | D28: Received, awaiting review | E28: Needs correction | F28: Not received | G28: % accepted
A29: Bylaws | C29: =COUNTIFS('Campus Register'!$A$2:$A$600,$C$3,'Campus Register'!$D$2:$D$600,"Yes",'Campus Register'!$G$2:$G$600,"Accepted") | D29: =COUNTIFS('Campus Register'!$A$2:$A$600,$C$3,'Campus Register'!$D$2:$D$600,"Yes",'Campus Register'!$G$2:$G$600,"Received") | E29: =COUNTIFS('Campus Register'!$A$2:$A$600,$C$3,'Campus Register'!$D$2:$D$600,"Yes",'Campus Register'!$G$2:$G$600,"Needs Correction") | F29: =COUNTIFS('Campus Register'!$A$2:$A$600,$C$3,'Campus Register'!$D$2:$D$600,"Yes",'Campus Register'!$G$2:$G$600,"Not Received") | G29: =IF($C$8=0,"",C29/$C$8)
A30: Officer Information | C30: =COUNTIFS('Campus Register'!$A$2:$A$600,$C$3,'Campus Register'!$D$2:$D$600,"Yes",'Campus Register'!$H$2:$H$600,"Accepted") | D30: =COUNTIFS('Campus Register'!$A$2:$A$600,$C$3,'Campus Register'!$D$2:$D$600,"Yes",'Campus Register'!$H$2:$H$600,"Received") | E30: =COUNTIFS('Campus Register'!$A$2:$A$600,$C$3,'Campus Register'!$D$2:$D$600,"Yes",'Campus Register'!$H$2:$H$600,"Needs Correction") | F30: =COUNTIFS('Campus Register'!$A$2:$A$600,$C$3,'Campus Register'!$D$2:$D$600,"Yes",'Campus Register'!$H$2:$H$600,"Not Received") | G30: =IF($C$8=0,"",C30/$C$8)
A31: Training Certificate | C31: =COUNTIFS('Campus Register'!$A$2:$A$600,$C$3,'Campus Register'!$D$2:$D$600,"Yes",'Campus Register'!$I$2:$I$600,"Accepted") | D31: =COUNTIFS('Campus Register'!$A$2:$A$600,$C$3,'Campus Register'!$D$2:$D$600,"Yes",'Campus Register'!$I$2:$I$600,"Received") | E31: =COUNTIFS('Campus Register'!$A$2:$A$600,$C$3,'Campus Register'!$D$2:$D$600,"Yes",'Campus Register'!$I$2:$I$600,"Needs Correction") | F31: =COUNTIFS('Campus Register'!$A$2:$A$600,$C$3,'Campus Register'!$D$2:$D$600,"Yes",'Campus Register'!$I$2:$I$600,"Not Received") | G31: =IF($C$8=0,"",C31/$C$8)
A32: Budget or Financial Report | C32: =COUNTIFS('Campus Register'!$A$2:$A$600,$C$3,'Campus Register'!$D$2:$D$600,"Yes",'Campus Register'!$J$2:$J$600,"Accepted") | D32: =COUNTIFS('Campus Register'!$A$2:$A$600,$C$3,'Campus Register'!$D$2:$D$600,"Yes",'Campus Register'!$J$2:$J$600,"Received") | E32: =COUNTIFS('Campus Register'!$A$2:$A$600,$C$3,'Campus Register'!$D$2:$D$600,"Yes",'Campus Register'!$J$2:$J$600,"Needs Correction") | F32: =COUNTIFS('Campus Register'!$A$2:$A$600,$C$3,'Campus Register'!$D$2:$D$600,"Yes",'Campus Register'!$J$2:$J$600,"Not Received") | G32: =IF($C$8=0,"",C32/$C$8)
A33: Proof of 501c Status | C33: =COUNTIFS('Campus Register'!$A$2:$A$600,$C$3,'Campus Register'!$D$2:$D$600,"Yes",'Campus Register'!$K$2:$K$600,"Accepted") | D33: =COUNTIFS('Campus Register'!$A$2:$A$600,$C$3,'Campus Register'!$D$2:$D$600,"Yes",'Campus Register'!$K$2:$K$600,"Received") | E33: =COUNTIFS('Campus Register'!$A$2:$A$600,$C$3,'Campus Register'!$D$2:$D$600,"Yes",'Campus Register'!$K$2:$K$600,"Needs Correction") | F33: =COUNTIFS('Campus Register'!$A$2:$A$600,$C$3,'Campus Register'!$D$2:$D$600,"Yes",'Campus Register'!$K$2:$K$600,"Not Received") | G33: =IF($C$8=0,"",C33/$C$8)
A34: Bank Verification Letter | C34: =COUNTIFS('Campus Register'!$A$2:$A$600,$C$3,'Campus Register'!$D$2:$D$600,"Yes",'Campus Register'!$L$2:$L$600,"Accepted") | D34: =COUNTIFS('Campus Register'!$A$2:$A$600,$C$3,'Campus Register'!$D$2:$D$600,"Yes",'Campus Register'!$L$2:$L$600,"Received") | E34: =COUNTIFS('Campus Register'!$A$2:$A$600,$C$3,'Campus Register'!$D$2:$D$600,"Yes",'Campus Register'!$L$2:$L$600,"Needs Correction") | F34: =COUNTIFS('Campus Register'!$A$2:$A$600,$C$3,'Campus Register'!$D$2:$D$600,"Yes",'Campus Register'!$L$2:$L$600,"Not Received") | G34: =IF($C$8=0,"",C34/$C$8)
A35: Articles of Incorporation | C35: =COUNTIFS('Campus Register'!$A$2:$A$600,$C$3,'Campus Register'!$D$2:$D$600,"Yes",'Campus Register'!$M$2:$M$600,"Accepted") | D35: =COUNTIFS('Campus Register'!$A$2:$A$600,$C$3,'Campus Register'!$D$2:$D$600,"Yes",'Campus Register'!$M$2:$M$600,"Received") | E35: =COUNTIFS('Campus Register'!$A$2:$A$600,$C$3,'Campus Register'!$D$2:$D$600,"Yes",'Campus Register'!$M$2:$M$600,"Needs Correction") | F35: =COUNTIFS('Campus Register'!$A$2:$A$600,$C$3,'Campus Register'!$D$2:$D$600,"Yes",'Campus Register'!$M$2:$M$600,"Not Received") | G35: =IF($C$8=0,"",C35/$C$8)
A36: Insurance (optional) | C36: =COUNTIFS('Campus Register'!$A$2:$A$600,$C$3,'Campus Register'!$D$2:$D$600,"Yes",'Campus Register'!$N$2:$N$600,"Accepted") | D36: =COUNTIFS('Campus Register'!$A$2:$A$600,$C$3,'Campus Register'!$D$2:$D$600,"Yes",'Campus Register'!$N$2:$N$600,"Received") | E36: =COUNTIFS('Campus Register'!$A$2:$A$600,$C$3,'Campus Register'!$D$2:$D$600,"Yes",'Campus Register'!$N$2:$N$600,"Needs Correction") | F36: =COUNTIFS('Campus Register'!$A$2:$A$600,$C$3,'Campus Register'!$D$2:$D$600,"Yes",'Campus Register'!$N$2:$N$600,"Not Received") | G36: =IF($C$8=0,"",C36/$C$8)
A39: Area Offices
A40: Area Office | C40: Campuses | D40: Have a PTO/PTA | E40: Registered | F40: Legalized | G40: % legalized
A41: =Settings!E18 | C41: =COUNTIFS('Campus Register'!$A$2:$A$600,$C$3,'Campus Register'!$C$2:$C$600,$A41) | D41: =COUNTIFS('Campus Register'!$A$2:$A$600,$C$3,'Campus Register'!$C$2:$C$600,$A41,'Campus Register'!$D$2:$D$600,"Yes") | E41: =COUNTIFS('Campus Register'!$A$2:$A$600,$C$3,'Campus Register'!$C$2:$C$600,$A41,'Campus Register'!$D$2:$D$600,"Yes",'Campus Register'!$P$2:$P$600,">="&Settings!$C$12) | F41: =COUNTIFS('Campus Register'!$A$2:$A$600,$C$3,'Campus Register'!$C$2:$C$600,$A41,'Campus Register'!$D$2:$D$600,"Yes",'Campus Register'!$Q$2:$Q$600,">="&Settings!$C$13) | G41: =IF(D41=0,"",F41/D41)
A42: =Settings!E19 | C42: =COUNTIFS('Campus Register'!$A$2:$A$600,$C$3,'Campus Register'!$C$2:$C$600,$A42) | D42: =COUNTIFS('Campus Register'!$A$2:$A$600,$C$3,'Campus Register'!$C$2:$C$600,$A42,'Campus Register'!$D$2:$D$600,"Yes") | E42: =COUNTIFS('Campus Register'!$A$2:$A$600,$C$3,'Campus Register'!$C$2:$C$600,$A42,'Campus Register'!$D$2:$D$600,"Yes",'Campus Register'!$P$2:$P$600,">="&Settings!$C$12) | F42: =COUNTIFS('Campus Register'!$A$2:$A$600,$C$3,'Campus Register'!$C$2:$C$600,$A42,'Campus Register'!$D$2:$D$600,"Yes",'Campus Register'!$Q$2:$Q$600,">="&Settings!$C$13) | G42: =IF(D42=0,"",F42/D42)
A43: =Settings!E20 | C43: =COUNTIFS('Campus Register'!$A$2:$A$600,$C$3,'Campus Register'!$C$2:$C$600,$A43) | D43: =COUNTIFS('Campus Register'!$A$2:$A$600,$C$3,'Campus Register'!$C$2:$C$600,$A43,'Campus Register'!$D$2:$D$600,"Yes") | E43: =COUNTIFS('Campus Register'!$A$2:$A$600,$C$3,'Campus Register'!$C$2:$C$600,$A43,'Campus Register'!$D$2:$D$600,"Yes",'Campus Register'!$P$2:$P$600,">="&Settings!$C$12) | F43: =COUNTIFS('Campus Register'!$A$2:$A$600,$C$3,'Campus Register'!$C$2:$C$600,$A43,'Campus Register'!$D$2:$D$600,"Yes",'Campus Register'!$Q$2:$Q$600,">="&Settings!$C$13) | G43: =IF(D43=0,"",F43/D43)
A44: =Settings!E21 | C44: =COUNTIFS('Campus Register'!$A$2:$A$600,$C$3,'Campus Register'!$C$2:$C$600,$A44) | D44: =COUNTIFS('Campus Register'!$A$2:$A$600,$C$3,'Campus Register'!$C$2:$C$600,$A44,'Campus Register'!$D$2:$D$600,"Yes") | E44: =COUNTIFS('Campus Register'!$A$2:$A$600,$C$3,'Campus Register'!$C$2:$C$600,$A44,'Campus Register'!$D$2:$D$600,"Yes",'Campus Register'!$P$2:$P$600,">="&Settings!$C$12) | F44: =COUNTIFS('Campus Register'!$A$2:$A$600,$C$3,'Campus Register'!$C$2:$C$600,$A44,'Campus Register'!$D$2:$D$600,"Yes",'Campus Register'!$Q$2:$Q$600,">="&Settings!$C$13) | G44: =IF(D44=0,"",F44/D44)
A45: =Settings!E22 | C45: =COUNTIFS('Campus Register'!$A$2:$A$600,$C$3,'Campus Register'!$C$2:$C$600,$A45) | D45: =COUNTIFS('Campus Register'!$A$2:$A$600,$C$3,'Campus Register'!$C$2:$C$600,$A45,'Campus Register'!$D$2:$D$600,"Yes") | E45: =COUNTIFS('Campus Register'!$A$2:$A$600,$C$3,'Campus Register'!$C$2:$C$600,$A45,'Campus Register'!$D$2:$D$600,"Yes",'Campus Register'!$P$2:$P$600,">="&Settings!$C$12) | F45: =COUNTIFS('Campus Register'!$A$2:$A$600,$C$3,'Campus Register'!$C$2:$C$600,$A45,'Campus Register'!$D$2:$D$600,"Yes",'Campus Register'!$Q$2:$Q$600,">="&Settings!$C$13) | G45: =IF(D45=0,"",F45/D45)
A48: Data checks
A49: Campuses with documents on file but Has PTO or PTA not confirmed as Yes | C49: =COUNTIFS('Campus Register'!$A$2:$A$600,$C$3,'Campus Register'!$D$2:$D$600,"<>Yes",'Campus Register'!$O$2:$O$600,">0") | D49: Ask the coordinator to confirm these campuses.
A50: Documents logged for this school year | C50: =COUNTIF('Submission Log'!$G$2:$G$800,$C$3) | D50: Rows in the Submission Log, added by the form.
A51: Officer update forms received for this school year | C51: =COUNTIFS(Officers!$C$2:$C$1000,$C$3,Officers!$F$2:$F$1000,1) | D51: From the Officers tab (one form = one organization).
A52: Officer forms still needing a campus picked | C52: =COUNTIFS(Officers!$F$2:$F$1000,1,Officers!$D$2:$D$1000,"",Officers!$C$2:$C$1000,$C$3) | D52: On the Officers tab, type the campus in the Campus column, then run the import again.

Sheet Campus Register
A1: School Year | B1: Campus | C1: Area Office | D1: Has PTO or PTA | E1: Org Type | F1: Org Name | G1: Bylaws | H1: Officer Information | I1: Training Certificate | J1: Budget or Financial Report | K1: Proof of 501c Status | L1: Bank Verification Letter | M1: Articles of Incorporation | N1: Insurance | O1: Items Received | P1: Registration Items Accepted | Q1: Legalization Items Accepted | R1: Status | S1: Items Awaiting Review | T1: Items Needing Correction | U1: Not Yet Accepted
A2: 2026-27 | B2: Anderson ES | C2: NES Elementary | D2: Not Yet Confirmed | G2: Not Received | H2: Not Received | I2: Not Received | J2: Not Received | K2: Not Received | L2: Not Received | M2: Not Received | N2: Not Received | O2: =IF($B2="","",COUNTIF(G2:N2,"Accepted")+COUNTIF(G2:N2,"Received")+COUNTIF(G2:N2,"Needs Correction")) | P2: =IF($B2="","",SUMPRODUCT(((G2:N2="Accepted")+(G2:N2="Not Needed"))*(Settings!$C$11:$J$11="Yes"))) | Q2: =IF($B2="","",SUMPRODUCT(((G2:N2="Accepted")+(G2:N2="Not Needed"))*(Settings!$C$15:$J$15="Yes"))) | R2: =IF($B2="","",IF($D2="No","No PTO/PTA",IF($D2<>"Yes","Not Yet Confirmed",IF($Q2>=Settings!$C$13,"Legalized",IF($P2>=Settings!$C$12,"Registered",IF($O2>0,"In Progress","Not Started")))))) | S2: =IF($B2="","",COUNTIF(G2:N2,"Received")) | T2: =IF($B2="","",COUNTIF(G2:N2,"Needs Correction")) | U2: =IF($B2="","",IF($D2<>"Yes","",IF($Q2>=Settings!$C$13,"None",MID(IF(AND(G2<>"Accepted",G2<>"Not Needed",Settings!$C$15="Yes"),", "&G$1,"")&IF(AND(H2<>"Accepted",H2<>"Not Needed",Settings!$D$15="Yes"),", "&H$1,"")&IF(AND(I2<>"Accepted",I2<>"Not Needed",Settings!$E$15="Yes"),", "&I$1,"")&IF(AND(J2<>"Accepted",J2<>"Not Needed",Settings!$F$15="Yes"),", "&J$1,"")&IF(AND(K2<>"Accepted",K2<>"Not Needed",Settings!$G$15="Yes"),", "&K$1,"")&IF(AND(L2<>"Accepted",L2<>"Not Needed",Settings!$H$15="Yes"),", "&L$1,"")&IF(AND(M2<>"Accepted",M2<>"Not Needed",Settings!$I$15="Yes"),", "&M$1,"")&IF(AND(N2<>"Accepted",N2<>"Not Needed",Settings!$J$15="Yes"),", "&N$1,""),3,400))))
A3: 2026-27 | B3: Ashford ES | C3: NES Elementary | D3: Not Yet Confirmed | G3: Not Received | H3: Not Received | I3: Not Received | J3: Not Received | K3: Not Received | L3: Not Received | M3: Not Received | N3: Not Received | O3: =IF($B3="","",COUNTIF(G3:N3,"Accepted")+COUNTIF(G3:N3,"Received")+COUNTIF(G3:N3,"Needs Correction")) | P3: =IF($B3="","",SUMPRODUCT(((G3:N3="Accepted")+(G3:N3="Not Needed"))*(Settings!$C$11:$J$11="Yes"))) | Q3: =IF($B3="","",SUMPRODUCT(((G3:N3="Accepted")+(G3:N3="Not Needed"))*(Settings!$C$15:$J$15="Yes"))) | R3: =IF($B3="","",IF($D3="No","No PTO/PTA",IF($D3<>"Yes","Not Yet Confirmed",IF($Q3>=Settings!$C$13,"Legalized",IF($P3>=Settings!$C$12,"Registered",IF($O3>0,"In Progress","Not Started")))))) | S3: =IF($B3="","",COUNTIF(G3:N3,"Received")) | T3: =IF($B3="","",COUNTIF(G3:N3,"Needs Correction")) | U3: =IF($B3="","",IF($D3<>"Yes","",IF($Q3>=Settings!$C$13,"None",MID(IF(AND(G3<>"Accepted",G3<>"Not Needed",Settings!$C$15="Yes"),", "&G$1,"")&IF(AND(H3<>"Accepted",H3<>"Not Needed",Settings!$D$15="Yes"),", "&H$1,"")&IF(AND(I3<>"Accepted",I3<>"Not Needed",Settings!$E$15="Yes"),", "&I$1,"")&IF(AND(J3<>"Accepted",J3<>"Not Needed",Settings!$F$15="Yes"),", "&J$1,"")&IF(AND(K3<>"Accepted",K3<>"Not Needed",Settings!$G$15="Yes"),", "&K$1,"")&IF(AND(L3<>"Accepted",L3<>"Not Needed",Settings!$H$15="Yes"),", "&L$1,"")&IF(AND(M3<>"Accepted",M3<>"Not Needed",Settings!$I$15="Yes"),", "&M$1,"")&IF(AND(N3<>"Accepted",N3<>"Not Needed",Settings!$J$15="Yes"),", "&N$1,""),3,400))))
A4: 2026-27 | B4: Askew ES | C4: NES Elementary | D4: Not Yet Confirmed | G4: Not Received | H4: Not Received | I4: Not Received | J4: Not Received | K4: Not Received | L4: Not Received | M4: Not Received | N4: Not Received | O4: =IF($B4="","",COUNTIF(G4:N4,"Accepted")+COUNTIF(G4:N4,"Received")+COUNTIF(G4:N4,"Needs Correction")) | P4: =IF($B4="","",SUMPRODUCT(((G4:N4="Accepted")+(G4:N4="Not Needed"))*(Settings!$C$11:$J$11="Yes"))) | Q4: =IF($B4="","",SUMPRODUCT(((G4:N4="Accepted")+(G4:N4="Not Needed"))*(Settings!$C$15:$J$15="Yes"))) | R4: =IF($B4="","",IF($D4="No","No PTO/PTA",IF($D4<>"Yes","Not Yet Confirmed",IF($Q4>=Settings!$C$13,"Legalized",IF($P4>=Settings!$C$12,"Registered",IF($O4>0,"In Progress","Not Started")))))) | S4: =IF($B4="","",COUNTIF(G4:N4,"Received")) | T4: =IF($B4="","",COUNTIF(G4:N4,"Needs Correction")) | U4: =IF($B4="","",IF($D4<>"Yes","",IF($Q4>=Settings!$C$13,"None",MID(IF(AND(G4<>"Accepted",G4<>"Not Needed",Settings!$C$15="Yes"),", "&G$1,"")&IF(AND(H4<>"Accepted",H4<>"Not Needed",Settings!$D$15="Yes"),", "&H$1,"")&IF(AND(I4<>"Accepted",I4<>"Not Needed",Settings!$E$15="Yes"),", "&I$1,"")&IF(AND(J4<>"Accepted",J4<>"Not Needed",Settings!$F$15="Yes"),", "&J$1,"")&IF(AND(K4<>"Accepted",K4<>"Not Needed",Settings!$G$15="Yes"),", "&K$1,"")&IF(AND(L4<>"Accepted",L4<>"Not Needed",Settings!$H$15="Yes"),", "&L$1,"")&IF(AND(M4<>"Accepted",M4<>"Not Needed",Settings!$I$15="Yes"),", "&M$1,"")&IF(AND(N4<>"Accepted",N4<>"Not Needed",Settings!$J$15="Yes"),", "&N$1,""),3,400))))
A5: 2026-27 | B5: Atherton ES | C5: NES Elementary | D5: Not Yet Confirmed | G5: Not Received | H5: Not Received | I5: Not Received | J5: Not Received | K5: Not Received | L5: Not Received | M5: Not Received | N5: Not Received | O5: =IF($B5="","",COUNTIF(G5:N5,"Accepted")+COUNTIF(G5:N5,"Received")+COUNTIF(G5:N5,"Needs Correction")) | P5: =IF($B5="","",SUMPRODUCT(((G5:N5="Accepted")+(G5:N5="Not Needed"))*(Settings!$C$11:$J$11="Yes"))) | Q5: =IF($B5="","",SUMPRODUCT(((G5:N5="Accepted")+(G5:N5="Not Needed"))*(Settings!$C$15:$J$15="Yes"))) | R5: =IF($B5="","",IF($D5="No","No PTO/PTA",IF($D5<>"Yes","Not Yet Confirmed",IF($Q5>=Settings!$C$13,"Legalized",IF($P5>=Settings!$C$12,"Registered",IF($O5>0,"In Progress","Not Started")))))) | S5: =IF($B5="","",COUNTIF(G5:N5,"Received")) | T5: =IF($B5="","",COUNTIF(G5:N5,"Needs Correction")) | U5: =IF($B5="","",IF($D5<>"Yes","",IF($Q5>=Settings!$C$13,"None",MID(IF(AND(G5<>"Accepted",G5<>"Not Needed",Settings!$C$15="Yes"),", "&G$1,"")&IF(AND(H5<>"Accepted",H5<>"Not Needed",Settings!$D$15="Yes"),", "&H$1,"")&IF(AND(I5<>"Accepted",I5<>"Not Needed",Settings!$E$15="Yes"),", "&I$1,"")&IF(AND(J5<>"Accepted",J5<>"Not Needed",Settings!$F$15="Yes"),", "&J$1,"")&IF(AND(K5<>"Accepted",K5<>"Not Needed",Settings!$G$15="Yes"),", "&K$1,"")&IF(AND(L5<>"Accepted",L5<>"Not Needed",Settings!$H$15="Yes"),", "&L$1,"")&IF(AND(M5<>"Accepted",M5<>"Not Needed",Settings!$I$15="Yes"),", "&M$1,"")&IF(AND(N5<>"Accepted",N5<>"Not Needed",Settings!$J$15="Yes"),", "&N$1,""),3,400))))
A6: 2026-27 | B6: Barrick ES | C6: NES Elementary | D6: Not Yet Confirmed | G6: Not Received | H6: Not Received | I6: Not Received | J6: Not Received | K6: Not Received | L6: Not Received | M6: Not Received | N6: Not Received | O6: =IF($B6="","",COUNTIF(G6:N6,"Accepted")+COUNTIF(G6:N6,"Received")+COUNTIF(G6:N6,"Needs Correction")) | P6: =IF($B6="","",SUMPRODUCT(((G6:N6="Accepted")+(G6:N6="Not Needed"))*(Settings!$C$11:$J$11="Yes"))) | Q6: =IF($B6="","",SUMPRODUCT(((G6:N6="Accepted")+(G6:N6="Not Needed"))*(Settings!$C$15:$J$15="Yes"))) | R6: =IF($B6="","",IF($D6="No","No PTO/PTA",IF($D6<>"Yes","Not Yet Confirmed",IF($Q6>=Settings!$C$13,"Legalized",IF($P6>=Settings!$C$12,"Registered",IF($O6>0,"In Progress","Not Started")))))) | S6: =IF($B6="","",COUNTIF(G6:N6,"Received")) | T6: =IF($B6="","",COUNTIF(G6:N6,"Needs Correction")) | U6: =IF($B6="","",IF($D6<>"Yes","",IF($Q6>=Settings!$C$13,"None",MID(IF(AND(G6<>"Accepted",G6<>"Not Needed",Settings!$C$15="Yes"),", "&G$1,"")&IF(AND(H6<>"Accepted",H6<>"Not Needed",Settings!$D$15="Yes"),", "&H$1,"")&IF(AND(I6<>"Accepted",I6<>"Not Needed",Settings!$E$15="Yes"),", "&I$1,"")&IF(AND(J6<>"Accepted",J6<>"Not Needed",Settings!$F$15="Yes"),", "&J$1,"")&IF(AND(K6<>"Accepted",K6<>"Not Needed",Settings!$G$15="Yes"),", "&K$1,"")&IF(AND(L6<>"Accepted",L6<>"Not Needed",Settings!$H$15="Yes"),", "&L$1,"")&IF(AND(M6<>"Accepted",M6<>"Not Needed",Settings!$I$15="Yes"),", "&M$1,"")&IF(AND(N6<>"Accepted",N6<>"Not Needed",Settings!$J$15="Yes"),", "&N$1,""),3,400))))
A7: 2026-27 | B7: Bastian ES | C7: NES Elementary | D7: No | G7: Not Received | H7: Not Received | I7: Not Received | J7: Not Received | K7: Not Received | L7: Not Received | M7: Not Received | N7: Not Received | O7: =IF($B7="","",COUNTIF(G7:N7,"Accepted")+COUNTIF(G7:N7,"Received")+COUNTIF(G7:N7,"Needs Correction")) | P7: =IF($B7="","",SUMPRODUCT(((G7:N7="Accepted")+(G7:N7="Not Needed"))*(Settings!$C$11:$J$11="Yes"))) | Q7: =IF($B7="","",SUMPRODUCT(((G7:N7="Accepted")+(G7:N7="Not Needed"))*(Settings!$C$15:$J$15="Yes"))) | R7: =IF($B7="","",IF($D7="No","No PTO/PTA",IF($D7<>"Yes","Not Yet Confirmed",IF($Q7>=Settings!$C$13,"Legalized",IF($P7>=Settings!$C$12,"Registered",IF($O7>0,"In Progress","Not Started")))))) | S7: =IF($B7="","",COUNTIF(G7:N7,"Received")) | T7: =IF($B7="","",COUNTIF(G7:N7,"Needs Correction")) | U7: =IF($B7="","",IF($D7<>"Yes","",IF($Q7>=Settings!$C$13,"None",MID(IF(AND(G7<>"Accepted",G7<>"Not Needed",Settings!$C$15="Yes"),", "&G$1,"")&IF(AND(H7<>"Accepted",H7<>"Not Needed",Settings!$D$15="Yes"),", "&H$1,"")&IF(AND(I7<>"Accepted",I7<>"Not Needed",Settings!$E$15="Yes"),", "&I$1,"")&IF(AND(J7<>"Accepted",J7<>"Not Needed",Settings!$F$15="Yes"),", "&J$1,"")&IF(AND(K7<>"Accepted",K7<>"Not Needed",Settings!$G$15="Yes"),", "&K$1,"")&IF(AND(L7<>"Accepted",L7<>"Not Needed",Settings!$H$15="Yes"),", "&L$1,"")&IF(AND(M7<>"Accepted",M7<>"Not Needed",Settings!$I$15="Yes"),", "&M$1,"")&IF(AND(N7<>"Accepted",N7<>"Not Needed",Settings!$J$15="Yes"),", "&N$1,""),3,400))))
A8: 2026-27 | B8: Benbrook ES | C8: NES Elementary | D8: No | G8: Not Received | H8: Not Received | I8: Not Received | J8: Not Received | K8: Not Received | L8: Not Received | M8: Not Received | N8: Not Received | O8: =IF($B8="","",COUNTIF(G8:N8,"Accepted")+COUNTIF(G8:N8,"Received")+COUNTIF(G8:N8,"Needs Correction")) | P8: =IF($B8="","",SUMPRODUCT(((G8:N8="Accepted")+(G8:N8="Not Needed"))*(Settings!$C$11:$J$11="Yes"))) | Q8: =IF($B8="","",SUMPRODUCT(((G8:N8="Accepted")+(G8:N8="Not Needed"))*(Settings!$C$15:$J$15="Yes"))) | R8: =IF($B8="","",IF($D8="No","No PTO/PTA",IF($D8<>"Yes","Not Yet Confirmed",IF($Q8>=Settings!$C$13,"Legalized",IF($P8>=Settings!$C$12,"Registered",IF($O8>0,"In Progress","Not Started")))))) | S8: =IF($B8="","",COUNTIF(G8:N8,"Received")) | T8: =IF($B8="","",COUNTIF(G8:N8,"Needs Correction")) | U8: =IF($B8="","",IF($D8<>"Yes","",IF($Q8>=Settings!$C$13,"None",MID(IF(AND(G8<>"Accepted",G8<>"Not Needed",Settings!$C$15="Yes"),", "&G$1,"")&IF(AND(H8<>"Accepted",H8<>"Not Needed",Settings!$D$15="Yes"),", "&H$1,"")&IF(AND(I8<>"Accepted",I8<>"Not Needed",Settings!$E$15="Yes"),", "&I$1,"")&IF(AND(J8<>"Accepted",J8<>"Not Needed",Settings!$F$15="Yes"),", "&J$1,"")&IF(AND(K8<>"Accepted",K8<>"Not Needed",Settings!$G$15="Yes"),", "&K$1,"")&IF(AND(L8<>"Accepted",L8<>"Not Needed",Settings!$H$15="Yes"),", "&L$1,"")&IF(AND(M8<>"Accepted",M8<>"Not Needed",Settings!$I$15="Yes"),", "&M$1,"")&IF(AND(N8<>"Accepted",N8<>"Not Needed",Settings!$J$15="Yes"),", "&N$1,""),3,400))))
A9: 2026-27 | B9: Berry ES | C9: NES Elementary | D9: Not Yet Confirmed | G9: Not Received | H9: Not Received | I9: Not Received | J9: Not Received | K9: Not Received | L9: Not Received | M9: Not Received | N9: Not Received | O9: =IF($B9="","",COUNTIF(G9:N9,"Accepted")+COUNTIF(G9:N9,"Received")+COUNTIF(G9:N9,"Needs Correction")) | P9: =IF($B9="","",SUMPRODUCT(((G9:N9="Accepted")+(G9:N9="Not Needed"))*(Settings!$C$11:$J$11="Yes"))) | Q9: =IF($B9="","",SUMPRODUCT(((G9:N9="Accepted")+(G9:N9="Not Needed"))*(Settings!$C$15:$J$15="Yes"))) | R9: =IF($B9="","",IF($D9="No","No PTO/PTA",IF($D9<>"Yes","Not Yet Confirmed",IF($Q9>=Settings!$C$13,"Legalized",IF($P9>=Settings!$C$12,"Registered",IF($O9>0,"In Progress","Not Started")))))) | S9: =IF($B9="","",COUNTIF(G9:N9,"Received")) | T9: =IF($B9="","",COUNTIF(G9:N9,"Needs Correction")) | U9: =IF($B9="","",IF($D9<>"Yes","",IF($Q9>=Settings!$C$13,"None",MID(IF(AND(G9<>"Accepted",G9<>"Not Needed",Settings!$C$15="Yes"),", "&G$1,"")&IF(AND(H9<>"Accepted",H9<>"Not Needed",Settings!$D$15="Yes"),", "&H$1,"")&IF(AND(I9<>"Accepted",I9<>"Not Needed",Settings!$E$15="Yes"),", "&I$1,"")&IF(AND(J9<>"Accepted",J9<>"Not Needed",Settings!$F$15="Yes"),", "&J$1,"")&IF(AND(K9<>"Accepted",K9<>"Not Needed",Settings!$G$15="Yes"),", "&K$1,"")&IF(AND(L9<>"Accepted",L9<>"Not Needed",Settings!$H$15="Yes"),", "&L$1,"")&IF(AND(M9<>"Accepted",M9<>"Not Needed",Settings!$I$15="Yes"),", "&M$1,"")&IF(AND(N9<>"Accepted",N9<>"Not Needed",Settings!$J$15="Yes"),", "&N$1,""),3,400))))
A10: 2026-27 | B10: Blackshear ES | C10: NES Elementary | D10: Not Yet Confirmed | G10: Not Received | H10: Not Received | I10: Not Received | J10: Not Received | K10: Not Received | L10: Not Received | M10: Not Received | N10: Not Received | O10: =IF($B10="","",COUNTIF(G10:N10,"Accepted")+COUNTIF(G10:N10,"Received")+COUNTIF(G10:N10,"Needs Correction")) | P10: =IF($B10="","",SUMPRODUCT(((G10:N10="Accepted")+(G10:N10="Not Needed"))*(Settings!$C$11:$J$11="Yes"))) | Q10: =IF($B10="","",SUMPRODUCT(((G10:N10="Accepted")+(G10:N10="Not Needed"))*(Settings!$C$15:$J$15="Yes"))) | R10: =IF($B10="","",IF($D10="No","No PTO/PTA",IF($D10<>"Yes","Not Yet Confirmed",IF($Q10>=Settings!$C$13,"Legalized",IF($P10>=Settings!$C$12,"Registered",IF($O10>0,"In Progress","Not Started")))))) | S10: =IF($B10="","",COUNTIF(G10:N10,"Received")) | T10: =IF($B10="","",COUNTIF(G10:N10,"Needs Correction")) | U10: =IF($B10="","",IF($D10<>"Yes","",IF($Q10>=Settings!$C$13,"None",MID(IF(AND(G10<>"Accepted",G10<>"Not Needed",Settings!$C$15="Yes"),", "&G$1,"")&IF(AND(H10<>"Accepted",H10<>"Not Needed",Settings!$D$15="Yes"),", "&H$1,"")&IF(AND(I10<>"Accepted",I10<>"Not Needed",Settings!$E$15="Yes"),", "&I$1,"")&IF(AND(J10<>"Accepted",J10<>"Not Needed",Settings!$F$15="Yes"),", "&J$1,"")&IF(AND(K10<>"Accepted",K10<>"Not Needed",Settings!$G$15="Yes"),", "&K$1,"")&IF(AND(L10<>"Accepted",L10<>"Not Needed",Settings!$H$15="Yes"),", "&L$1,"")&IF(AND(M10<>"Accepted",M10<>"Not Needed",Settings!$I$15="Yes"),", "&M$1,"")&IF(AND(N10<>"Accepted",N10<>"Not Needed",Settings!$J$15="Yes"),", "&N$1,""),3,400))))
A11: 2026-27 | B11: Bonham ES | C11: NES Elementary | D11: Not Yet Confirmed | G11: Not Received | H11: Not Received | I11: Not Received | J11: Not Received | K11: Not Received | L11: Not Received | M11: Not Received | N11: Not Received | O11: =IF($B11="","",COUNTIF(G11:N11,"Accepted")+COUNTIF(G11:N11,"Received")+COUNTIF(G11:N11,"Needs Correction")) | P11: =IF($B11="","",SUMPRODUCT(((G11:N11="Accepted")+(G11:N11="Not Needed"))*(Settings!$C$11:$J$11="Yes"))) | Q11: =IF($B11="","",SUMPRODUCT(((G11:N11="Accepted")+(G11:N11="Not Needed"))*(Settings!$C$15:$J$15="Yes"))) | R11: =IF($B11="","",IF($D11="No","No PTO/PTA",IF($D11<>"Yes","Not Yet Confirmed",IF($Q11>=Settings!$C$13,"Legalized",IF($P11>=Settings!$C$12,"Registered",IF($O11>0,"In Progress","Not Started")))))) | S11: =IF($B11="","",COUNTIF(G11:N11,"Received")) | T11: =IF($B11="","",COUNTIF(G11:N11,"Needs Correction")) | U11: =IF($B11="","",IF($D11<>"Yes","",IF($Q11>=Settings!$C$13,"None",MID(IF(AND(G11<>"Accepted",G11<>"Not Needed",Settings!$C$15="Yes"),", "&G$1,"")&IF(AND(H11<>"Accepted",H11<>"Not Needed",Settings!$D$15="Yes"),", "&H$1,"")&IF(AND(I11<>"Accepted",I11<>"Not Needed",Settings!$E$15="Yes"),", "&I$1,"")&IF(AND(J11<>"Accepted",J11<>"Not Needed",Settings!$F$15="Yes"),", "&J$1,"")&IF(AND(K11<>"Accepted",K11<>"Not Needed",Settings!$G$15="Yes"),", "&K$1,"")&IF(AND(L11<>"Accepted",L11<>"Not Needed",Settings!$H$15="Yes"),", "&L$1,"")&IF(AND(M11<>"Accepted",M11<>"Not Needed",Settings!$I$15="Yes"),", "&M$1,"")&IF(AND(N11<>"Accepted",N11<>"Not Needed",Settings!$J$15="Yes"),", "&N$1,""),3,400))))
A12: 2026-27 | B12: Bonner ES | C12: NES Elementary | D12: Not Yet Confirmed | G12: Not Received | H12: Not Received | I12: Not Received | J12: Not Received | K12: Not Received | L12: Not Received | M12: Not Received | N12: Not Received | O12: =IF($B12="","",COUNTIF(G12:N12,"Accepted")+COUNTIF(G12:N12,"Received")+COUNTIF(G12:N12,"Needs Correction")) | P12: =IF($B12="","",SUMPRODUCT(((G12:N12="Accepted")+(G12:N12="Not Needed"))*(Settings!$C$11:$J$11="Yes"))) | Q12: =IF($B12="","",SUMPRODUCT(((G12:N12="Accepted")+(G12:N12="Not Needed"))*(Settings!$C$15:$J$15="Yes"))) | R12: =IF($B12="","",IF($D12="No","No PTO/PTA",IF($D12<>"Yes","Not Yet Confirmed",IF($Q12>=Settings!$C$13,"Legalized",IF($P12>=Settings!$C$12,"Registered",IF($O12>0,"In Progress","Not Started")))))) | S12: =IF($B12="","",COUNTIF(G12:N12,"Received")) | T12: =IF($B12="","",COUNTIF(G12:N12,"Needs Correction")) | U12: =IF($B12="","",IF($D12<>"Yes","",IF($Q12>=Settings!$C$13,"None",MID(IF(AND(G12<>"Accepted",G12<>"Not Needed",Settings!$C$15="Yes"),", "&G$1,"")&IF(AND(H12<>"Accepted",H12<>"Not Needed",Settings!$D$15="Yes"),", "&H$1,"")&IF(AND(I12<>"Accepted",I12<>"Not Needed",Settings!$E$15="Yes"),", "&I$1,"")&IF(AND(J12<>"Accepted",J12<>"Not Needed",Settings!$F$15="Yes"),", "&J$1,"")&IF(AND(K12<>"Accepted",K12<>"Not Needed",Settings!$G$15="Yes"),", "&K$1,"")&IF(AND(L12<>"Accepted",L12<>"Not Needed",Settings!$H$15="Yes"),", "&L$1,"")&IF(AND(M12<>"Accepted",M12<>"Not Needed",Settings!$I$15="Yes"),", "&M$1,"")&IF(AND(N12<>"Accepted",N12<>"Not Needed",Settings!$J$15="Yes"),", "&N$1,""),3,400))))
A13: 2026-27 | B13: Browning ES | C13: NES Elementary | D13: Yes | E13: PTA | G13: Accepted | H13: Not Received | I13: Not Received | J13: Not Received | K13: Accepted | L13: Accepted | M13: Not Received | N13: Not Received | O13: =IF($B13="","",COUNTIF(G13:N13,"Accepted")+COUNTIF(G13:N13,"Received")+COUNTIF(G13:N13,"Needs Correction")) | P13: =IF($B13="","",SUMPRODUCT(((G13:N13="Accepted")+(G13:N13="Not Needed"))*(Settings!$C$11:$J$11="Yes"))) | Q13: =IF($B13="","",SUMPRODUCT(((G13:N13="Accepted")+(G13:N13="Not Needed"))*(Settings!$C$15:$J$15="Yes"))) | R13: =IF($B13="","",IF($D13="No","No PTO/PTA",IF($D13<>"Yes","Not Yet Confirmed",IF($Q13>=Settings!$C$13,"Legalized",IF($P13>=Settings!$C$12,"Registered",IF($O13>0,"In Progress","Not Started")))))) | S13: =IF($B13="","",COUNTIF(G13:N13,"Received")) | T13: =IF($B13="","",COUNTIF(G13:N13,"Needs Correction")) | U13: =IF($B13="","",IF($D13<>"Yes","",IF($Q13>=Settings!$C$13,"None",MID(IF(AND(G13<>"Accepted",G13<>"Not Needed",Settings!$C$15="Yes"),", "&G$1,"")&IF(AND(H13<>"Accepted",H13<>"Not Needed",Settings!$D$15="Yes"),", "&H$1,"")&IF(AND(I13<>"Accepted",I13<>"Not Needed",Settings!$E$15="Yes"),", "&I$1,"")&IF(AND(J13<>"Accepted",J13<>"Not Needed",Settings!$F$15="Yes"),", "&J$1,"")&IF(AND(K13<>"Accepted",K13<>"Not Needed",Settings!$G$15="Yes"),", "&K$1,"")&IF(AND(L13<>"Accepted",L13<>"Not Needed",Settings!$H$15="Yes"),", "&L$1,"")&IF(AND(M13<>"Accepted",M13<>"Not Needed",Settings!$I$15="Yes"),", "&M$1,"")&IF(AND(N13<>"Accepted",N13<>"Not Needed",Settings!$J$15="Yes"),", "&N$1,""),3,400))))
A14: 2026-27 | B14: Bruce ES | C14: NES Elementary | D14: No | G14: Not Received | H14: Not Received | I14: Not Received | J14: Not Received | K14: Not Received | L14: Not Received | M14: Not Received | N14: Not Received | O14: =IF($B14="","",COUNTIF(G14:N14,"Accepted")+COUNTIF(G14:N14,"Received")+COUNTIF(G14:N14,"Needs Correction")) | P14: =IF($B14="","",SUMPRODUCT(((G14:N14="Accepted")+(G14:N14="Not Needed"))*(Settings!$C$11:$J$11="Yes"))) | Q14: =IF($B14="","",SUMPRODUCT(((G14:N14="Accepted")+(G14:N14="Not Needed"))*(Settings!$C$15:$J$15="Yes"))) | R14: =IF($B14="","",IF($D14="No","No PTO/PTA",IF($D14<>"Yes","Not Yet Confirmed",IF($Q14>=Settings!$C$13,"Legalized",IF($P14>=Settings!$C$12,"Registered",IF($O14>0,"In Progress","Not Started")))))) | S14: =IF($B14="","",COUNTIF(G14:N14,"Received")) | T14: =IF($B14="","",COUNTIF(G14:N14,"Needs Correction")) | U14: =IF($B14="","",IF($D14<>"Yes","",IF($Q14>=Settings!$C$13,"None",MID(IF(AND(G14<>"Accepted",G14<>"Not Needed",Settings!$C$15="Yes"),", "&G$1,"")&IF(AND(H14<>"Accepted",H14<>"Not Needed",Settings!$D$15="Yes"),", "&H$1,"")&IF(AND(I14<>"Accepted",I14<>"Not Needed",Settings!$E$15="Yes"),", "&I$1,"")&IF(AND(J14<>"Accepted",J14<>"Not Needed",Settings!$F$15="Yes"),", "&J$1,"")&IF(AND(K14<>"Accepted",K14<>"Not Needed",Settings!$G$15="Yes"),", "&K$1,"")&IF(AND(L14<>"Accepted",L14<>"Not Needed",Settings!$H$15="Yes"),", "&L$1,"")&IF(AND(M14<>"Accepted",M14<>"Not Needed",Settings!$I$15="Yes"),", "&M$1,"")&IF(AND(N14<>"Accepted",N14<>"Not Needed",Settings!$J$15="Yes"),", "&N$1,""),3,400))))
A15: 2026-27 | B15: Carrillo ES | C15: NES Elementary | D15: Not Yet Confirmed | G15: Not Received | H15: Not Received | I15: Not Received | J15: Not Received | K15: Not Received | L15: Not Received | M15: Not Received | N15: Not Received | O15: =IF($B15="","",COUNTIF(G15:N15,"Accepted")+COUNTIF(G15:N15,"Received")+COUNTIF(G15:N15,"Needs Correction")) | P15: =IF($B15="","",SUMPRODUCT(((G15:N15="Accepted")+(G15:N15="Not Needed"))*(Settings!$C$11:$J$11="Yes"))) | Q15: =IF($B15="","",SUMPRODUCT(((G15:N15="Accepted")+(G15:N15="Not Needed"))*(Settings!$C$15:$J$15="Yes"))) | R15: =IF($B15="","",IF($D15="No","No PTO/PTA",IF($D15<>"Yes","Not Yet Confirmed",IF($Q15>=Settings!$C$13,"Legalized",IF($P15>=Settings!$C$12,"Registered",IF($O15>0,"In Progress","Not Started")))))) | S15: =IF($B15="","",COUNTIF(G15:N15,"Received")) | T15: =IF($B15="","",COUNTIF(G15:N15,"Needs Correction")) | U15: =IF($B15="","",IF($D15<>"Yes","",IF($Q15>=Settings!$C$13,"None",MID(IF(AND(G15<>"Accepted",G15<>"Not Needed",Settings!$C$15="Yes"),", "&G$1,"")&IF(AND(H15<>"Accepted",H15<>"Not Needed",Settings!$D$15="Yes"),", "&H$1,"")&IF(AND(I15<>"Accepted",I15<>"Not Needed",Settings!$E$15="Yes"),", "&I$1,"")&IF(AND(J15<>"Accepted",J15<>"Not Needed",Settings!$F$15="Yes"),", "&J$1,"")&IF(AND(K15<>"Accepted",K15<>"Not Needed",Settings!$G$15="Yes"),", "&K$1,"")&IF(AND(L15<>"Accepted",L15<>"Not Needed",Settings!$H$15="Yes"),", "&L$1,"")&IF(AND(M15<>"Accepted",M15<>"Not Needed",Settings!$I$15="Yes"),", "&M$1,"")&IF(AND(N15<>"Accepted",N15<>"Not Needed",Settings!$J$15="Yes"),", "&N$1,""),3,400))))
A16: 2026-27 | B16: Coop ES | C16: NES Elementary | D16: Not Yet Confirmed | G16: Not Received | H16: Not Received | I16: Not Received | J16: Not Received | K16: Not Received | L16: Not Received | M16: Not Received | N16: Not Received | O16: =IF($B16="","",COUNTIF(G16:N16,"Accepted")+COUNTIF(G16:N16,"Received")+COUNTIF(G16:N16,"Needs Correction")) | P16: =IF($B16="","",SUMPRODUCT(((G16:N16="Accepted")+(G16:N16="Not Needed"))*(Settings!$C$11:$J$11="Yes"))) | Q16: =IF($B16="","",SUMPRODUCT(((G16:N16="Accepted")+(G16:N16="Not Needed"))*(Settings!$C$15:$J$15="Yes"))) | R16: =IF($B16="","",IF($D16="No","No PTO/PTA",IF($D16<>"Yes","Not Yet Confirmed",IF($Q16>=Settings!$C$13,"Legalized",IF($P16>=Settings!$C$12,"Registered",IF($O16>0,"In Progress","Not Started")))))) | S16: =IF($B16="","",COUNTIF(G16:N16,"Received")) | T16: =IF($B16="","",COUNTIF(G16:N16,"Needs Correction")) | U16: =IF($B16="","",IF($D16<>"Yes","",IF($Q16>=Settings!$C$13,"None",MID(IF(AND(G16<>"Accepted",G16<>"Not Needed",Settings!$C$15="Yes"),", "&G$1,"")&IF(AND(H16<>"Accepted",H16<>"Not Needed",Settings!$D$15="Yes"),", "&H$1,"")&IF(AND(I16<>"Accepted",I16<>"Not Needed",Settings!$E$15="Yes"),", "&I$1,"")&IF(AND(J16<>"Accepted",J16<>"Not Needed",Settings!$F$15="Yes"),", "&J$1,"")&IF(AND(K16<>"Accepted",K16<>"Not Needed",Settings!$G$15="Yes"),", "&K$1,"")&IF(AND(L16<>"Accepted",L16<>"Not Needed",Settings!$H$15="Yes"),", "&L$1,"")&IF(AND(M16<>"Accepted",M16<>"Not Needed",Settings!$I$15="Yes"),", "&M$1,"")&IF(AND(N16<>"Accepted",N16<>"Not Needed",Settings!$J$15="Yes"),", "&N$1,""),3,400))))
A17: 2026-27 | B17: Crockett ES | C17: NES Elementary | D17: Not Yet Confirmed | G17: Not Received | H17: Not Received | I17: Not Received | J17: Not Received | K17: Not Received | L17: Not Received | M17: Not Received | N17: Not Received | O17: =IF($B17="","",COUNTIF(G17:N17,"Accepted")+COUNTIF(G17:N17,"Received")+COUNTIF(G17:N17,"Needs Correction")) | P17: =IF($B17="","",SUMPRODUCT(((G17:N17="Accepted")+(G17:N17="Not Needed"))*(Settings!$C$11:$J$11="Yes"))) | Q17: =IF($B17="","",SUMPRODUCT(((G17:N17="Accepted")+(G17:N17="Not Needed"))*(Settings!$C$15:$J$15="Yes"))) | R17: =IF($B17="","",IF($D17="No","No PTO/PTA",IF($D17<>"Yes","Not Yet Confirmed",IF($Q17>=Settings!$C$13,"Legalized",IF($P17>=Settings!$C$12,"Registered",IF($O17>0,"In Progress","Not Started")))))) | S17: =IF($B17="","",COUNTIF(G17:N17,"Received")) | T17: =IF($B17="","",COUNTIF(G17:N17,"Needs Correction")) | U17: =IF($B17="","",IF($D17<>"Yes","",IF($Q17>=Settings!$C$13,"None",MID(IF(AND(G17<>"Accepted",G17<>"Not Needed",Settings!$C$15="Yes"),", "&G$1,"")&IF(AND(H17<>"Accepted",H17<>"Not Needed",Settings!$D$15="Yes"),", "&H$1,"")&IF(AND(I17<>"Accepted",I17<>"Not Needed",Settings!$E$15="Yes"),", "&I$1,"")&IF(AND(J17<>"Accepted",J17<>"Not Needed",Settings!$F$15="Yes"),", "&J$1,"")&IF(AND(K17<>"Accepted",K17<>"Not Needed",Settings!$G$15="Yes"),", "&K$1,"")&IF(AND(L17<>"Accepted",L17<>"Not Needed",Settings!$H$15="Yes"),", "&L$1,"")&IF(AND(M17<>"Accepted",M17<>"Not Needed",Settings!$I$15="Yes"),", "&M$1,"")&IF(AND(N17<>"Accepted",N17<>"Not Needed",Settings!$J$15="Yes"),", "&N$1,""),3,400))))
A18: 2026-27 | B18: DeZavala ES | C18: NES Elementary | D18: Not Yet Confirmed | G18: Not Received | H18: Not Received | I18: Not Received | J18: Not Received | K18: Not Received | L18: Not Received | M18: Not Received | N18: Not Received | O18: =IF($B18="","",COUNTIF(G18:N18,"Accepted")+COUNTIF(G18:N18,"Received")+COUNTIF(G18:N18,"Needs Correction")) | P18: =IF($B18="","",SUMPRODUCT(((G18:N18="Accepted")+(G18:N18="Not Needed"))*(Settings!$C$11:$J$11="Yes"))) | Q18: =IF($B18="","",SUMPRODUCT(((G18:N18="Accepted")+(G18:N18="Not Needed"))*(Settings!$C$15:$J$15="Yes"))) | R18: =IF($B18="","",IF($D18="No","No PTO/PTA",IF($D18<>"Yes","Not Yet Confirmed",IF($Q18>=Settings!$C$13,"Legalized",IF($P18>=Settings!$C$12,"Registered",IF($O18>0,"In Progress","Not Started")))))) | S18: =IF($B18="","",COUNTIF(G18:N18,"Received")) | T18: =IF($B18="","",COUNTIF(G18:N18,"Needs Correction")) | U18: =IF($B18="","",IF($D18<>"Yes","",IF($Q18>=Settings!$C$13,"None",MID(IF(AND(G18<>"Accepted",G18<>"Not Needed",Settings!$C$15="Yes"),", "&G$1,"")&IF(AND(H18<>"Accepted",H18<>"Not Needed",Settings!$D$15="Yes"),", "&H$1,"")&IF(AND(I18<>"Accepted",I18<>"Not Needed",Settings!$E$15="Yes"),", "&I$1,"")&IF(AND(J18<>"Accepted",J18<>"Not Needed",Settings!$F$15="Yes"),", "&J$1,"")&IF(AND(K18<>"Accepted",K18<>"Not Needed",Settings!$G$15="Yes"),", "&K$1,"")&IF(AND(L18<>"Accepted",L18<>"Not Needed",Settings!$H$15="Yes"),", "&L$1,"")&IF(AND(M18<>"Accepted",M18<>"Not Needed",Settings!$I$15="Yes"),", "&M$1,"")&IF(AND(N18<>"Accepted",N18<>"Not Needed",Settings!$J$15="Yes"),", "&N$1,""),3,400))))
A19: 2026-27 | B19: Eliot ES | C19: NES Elementary | D19: Not Yet Confirmed | G19: Not Received | H19: Not Received | I19: Not Received | J19: Not Received | K19: Not Received | L19: Not Received | M19: Not Received | N19: Not Received | O19: =IF($B19="","",COUNTIF(G19:N19,"Accepted")+COUNTIF(G19:N19,"Received")+COUNTIF(G19:N19,"Needs Correction")) | P19: =IF($B19="","",SUMPRODUCT(((G19:N19="Accepted")+(G19:N19="Not Needed"))*(Settings!$C$11:$J$11="Yes"))) | Q19: =IF($B19="","",SUMPRODUCT(((G19:N19="Accepted")+(G19:N19="Not Needed"))*(Settings!$C$15:$J$15="Yes"))) | R19: =IF($B19="","",IF($D19="No","No PTO/PTA",IF($D19<>"Yes","Not Yet Confirmed",IF($Q19>=Settings!$C$13,"Legalized",IF($P19>=Settings!$C$12,"Registered",IF($O19>0,"In Progress","Not Started")))))) | S19: =IF($B19="","",COUNTIF(G19:N19,"Received")) | T19: =IF($B19="","",COUNTIF(G19:N19,"Needs Correction")) | U19: =IF($B19="","",IF($D19<>"Yes","",IF($Q19>=Settings!$C$13,"None",MID(IF(AND(G19<>"Accepted",G19<>"Not Needed",Settings!$C$15="Yes"),", "&G$1,"")&IF(AND(H19<>"Accepted",H19<>"Not Needed",Settings!$D$15="Yes"),", "&H$1,"")&IF(AND(I19<>"Accepted",I19<>"Not Needed",Settings!$E$15="Yes"),", "&I$1,"")&IF(AND(J19<>"Accepted",J19<>"Not Needed",Settings!$F$15="Yes"),", "&J$1,"")&IF(AND(K19<>"Accepted",K19<>"Not Needed",Settings!$G$15="Yes"),", "&K$1,"")&IF(AND(L19<>"Accepted",L19<>"Not Needed",Settings!$H$15="Yes"),", "&L$1,"")&IF(AND(M19<>"Accepted",M19<>"Not Needed",Settings!$I$15="Yes"),", "&M$1,"")&IF(AND(N19<>"Accepted",N19<>"Not Needed",Settings!$J$15="Yes"),", "&N$1,""),3,400))))
A20: 2026-27 | B20: Elmore ES | C20: NES Elementary | D20: Not Yet Confirmed | G20: Not Received | H20: Not Received | I20: Not Received | J20: Not Received | K20: Not Received | L20: Not Received | M20: Not Received | N20: Not Received | O20: =IF($B20="","",COUNTIF(G20:N20,"Accepted")+COUNTIF(G20:N20,"Received")+COUNTIF(G20:N20,"Needs Correction")) | P20: =IF($B20="","",SUMPRODUCT(((G20:N20="Accepted")+(G20:N20="Not Needed"))*(Settings!$C$11:$J$11="Yes"))) | Q20: =IF($B20="","",SUMPRODUCT(((G20:N20="Accepted")+(G20:N20="Not Needed"))*(Settings!$C$15:$J$15="Yes"))) | R20: =IF($B20="","",IF($D20="No","No PTO/PTA",IF($D20<>"Yes","Not Yet Confirmed",IF($Q20>=Settings!$C$13,"Legalized",IF($P20>=Settings!$C$12,"Registered",IF($O20>0,"In Progress","Not Started")))))) | S20: =IF($B20="","",COUNTIF(G20:N20,"Received")) | T20: =IF($B20="","",COUNTIF(G20:N20,"Needs Correction")) | U20: =IF($B20="","",IF($D20<>"Yes","",IF($Q20>=Settings!$C$13,"None",MID(IF(AND(G20<>"Accepted",G20<>"Not Needed",Settings!$C$15="Yes"),", "&G$1,"")&IF(AND(H20<>"Accepted",H20<>"Not Needed",Settings!$D$15="Yes"),", "&H$1,"")&IF(AND(I20<>"Accepted",I20<>"Not Needed",Settings!$E$15="Yes"),", "&I$1,"")&IF(AND(J20<>"Accepted",J20<>"Not Needed",Settings!$F$15="Yes"),", "&J$1,"")&IF(AND(K20<>"Accepted",K20<>"Not Needed",Settings!$G$15="Yes"),", "&K$1,"")&IF(AND(L20<>"Accepted",L20<>"Not Needed",Settings!$H$15="Yes"),", "&L$1,"")&IF(AND(M20<>"Accepted",M20<>"Not Needed",Settings!$I$15="Yes"),", "&M$1,"")&IF(AND(N20<>"Accepted",N20<>"Not Needed",Settings!$J$15="Yes"),", "&N$1,""),3,400))))
A21: 2026-27 | B21: Gallegos ES | C21: NES Elementary | D21: Not Yet Confirmed | G21: Not Received | H21: Not Received | I21: Not Received | J21: Not Received | K21: Not Received | L21: Not Received | M21: Not Received | N21: Not Received | O21: =IF($B21="","",COUNTIF(G21:N21,"Accepted")+COUNTIF(G21:N21,"Received")+COUNTIF(G21:N21,"Needs Correction")) | P21: =IF($B21="","",SUMPRODUCT(((G21:N21="Accepted")+(G21:N21="Not Needed"))*(Settings!$C$11:$J$11="Yes"))) | Q21: =IF($B21="","",SUMPRODUCT(((G21:N21="Accepted")+(G21:N21="Not Needed"))*(Settings!$C$15:$J$15="Yes"))) | R21: =IF($B21="","",IF($D21="No","No PTO/PTA",IF($D21<>"Yes","Not Yet Confirmed",IF($Q21>=Settings!$C$13,"Legalized",IF($P21>=Settings!$C$12,"Registered",IF($O21>0,"In Progress","Not Started")))))) | S21: =IF($B21="","",COUNTIF(G21:N21,"Received")) | T21: =IF($B21="","",COUNTIF(G21:N21,"Needs Correction")) | U21: =IF($B21="","",IF($D21<>"Yes","",IF($Q21>=Settings!$C$13,"None",MID(IF(AND(G21<>"Accepted",G21<>"Not Needed",Settings!$C$15="Yes"),", "&G$1,"")&IF(AND(H21<>"Accepted",H21<>"Not Needed",Settings!$D$15="Yes"),", "&H$1,"")&IF(AND(I21<>"Accepted",I21<>"Not Needed",Settings!$E$15="Yes"),", "&I$1,"")&IF(AND(J21<>"Accepted",J21<>"Not Needed",Settings!$F$15="Yes"),", "&J$1,"")&IF(AND(K21<>"Accepted",K21<>"Not Needed",Settings!$G$15="Yes"),", "&K$1,"")&IF(AND(L21<>"Accepted",L21<>"Not Needed",Settings!$H$15="Yes"),", "&L$1,"")&IF(AND(M21<>"Accepted",M21<>"Not Needed",Settings!$I$15="Yes"),", "&M$1,"")&IF(AND(N21<>"Accepted",N21<>"Not Needed",Settings!$J$15="Yes"),", "&N$1,""),3,400))))
A22: 2026-27 | B22: Golfcrest ES | C22: NES Elementary | D22: Not Yet Confirmed | G22: Not Received | H22: Not Received | I22: Not Received | J22: Not Received | K22: Not Received | L22: Not Received | M22: Not Received | N22: Not Received | O22: =IF($B22="","",COUNTIF(G22:N22,"Accepted")+COUNTIF(G22:N22,"Received")+COUNTIF(G22:N22,"Needs Correction")) | P22: =IF($B22="","",SUMPRODUCT(((G22:N22="Accepted")+(G22:N22="Not Needed"))*(Settings!$C$11:$J$11="Yes"))) | Q22: =IF($B22="","",SUMPRODUCT(((G22:N22="Accepted")+(G22:N22="Not Needed"))*(Settings!$C$15:$J$15="Yes"))) | R22: =IF($B22="","",IF($D22="No","No PTO/PTA",IF($D22<>"Yes","Not Yet Confirmed",IF($Q22>=Settings!$C$13,"Legalized",IF($P22>=Settings!$C$12,"Registered",IF($O22>0,"In Progress","Not Started")))))) | S22: =IF($B22="","",COUNTIF(G22:N22,"Received")) | T22: =IF($B22="","",COUNTIF(G22:N22,"Needs Correction")) | U22: =IF($B22="","",IF($D22<>"Yes","",IF($Q22>=Settings!$C$13,"None",MID(IF(AND(G22<>"Accepted",G22<>"Not Needed",Settings!$C$15="Yes"),", "&G$1,"")&IF(AND(H22<>"Accepted",H22<>"Not Needed",Settings!$D$15="Yes"),", "&H$1,"")&IF(AND(I22<>"Accepted",I22<>"Not Needed",Settings!$E$15="Yes"),", "&I$1,"")&IF(AND(J22<>"Accepted",J22<>"Not Needed",Settings!$F$15="Yes"),", "&J$1,"")&IF(AND(K22<>"Accepted",K22<>"Not Needed",Settings!$G$15="Yes"),", "&K$1,"")&IF(AND(L22<>"Accepted",L22<>"Not Needed",Settings!$H$15="Yes"),", "&L$1,"")&IF(AND(M22<>"Accepted",M22<>"Not Needed",Settings!$I$15="Yes"),", "&M$1,"")&IF(AND(N22<>"Accepted",N22<>"Not Needed",Settings!$J$15="Yes"),", "&N$1,""),3,400))))
A23: 2026-27 | B23: Gross ES | C23: NES Elementary | D23: No | G23: Not Received | H23: Not Received | I23: Not Received | J23: Not Received | K23: Not Received | L23: Not Received | M23: Not Received | N23: Not Received | O23: =IF($B23="","",COUNTIF(G23:N23,"Accepted")+COUNTIF(G23:N23,"Received")+COUNTIF(G23:N23,"Needs Correction")) | P23: =IF($B23="","",SUMPRODUCT(((G23:N23="Accepted")+(G23:N23="Not Needed"))*(Settings!$C$11:$J$11="Yes"))) | Q23: =IF($B23="","",SUMPRODUCT(((G23:N23="Accepted")+(G23:N23="Not Needed"))*(Settings!$C$15:$J$15="Yes"))) | R23: =IF($B23="","",IF($D23="No","No PTO/PTA",IF($D23<>"Yes","Not Yet Confirmed",IF($Q23>=Settings!$C$13,"Legalized",IF($P23>=Settings!$C$12,"Registered",IF($O23>0,"In Progress","Not Started")))))) | S23: =IF($B23="","",COUNTIF(G23:N23,"Received")) | T23: =IF($B23="","",COUNTIF(G23:N23,"Needs Correction")) | U23: =IF($B23="","",IF($D23<>"Yes","",IF($Q23>=Settings!$C$13,"None",MID(IF(AND(G23<>"Accepted",G23<>"Not Needed",Settings!$C$15="Yes"),", "&G$1,"")&IF(AND(H23<>"Accepted",H23<>"Not Needed",Settings!$D$15="Yes"),", "&H$1,"")&IF(AND(I23<>"Accepted",I23<>"Not Needed",Settings!$E$15="Yes"),", "&I$1,"")&IF(AND(J23<>"Accepted",J23<>"Not Needed",Settings!$F$15="Yes"),", "&J$1,"")&IF(AND(K23<>"Accepted",K23<>"Not Needed",Settings!$G$15="Yes"),", "&K$1,"")&IF(AND(L23<>"Accepted",L23<>"Not Needed",Settings!$H$15="Yes"),", "&L$1,"")&IF(AND(M23<>"Accepted",M23<>"Not Needed",Settings!$I$15="Yes"),", "&M$1,"")&IF(AND(N23<>"Accepted",N23<>"Not Needed",Settings!$J$15="Yes"),", "&N$1,""),3,400))))
A24: 2026-27 | B24: Harris RP ES | C24: NES Elementary | D24: Not Yet Confirmed | G24: Not Received | H24: Not Received | I24: Not Received | J24: Not Received | K24: Not Received | L24: Not Received | M24: Not Received | N24: Not Received | O24: =IF($B24="","",COUNTIF(G24:N24,"Accepted")+COUNTIF(G24:N24,"Received")+COUNTIF(G24:N24,"Needs Correction")) | P24: =IF($B24="","",SUMPRODUCT(((G24:N24="Accepted")+(G24:N24="Not Needed"))*(Settings!$C$11:$J$11="Yes"))) | Q24: =IF($B24="","",SUMPRODUCT(((G24:N24="Accepted")+(G24:N24="Not Needed"))*(Settings!$C$15:$J$15="Yes"))) | R24: =IF($B24="","",IF($D24="No","No PTO/PTA",IF($D24<>"Yes","Not Yet Confirmed",IF($Q24>=Settings!$C$13,"Legalized",IF($P24>=Settings!$C$12,"Registered",IF($O24>0,"In Progress","Not Started")))))) | S24: =IF($B24="","",COUNTIF(G24:N24,"Received")) | T24: =IF($B24="","",COUNTIF(G24:N24,"Needs Correction")) | U24: =IF($B24="","",IF($D24<>"Yes","",IF($Q24>=Settings!$C$13,"None",MID(IF(AND(G24<>"Accepted",G24<>"Not Needed",Settings!$C$15="Yes"),", "&G$1,"")&IF(AND(H24<>"Accepted",H24<>"Not Needed",Settings!$D$15="Yes"),", "&H$1,"")&IF(AND(I24<>"Accepted",I24<>"Not Needed",Settings!$E$15="Yes"),", "&I$1,"")&IF(AND(J24<>"Accepted",J24<>"Not Needed",Settings!$F$15="Yes"),", "&J$1,"")&IF(AND(K24<>"Accepted",K24<>"Not Needed",Settings!$G$15="Yes"),", "&K$1,"")&IF(AND(L24<>"Accepted",L24<>"Not Needed",Settings!$H$15="Yes"),", "&L$1,"")&IF(AND(M24<>"Accepted",M24<>"Not Needed",Settings!$I$15="Yes"),", "&M$1,"")&IF(AND(N24<>"Accepted",N24<>"Not Needed",Settings!$J$15="Yes"),", "&N$1,""),3,400))))
A25: 2026-27 | B25: Hartsfield ES | C25: NES Elementary | D25: Not Yet Confirmed | G25: Not Received | H25: Not Received | I25: Not Received | J25: Not Received | K25: Not Received | L25: Not Received | M25: Not Received | N25: Not Received | O25: =IF($B25="","",COUNTIF(G25:N25,"Accepted")+COUNTIF(G25:N25,"Received")+COUNTIF(G25:N25,"Needs Correction")) | P25: =IF($B25="","",SUMPRODUCT(((G25:N25="Accepted")+(G25:N25="Not Needed"))*(Settings!$C$11:$J$11="Yes"))) | Q25: =IF($B25="","",SUMPRODUCT(((G25:N25="Accepted")+(G25:N25="Not Needed"))*(Settings!$C$15:$J$15="Yes"))) | R25: =IF($B25="","",IF($D25="No","No PTO/PTA",IF($D25<>"Yes","Not Yet Confirmed",IF($Q25>=Settings!$C$13,"Legalized",IF($P25>=Settings!$C$12,"Registered",IF($O25>0,"In Progress","Not Started")))))) | S25: =IF($B25="","",COUNTIF(G25:N25,"Received")) | T25: =IF($B25="","",COUNTIF(G25:N25,"Needs Correction")) | U25: =IF($B25="","",IF($D25<>"Yes","",IF($Q25>=Settings!$C$13,"None",MID(IF(AND(G25<>"Accepted",G25<>"Not Needed",Settings!$C$15="Yes"),", "&G$1,"")&IF(AND(H25<>"Accepted",H25<>"Not Needed",Settings!$D$15="Yes"),", "&H$1,"")&IF(AND(I25<>"Accepted",I25<>"Not Needed",Settings!$E$15="Yes"),", "&I$1,"")&IF(AND(J25<>"Accepted",J25<>"Not Needed",Settings!$F$15="Yes"),", "&J$1,"")&IF(AND(K25<>"Accepted",K25<>"Not Needed",Settings!$G$15="Yes"),", "&K$1,"")&IF(AND(L25<>"Accepted",L25<>"Not Needed",Settings!$H$15="Yes"),", "&L$1,"")&IF(AND(M25<>"Accepted",M25<>"Not Needed",Settings!$I$15="Yes"),", "&M$1,"")&IF(AND(N25<>"Accepted",N25<>"Not Needed",Settings!$J$15="Yes"),", "&N$1,""),3,400))))
... A28: 2026-27 | B28: Kennedy ES | C28: NES Elementary | D28: No | G28: Not Received | H28: Not Received | I28: Not Received | J28: Not Received | K28: Not Received | L28: Not Received | M28: Not Received | N28: Not Received | O28: =IF($B28="","",COUNTIF(G28:N28,"Accepted")+COUNTIF(G28:N28,"Received")+COUNTIF(G28:N28,"Needs Correction")) | P28: =IF($B28="","",SUMPRODUCT(((G28:N28="Accepted")+(G28:N28="Not Needed"))*(Settings!$C$11:$J$11="Yes"))) | Q28: =IF($B28="","",SUMPRODUCT(((G28:N28="Accepted")+(G28:N28="Not Needed"))*(Settings!$C$15:$J$15="Yes"))) | R28: =IF($B28="","",IF($D28="No","No PTO/PTA",IF($D28<>"Yes","Not Yet Confirmed",IF($Q28>=Settings!$C$13,"Legalized",IF($P28>=Settings!$C$12,"Registered",IF($O28>0,"In Progress","Not Started")))))) | S28: =IF($B28="","",COUNTIF(G28:N28,"Received")) | T28: =IF($B28="","",COUNTIF(G28:N28,"Needs Correction")) | U28: =IF($B28="","",IF($D28<>"Yes","",IF($Q28>=Settings!$C$13,"None",MID(IF(AND(G28<>"Accepted",G28<>"Not Needed",Settings!$C$15="Yes"),", "&G$1,"")&IF(AND(H28<>"Accepted",H28<>"Not Needed",Settings!$D$15="Yes"),", "&H$1,"")&IF(AND(I28<>"Accepted",I28<>"Not Needed",Settings!$E$15="Yes"),", "&I$1,"")&IF(AND(J28<>"Accepted",J28<>"Not Needed",Settings!$F$15="Yes"),", "&J$1,"")&IF(AND(K28<>"Accepted",K28<>"Not Needed",Settings!$G$15="Yes"),", "&K$1,"")&IF(AND(L28<>"Accepted",L28<>"Not Needed",Settings!$H$15="Yes"),", "&L$1,"")&IF(AND(M28<>"Accepted",M28<>"Not Needed",Settings!$I$15="Yes"),", "&M$1,"")&IF(AND(N28<>"Accepted",N28<>"Not Needed",Settings!$J$15="Yes"),", "&N$1,""),3,400))))
A29: 2026-27 | B29: Ketelsen ES | C29: NES Elementary | D29: Yes | E29: PTA | G29: Not Received | H29: Not Received | I29: Not Received | J29: Accepted | K29: Accepted | L29: Accepted | M29: Not Received | N29: Not Received | O29: =IF($B29="","",COUNTIF(G29:N29,"Accepted")+COUNTIF(G29:N29,"Received")+COUNTIF(G29:N29,"Needs Correction")) | P29: =IF($B29="","",SUMPRODUCT(((G29:N29="Accepted")+(G29:N29="Not Needed"))*(Settings!$C$11:$J$11="Yes"))) | Q29: =IF($B29="","",SUMPRODUCT(((G29:N29="Accepted")+(G29:N29="Not Needed"))*(Settings!$C$15:$J$15="Yes"))) | R29: =IF($B29="","",IF($D29="No","No PTO/PTA",IF($D29<>"Yes","Not Yet Confirmed",IF($Q29>=Settings!$C$13,"Legalized",IF($P29>=Settings!$C$12,"Registered",IF($O29>0,"In Progress","Not Started")))))) | S29: =IF($B29="","",COUNTIF(G29:N29,"Received")) | T29: =IF($B29="","",COUNTIF(G29:N29,"Needs Correction")) | U29: =IF($B29="","",IF($D29<>"Yes","",IF($Q29>=Settings!$C$13,"None",MID(IF(AND(G29<>"Accepted",G29<>"Not Needed",Settings!$C$15="Yes"),", "&G$1,"")&IF(AND(H29<>"Accepted",H29<>"Not Needed",Settings!$D$15="Yes"),", "&H$1,"")&IF(AND(I29<>"Accepted",I29<>"Not Needed",Settings!$E$15="Yes"),", "&I$1,"")&IF(AND(J29<>"Accepted",J29<>"Not Needed",Settings!$F$15="Yes"),", "&J$1,"")&IF(AND(K29<>"Accepted",K29<>"Not Needed",Settings!$G$15="Yes"),", "&K$1,"")&IF(AND(L29<>"Accepted",L29<>"Not Needed",Settings!$H$15="Yes"),", "&L$1,"")&IF(AND(M29<>"Accepted",M29<>"Not Needed",Settings!$I$15="Yes"),", "&M$1,"")&IF(AND(N29<>"Accepted",N29<>"Not Needed",Settings!$J$15="Yes"),", "&N$1,""),3,400))))
A30: 2026-27 | B30: Lockhart ES | C30: NES Elementary | D30: Not Yet Confirmed | G30: Not Received | H30: Not Received | I30: Not Received | J30: Not Received | K30: Not Received | L30: Not Received | M30: Not Received | N30: Not Received | O30: =IF($B30="","",COUNTIF(G30:N30,"Accepted")+COUNTIF(G30:N30,"Received")+COUNTIF(G30:N30,"Needs Correction")) | P30: =IF($B30="","",SUMPRODUCT(((G30:N30="Accepted")+(G30:N30="Not Needed"))*(Settings!$C$11:$J$11="Yes"))) | Q30: =IF($B30="","",SUMPRODUCT(((G30:N30="Accepted")+(G30:N30="Not Needed"))*(Settings!$C$15:$J$15="Yes"))) | R30: =IF($B30="","",IF($D30="No","No PTO/PTA",IF($D30<>"Yes","Not Yet Confirmed",IF($Q30>=Settings!$C$13,"Legalized",IF($P30>=Settings!$C$12,"Registered",IF($O30>0,"In Progress","Not Started")))))) | S30: =IF($B30="","",COUNTIF(G30:N30,"Received")) | T30: =IF($B30="","",COUNTIF(G30:N30,"Needs Correction")) | U30: =IF($B30="","",IF($D30<>"Yes","",IF($Q30>=Settings!$C$13,"None",MID(IF(AND(G30<>"Accepted",G30<>"Not Needed",Settings!$C$15="Yes"),", "&G$1,"")&IF(AND(H30<>"Accepted",H30<>"Not Needed",Settings!$D$15="Yes"),", "&H$1,"")&IF(AND(I30<>"Accepted",I30<>"Not Needed",Settings!$E$15="Yes"),", "&I$1,"")&IF(AND(J30<>"Accepted",J30<>"Not Needed",Settings!$F$15="Yes"),", "&J$1,"")&IF(AND(K30<>"Accepted",K30<>"Not Needed",Settings!$G$15="Yes"),", "&K$1,"")&IF(AND(L30<>"Accepted",L30<>"Not Needed",Settings!$H$15="Yes"),", "&L$1,"")&IF(AND(M30<>"Accepted",M30<>"Not Needed",Settings!$I$15="Yes"),", "&M$1,"")&IF(AND(N30<>"Accepted",N30<>"Not Needed",Settings!$J$15="Yes"),", "&N$1,""),3,400))))
A31: 2026-27 | B31: Longfellow ES | C31: NES Elementary | D31: Not Yet Confirmed | G31: Not Received | H31: Not Received | I31: Not Received | J31: Not Received | K31: Not Received | L31: Not Received | M31: Not Received | N31: Not Received | O31: =IF($B31="","",COUNTIF(G31:N31,"Accepted")+COUNTIF(G31:N31,"Received")+COUNTIF(G31:N31,"Needs Correction")) | P31: =IF($B31="","",SUMPRODUCT(((G31:N31="Accepted")+(G31:N31="Not Needed"))*(Settings!$C$11:$J$11="Yes"))) | Q31: =IF($B31="","",SUMPRODUCT(((G31:N31="Accepted")+(G31:N31="Not Needed"))*(Settings!$C$15:$J$15="Yes"))) | R31: =IF($B31="","",IF($D31="No","No PTO/PTA",IF($D31<>"Yes","Not Yet Confirmed",IF($Q31>=Settings!$C$13,"Legalized",IF($P31>=Settings!$C$12,"Registered",IF($O31>0,"In Progress","Not Started")))))) | S31: =IF($B31="","",COUNTIF(G31:N31,"Received")) | T31: =IF($B31="","",COUNTIF(G31:N31,"Needs Correction")) | U31: =IF($B31="","",IF($D31<>"Yes","",IF($Q31>=Settings!$C$13,"None",MID(IF(AND(G31<>"Accepted",G31<>"Not Needed",Settings!$C$15="Yes"),", "&G$1,"")&IF(AND(H31<>"Accepted",H31<>"Not Needed",Settings!$D$15="Yes"),", "&H$1,"")&IF(AND(I31<>"Accepted",I31<>"Not Needed",Settings!$E$15="Yes"),", "&I$1,"")&IF(AND(J31<>"Accepted",J31<>"Not Needed",Settings!$F$15="Yes"),", "&J$1,"")&IF(AND(K31<>"Accepted",K31<>"Not Needed",Settings!$G$15="Yes"),", "&K$1,"")&IF(AND(L31<>"Accepted",L31<>"Not Needed",Settings!$H$15="Yes"),", "&L$1,"")&IF(AND(M31<>"Accepted",M31<>"Not Needed",Settings!$I$15="Yes"),", "&M$1,"")&IF(AND(N31<>"Accepted",N31<>"Not Needed",Settings!$J$15="Yes"),", "&N$1,""),3,400))))
A32: 2026-27 | B32: Martinez R ES | C32: NES Elementary | D32: Not Yet Confirmed | G32: Not Received | H32: Not Received | I32: Not Received | J32: Not Received | K32: Not Received | L32: Not Received | M32: Not Received | N32: Not Received | O32: =IF($B32="","",COUNTIF(G32:N32,"Accepted")+COUNTIF(G32:N32,"Received")+COUNTIF(G32:N32,"Needs Correction")) | P32: =IF($B32="","",SUMPRODUCT(((G32:N32="Accepted")+(G32:N32="Not Needed"))*(Settings!$C$11:$J$11="Yes"))) | Q32: =IF($B32="","",SUMPRODUCT(((G32:N32="Accepted")+(G32:N32="Not Needed"))*(Settings!$C$15:$J$15="Yes"))) | R32: =IF($B32="","",IF($D32="No","No PTO/PTA",IF($D32<>"Yes","Not Yet Confirmed",IF($Q32>=Settings!$C$13,"Legalized",IF($P32>=Settings!$C$12,"Registered",IF($O32>0,"In Progress","Not Started")))))) | S32: =IF($B32="","",COUNTIF(G32:N32,"Received")) | T32: =IF($B32="","",COUNTIF(G32:N32,"Needs Correction")) | U32: =IF($B32="","",IF($D32<>"Yes","",IF($Q32>=Settings!$C$13,"None",MID(IF(AND(G32<>"Accepted",G32<>"Not Needed",Settings!$C$15="Yes"),", "&G$1,"")&IF(AND(H32<>"Accepted",H32<>"Not Needed",Settings!$D$15="Yes"),", "&H$1,"")&IF(AND(I32<>"Accepted",I32<>"Not Needed",Settings!$E$15="Yes"),", "&I$1,"")&IF(AND(J32<>"Accepted",J32<>"Not Needed",Settings!$F$15="Yes"),", "&J$1,"")&IF(AND(K32<>"Accepted",K32<>"Not Needed",Settings!$G$15="Yes"),", "&K$1,"")&IF(AND(L32<>"Accepted",L32<>"Not Needed",Settings!$H$15="Yes"),", "&L$1,"")&IF(AND(M32<>"Accepted",M32<>"Not Needed",Settings!$I$15="Yes"),", "&M$1,"")&IF(AND(N32<>"Accepted",N32<>"Not Needed",Settings!$J$15="Yes"),", "&N$1,""),3,400))))
A33: 2026-27 | B33: Mitchell ES | C33: NES Elementary | D33: Not Yet Confirmed | G33: Not Received | H33: Not Received | I33: Not Received | J33: Not Received | K33: Not Received | L33: Not Received | M33: Not Received | N33: Not Received | O33: =IF($B33="","",COUNTIF(G33:N33,"Accepted")+COUNTIF(G33:N33,"Received")+COUNTIF(G33:N33,"Needs Correction")) | P33: =IF($B33="","",SUMPRODUCT(((G33:N33="Accepted")+(G33:N33="Not Needed"))*(Settings!$C$11:$J$11="Yes"))) | Q33: =IF($B33="","",SUMPRODUCT(((G33:N33="Accepted")+(G33:N33="Not Needed"))*(Settings!$C$15:$J$15="Yes"))) | R33: =IF($B33="","",IF($D33="No","No PTO/PTA",IF($D33<>"Yes","Not Yet Confirmed",IF($Q33>=Settings!$C$13,"Legalized",IF($P33>=Settings!$C$12,"Registered",IF($O33>0,"In Progress","Not Started")))))) | S33: =IF($B33="","",COUNTIF(G33:N33,"Received")) | T33: =IF($B33="","",COUNTIF(G33:N33,"Needs Correction")) | U33: =IF($B33="","",IF($D33<>"Yes","",IF($Q33>=Settings!$C$13,"None",MID(IF(AND(G33<>"Accepted",G33<>"Not Needed",Settings!$C$15="Yes"),", "&G$1,"")&IF(AND(H33<>"Accepted",H33<>"Not Needed",Settings!$D$15="Yes"),", "&H$1,"")&IF(AND(I33<>"Accepted",I33<>"Not Needed",Settings!$E$15="Yes"),", "&I$1,"")&IF(AND(J33<>"Accepted",J33<>"Not Needed",Settings!$F$15="Yes"),", "&J$1,"")&IF(AND(K33<>"Accepted",K33<>"Not Needed",Settings!$G$15="Yes"),", "&K$1,"")&IF(AND(L33<>"Accepted",L33<>"Not Needed",Settings!$H$15="Yes"),", "&L$1,"")&IF(AND(M33<>"Accepted",M33<>"Not Needed",Settings!$I$15="Yes"),", "&M$1,"")&IF(AND(N33<>"Accepted",N33<>"Not Needed",Settings!$J$15="Yes"),", "&N$1,""),3,400))))
A34: 2026-27 | B34: Oates ES | C34: NES Elementary | D34: Not Yet Confirmed | G34: Not Received | H34: Not Received | I34: Not Received | J34: Not Received | K34: Not Received | L34: Not Received | M34: Not Received | N34: Not Received | O34: =IF($B34="","",COUNTIF(G34:N34,"Accepted")+COUNTIF(G34:N34,"Received")+COUNTIF(G34:N34,"Needs Correction")) | P34: =IF($B34="","",SUMPRODUCT(((G34:N34="Accepted")+(G34:N34="Not Needed"))*(Settings!$C$11:$J$11="Yes"))) | Q34: =IF($B34="","",SUMPRODUCT(((G34:N34="Accepted")+(G34:N34="Not Needed"))*(Settings!$C$15:$J$15="Yes"))) | R34: =IF($B34="","",IF($D34="No","No PTO/PTA",IF($D34<>"Yes","Not Yet Confirmed",IF($Q34>=Settings!$C$13,"Legalized",IF($P34>=Settings!$C$12,"Registered",IF($O34>0,"In Progress","Not Started")))))) | S34: =IF($B34="","",COUNTIF(G34:N34,"Received")) | T34: =IF($B34="","",COUNTIF(G34:N34,"Needs Correction")) | U34: =IF($B34="","",IF($D34<>"Yes","",IF($Q34>=Settings!$C$13,"None",MID(IF(AND(G34<>"Accepted",G34<>"Not Needed",Settings!$C$15="Yes"),", "&G$1,"")&IF(AND(H34<>"Accepted",H34<>"Not Needed",Settings!$D$15="Yes"),", "&H$1,"")&IF(AND(I34<>"Accepted",I34<>"Not Needed",Settings!$E$15="Yes"),", "&I$1,"")&IF(AND(J34<>"Accepted",J34<>"Not Needed",Settings!$F$15="Yes"),", "&J$1,"")&IF(AND(K34<>"Accepted",K34<>"Not Needed",Settings!$G$15="Yes"),", "&K$1,"")&IF(AND(L34<>"Accepted",L34<>"Not Needed",Settings!$H$15="Yes"),", "&L$1,"")&IF(AND(M34<>"Accepted",M34<>"Not Needed",Settings!$I$15="Yes"),", "&M$1,"")&IF(AND(N34<>"Accepted",N34<>"Not Needed",Settings!$J$15="Yes"),", "&N$1,""),3,400))))
A35: 2026-27 | B35: Osborne ES | C35: NES Elementary | D35: No | G35: Not Received | H35: Not Received | I35: Not Received | J35: Not Received | K35: Not Received | L35: Not Received | M35: Not Received | N35: Not Received | O35: =IF($B35="","",COUNTIF(G35:N35,"Accepted")+COUNTIF(G35:N35,"Received")+COUNTIF(G35:N35,"Needs Correction")) | P35: =IF($B35="","",SUMPRODUCT(((G35:N35="Accepted")+(G35:N35="Not Needed"))*(Settings!$C$11:$J$11="Yes"))) | Q35: =IF($B35="","",SUMPRODUCT(((G35:N35="Accepted")+(G35:N35="Not Needed"))*(Settings!$C$15:$J$15="Yes"))) | R35: =IF($B35="","",IF($D35="No","No PTO/PTA",IF($D35<>"Yes","Not Yet Confirmed",IF($Q35>=Settings!$C$13,"Legalized",IF($P35>=Settings!$C$12,"Registered",IF($O35>0,"In Progress","Not Started")))))) | S35: =IF($B35="","",COUNTIF(G35:N35,"Received")) | T35: =IF($B35="","",COUNTIF(G35:N35,"Needs Correction")) | U35: =IF($B35="","",IF($D35<>"Yes","",IF($Q35>=Settings!$C$13,"None",MID(IF(AND(G35<>"Accepted",G35<>"Not Needed",Settings!$C$15="Yes"),", "&G$1,"")&IF(AND(H35<>"Accepted",H35<>"Not Needed",Settings!$D$15="Yes"),", "&H$1,"")&IF(AND(I35<>"Accepted",I35<>"Not Needed",Settings!$E$15="Yes"),", "&I$1,"")&IF(AND(J35<>"Accepted",J35<>"Not Needed",Settings!$F$15="Yes"),", "&J$1,"")&IF(AND(K35<>"Accepted",K35<>"Not Needed",Settings!$G$15="Yes"),", "&K$1,"")&IF(AND(L35<>"Accepted",L35<>"Not Needed",Settings!$H$15="Yes"),", "&L$1,"")&IF(AND(M35<>"Accepted",M35<>"Not Needed",Settings!$I$15="Yes"),", "&M$1,"")&IF(AND(N35<>"Accepted",N35<>"Not Needed",Settings!$J$15="Yes"),", "&N$1,""),3,400))))
A36: 2026-27 | B36: Peck ES | C36: NES Elementary | D36: Not Yet Confirmed | G36: Not Received | H36: Not Received | I36: Not Received | J36: Not Received | K36: Not Received | L36: Not Received | M36: Not Received | N36: Not Received | O36: =IF($B36="","",COUNTIF(G36:N36,"Accepted")+COUNTIF(G36:N36,"Received")+COUNTIF(G36:N36,"Needs Correction")) | P36: =IF($B36="","",SUMPRODUCT(((G36:N36="Accepted")+(G36:N36="Not Needed"))*(Settings!$C$11:$J$11="Yes"))) | Q36: =IF($B36="","",SUMPRODUCT(((G36:N36="Accepted")+(G36:N36="Not Needed"))*(Settings!$C$15:$J$15="Yes"))) | R36: =IF($B36="","",IF($D36="No","No PTO/PTA",IF($D36<>"Yes","Not Yet Confirmed",IF($Q36>=Settings!$C$13,"Legalized",IF($P36>=Settings!$C$12,"Registered",IF($O36>0,"In Progress","Not Started")))))) | S36: =IF($B36="","",COUNTIF(G36:N36,"Received")) | T36: =IF($B36="","",COUNTIF(G36:N36,"Needs Correction")) | U36: =IF($B36="","",IF($D36<>"Yes","",IF($Q36>=Settings!$C$13,"None",MID(IF(AND(G36<>"Accepted",G36<>"Not Needed",Settings!$C$15="Yes"),", "&G$1,"")&IF(AND(H36<>"Accepted",H36<>"Not Needed",Settings!$D$15="Yes"),", "&H$1,"")&IF(AND(I36<>"Accepted",I36<>"Not Needed",Settings!$E$15="Yes"),", "&I$1,"")&IF(AND(J36<>"Accepted",J36<>"Not Needed",Settings!$F$15="Yes"),", "&J$1,"")&IF(AND(K36<>"Accepted",K36<>"Not Needed",Settings!$G$15="Yes"),", "&K$1,"")&IF(AND(L36<>"Accepted",L36<>"Not Needed",Settings!$H$15="Yes"),", "&L$1,"")&IF(AND(M36<>"Accepted",M36<>"Not Needed",Settings!$I$15="Yes"),", "&M$1,"")&IF(AND(N36<>"Accepted",N36<>"Not Needed",Settings!$J$15="Yes"),", "&N$1,""),3,400))))
A37: 2026-27 | B37: Rucker ES | C37: NES Elementary | D37: Not Yet Confirmed | G37: Not Received | H37: Not Received | I37: Not Received | J37: Not Received | K37: Not Received | L37: Not Received | M37: Not Received | N37: Not Received | O37: =IF($B37="","",COUNTIF(G37:N37,"Accepted")+COUNTIF(G37:N37,"Received")+COUNTIF(G37:N37,"Needs Correction")) | P37: =IF($B37="","",SUMPRODUCT(((G37:N37="Accepted")+(G37:N37="Not Needed"))*(Settings!$C$11:$J$11="Yes"))) | Q37: =IF($B37="","",SUMPRODUCT(((G37:N37="Accepted")+(G37:N37="Not Needed"))*(Settings!$C$15:$J$15="Yes"))) | R37: =IF($B37="","",IF($D37="No","No PTO/PTA",IF($D37<>"Yes","Not Yet Confirmed",IF($Q37>=Settings!$C$13,"Legalized",IF($P37>=Settings!$C$12,"Registered",IF($O37>0,"In Progress","Not Started")))))) | S37: =IF($B37="","",COUNTIF(G37:N37,"Received")) | T37: =IF($B37="","",COUNTIF(G37:N37,"Needs Correction")) | U37: =IF($B37="","",IF($D37<>"Yes","",IF($Q37>=Settings!$C$13,"None",MID(IF(AND(G37<>"Accepted",G37<>"Not Needed",Settings!$C$15="Yes"),", "&G$1,"")&IF(AND(H37<>"Accepted",H37<>"Not Needed",Settings!$D$15="Yes"),", "&H$1,"")&IF(AND(I37<>"Accepted",I37<>"Not Needed",Settings!$E$15="Yes"),", "&I$1,"")&IF(AND(J37<>"Accepted",J37<>"Not Needed",Settings!$F$15="Yes"),", "&J$1,"")&IF(AND(K37<>"Accepted",K37<>"Not Needed",Settings!$G$15="Yes"),", "&K$1,"")&IF(AND(L37<>"Accepted",L37<>"Not Needed",Settings!$H$15="Yes"),", "&L$1,"")&IF(AND(M37<>"Accepted",M37<>"Not Needed",Settings!$I$15="Yes"),", "&M$1,"")&IF(AND(N37<>"Accepted",N37<>"Not Needed",Settings!$J$15="Yes"),", "&N$1,""),3,400))))
A38: 2026-27 | B38: Seguin ES | C38: NES Elementary | D38: Not Yet Confirmed | G38: Not Received | H38: Not Received | I38: Not Received | J38: Not Received | K38: Not Received | L38: Not Received | M38: Not Received | N38: Not Received | O38: =IF($B38="","",COUNTIF(G38:N38,"Accepted")+COUNTIF(G38:N38,"Received")+COUNTIF(G38:N38,"Needs Correction")) | P38: =IF($B38="","",SUMPRODUCT(((G38:N38="Accepted")+(G38:N38="Not Needed"))*(Settings!$C$11:$J$11="Yes"))) | Q38: =IF($B38="","",SUMPRODUCT(((G38:N38="Accepted")+(G38:N38="Not Needed"))*(Settings!$C$15:$J$15="Yes"))) | R38: =IF($B38="","",IF($D38="No","No PTO/PTA",IF($D38<>"Yes","Not Yet Confirmed",IF($Q38>=Settings!$C$13,"Legalized",IF($P38>=Settings!$C$12,"Registered",IF($O38>0,"In Progress","Not Started")))))) | S38: =IF($B38="","",COUNTIF(G38:N38,"Received")) | T38: =IF($B38="","",COUNTIF(G38:N38,"Needs Correction")) | U38: =IF($B38="","",IF($D38<>"Yes","",IF($Q38>=Settings!$C$13,"None",MID(IF(AND(G38<>"Accepted",G38<>"Not Needed",Settings!$C$15="Yes"),", "&G$1,"")&IF(AND(H38<>"Accepted",H38<>"Not Needed",Settings!$D$15="Yes"),", "&H$1,"")&IF(AND(I38<>"Accepted",I38<>"Not Needed",Settings!$E$15="Yes"),", "&I$1,"")&IF(AND(J38<>"Accepted",J38<>"Not Needed",Settings!$F$15="Yes"),", "&J$1,"")&IF(AND(K38<>"Accepted",K38<>"Not Needed",Settings!$G$15="Yes"),", "&K$1,"")&IF(AND(L38<>"Accepted",L38<>"Not Needed",Settings!$H$15="Yes"),", "&L$1,"")&IF(AND(M38<>"Accepted",M38<>"Not Needed",Settings!$I$15="Yes"),", "&M$1,"")&IF(AND(N38<>"Accepted",N38<>"Not Needed",Settings!$J$15="Yes"),", "&N$1,""),3,400))))
A39: 2026-27 | B39: Stevens ES | C39: NES Elementary | D39: Not Yet Confirmed | G39: Not Received | H39: Not Received | I39: Not Received | J39: Not Received | K39: Not Received | L39: Not Received | M39: Not Received | N39: Not Received | O39: =IF($B39="","",COUNTIF(G39:N39,"Accepted")+COUNTIF(G39:N39,"Received")+COUNTIF(G39:N39,"Needs Correction")) | P39: =IF($B39="","",SUMPRODUCT(((G39:N39="Accepted")+(G39:N39="Not Needed"))*(Settings!$C$11:$J$11="Yes"))) | Q39: =IF($B39="","",SUMPRODUCT(((G39:N39="Accepted")+(G39:N39="Not Needed"))*(Settings!$C$15:$J$15="Yes"))) | R39: =IF($B39="","",IF($D39="No","No PTO/PTA",IF($D39<>"Yes","Not Yet Confirmed",IF($Q39>=Settings!$C$13,"Legalized",IF($P39>=Settings!$C$12,"Registered",IF($O39>0,"In Progress","Not Started")))))) | S39: =IF($B39="","",COUNTIF(G39:N39,"Received")) | T39: =IF($B39="","",COUNTIF(G39:N39,"Needs Correction")) | U39: =IF($B39="","",IF($D39<>"Yes","",IF($Q39>=Settings!$C$13,"None",MID(IF(AND(G39<>"Accepted",G39<>"Not Needed",Settings!$C$15="Yes"),", "&G$1,"")&IF(AND(H39<>"Accepted",H39<>"Not Needed",Settings!$D$15="Yes"),", "&H$1,"")&IF(AND(I39<>"Accepted",I39<>"Not Needed",Settings!$E$15="Yes"),", "&I$1,"")&IF(AND(J39<>"Accepted",J39<>"Not Needed",Settings!$F$15="Yes"),", "&J$1,"")&IF(AND(K39<>"Accepted",K39<>"Not Needed",Settings!$G$15="Yes"),", "&K$1,"")&IF(AND(L39<>"Accepted",L39<>"Not Needed",Settings!$H$15="Yes"),", "&L$1,"")&IF(AND(M39<>"Accepted",M39<>"Not Needed",Settings!$I$15="Yes"),", "&M$1,"")&IF(AND(N39<>"Accepted",N39<>"Not Needed",Settings!$J$15="Yes"),", "&N$1,""),3,400))))
A40: 2026-27 | B40: Walnut Bend ES | C40: NES Elementary | D40: Not Yet Confirmed | G40: Not Received | H40: Not Received | I40: Not Received | J40: Not Received | K40: Not Received | L40: Not Received | M40: Not Received | N40: Not Received | O40: =IF($B40="","",COUNTIF(G40:N40,"Accepted")+COUNTIF(G40:N40,"Received")+COUNTIF(G40:N40,"Needs Correction")) | P40: =IF($B40="","",SUMPRODUCT(((G40:N40="Accepted")+(G40:N40="Not Needed"))*(Settings!$C$11:$J$11="Yes"))) | Q40: =IF($B40="","",SUMPRODUCT(((G40:N40="Accepted")+(G40:N40="Not Needed"))*(Settings!$C$15:$J$15="Yes"))) | R40: =IF($B40="","",IF($D40="No","No PTO/PTA",IF($D40<>"Yes","Not Yet Confirmed",IF($Q40>=Settings!$C$13,"Legalized",IF($P40>=Settings!$C$12,"Registered",IF($O40>0,"In Progress","Not Started")))))) | S40: =IF($B40="","",COUNTIF(G40:N40,"Received")) | T40: =IF($B40="","",COUNTIF(G40:N40,"Needs Correction")) | U40: =IF($B40="","",IF($D40<>"Yes","",IF($Q40>=Settings!$C$13,"None",MID(IF(AND(G40<>"Accepted",G40<>"Not Needed",Settings!$C$15="Yes"),", "&G$1,"")&IF(AND(H40<>"Accepted",H40<>"Not Needed",Settings!$D$15="Yes"),", "&H$1,"")&IF(AND(I40<>"Accepted",I40<>"Not Needed",Settings!$E$15="Yes"),", "&I$1,"")&IF(AND(J40<>"Accepted",J40<>"Not Needed",Settings!$F$15="Yes"),", "&J$1,"")&IF(AND(K40<>"Accepted",K40<>"Not Needed",Settings!$G$15="Yes"),", "&K$1,"")&IF(AND(L40<>"Accepted",L40<>"Not Needed",Settings!$H$15="Yes"),", "&L$1,"")&IF(AND(M40<>"Accepted",M40<>"Not Needed",Settings!$I$15="Yes"),", "&M$1,"")&IF(AND(N40<>"Accepted",N40<>"Not Needed",Settings!$J$15="Yes"),", "&N$1,""),3,400))))
A41: 2026-27 | B41: Woodson | C41: NES Elementary | D41: Not Yet Confirmed | G41: Not Received | H41: Not Received | I41: Not Received | J41: Not Received | K41: Not Received | L41: Not Received | M41: Not Received | N41: Not Received | O41: =IF($B41="","",COUNTIF(G41:N41,"Accepted")+COUNTIF(G41:N41,"Received")+COUNTIF(G41:N41,"Needs Correction")) | P41: =IF($B41="","",SUMPRODUCT(((G41:N41="Accepted")+(G41:N41="Not Needed"))*(Settings!$C$11:$J$11="Yes"))) | Q41: =IF($B41="","",SUMPRODUCT(((G41:N41="Accepted")+(G41:N41="Not Needed"))*(Settings!$C$15:$J$15="Yes"))) | R41: =IF($B41="","",IF($D41="No","No PTO/PTA",IF($D41<>"Yes","Not Yet Confirmed",IF($Q41>=Settings!$C$13,"Legalized",IF($P41>=Settings!$C$12,"Registered",IF($O41>0,"In Progress","Not Started")))))) | S41: =IF($B41="","",COUNTIF(G41:N41,"Received")) | T41: =IF($B41="","",COUNTIF(G41:N41,"Needs Correction")) | U41: =IF($B41="","",IF($D41<>"Yes","",IF($Q41>=Settings!$C$13,"None",MID(IF(AND(G41<>"Accepted",G41<>"Not Needed",Settings!$C$15="Yes"),", "&G$1,"")&IF(AND(H41<>"Accepted",H41<>"Not Needed",Settings!$D$15="Yes"),", "&H$1,"")&IF(AND(I41<>"Accepted",I41<>"Not Needed",Settings!$E$15="Yes"),", "&I$1,"")&IF(AND(J41<>"Accepted",J41<>"Not Needed",Settings!$F$15="Yes"),", "&J$1,"")&IF(AND(K41<>"Accepted",K41<>"Not Needed",Settings!$G$15="Yes"),", "&K$1,"")&IF(AND(L41<>"Accepted",L41<>"Not Needed",Settings!$H$15="Yes"),", "&L$1,"")&IF(AND(M41<>"Accepted",M41<>"Not Needed",Settings!$I$15="Yes"),", "&M$1,"")&IF(AND(N41<>"Accepted",N41<>"Not Needed",Settings!$J$15="Yes"),", "&N$1,""),3,400))))
... A68: 2026-27 | B68: DeAnda ES | C68: EAS Elementary | D68: Not Yet Confirmed | G68: Not Received | H68: Not Received | I68: Not Received | J68: Not Received | K68: Not Received | L68: Not Received | M68: Not Received | N68: Not Received | O68: =IF($B68="","",COUNTIF(G68:N68,"Accepted")+COUNTIF(G68:N68,"Received")+COUNTIF(G68:N68,"Needs Correction")) | P68: =IF($B68="","",SUMPRODUCT(((G68:N68="Accepted")+(G68:N68="Not Needed"))*(Settings!$C$11:$J$11="Yes"))) | Q68: =IF($B68="","",SUMPRODUCT(((G68:N68="Accepted")+(G68:N68="Not Needed"))*(Settings!$C$15:$J$15="Yes"))) | R68: =IF($B68="","",IF($D68="No","No PTO/PTA",IF($D68<>"Yes","Not Yet Confirmed",IF($Q68>=Settings!$C$13,"Legalized",IF($P68>=Settings!$C$12,"Registered",IF($O68>0,"In Progress","Not Started")))))) | S68: =IF($B68="","",COUNTIF(G68:N68,"Received")) | T68: =IF($B68="","",COUNTIF(G68:N68,"Needs Correction")) | U68: =IF($B68="","",IF($D68<>"Yes","",IF($Q68>=Settings!$C$13,"None",MID(IF(AND(G68<>"Accepted",G68<>"Not Needed",Settings!$C$15="Yes"),", "&G$1,"")&IF(AND(H68<>"Accepted",H68<>"Not Needed",Settings!$D$15="Yes"),", "&H$1,"")&IF(AND(I68<>"Accepted",I68<>"Not Needed",Settings!$E$15="Yes"),", "&I$1,"")&IF(AND(J68<>"Accepted",J68<>"Not Needed",Settings!$F$15="Yes"),", "&J$1,"")&IF(AND(K68<>"Accepted",K68<>"Not Needed",Settings!$G$15="Yes"),", "&K$1,"")&IF(AND(L68<>"Accepted",L68<>"Not Needed",Settings!$H$15="Yes"),", "&L$1,"")&IF(AND(M68<>"Accepted",M68<>"Not Needed",Settings!$I$15="Yes"),", "&M$1,"")&IF(AND(N68<>"Accepted",N68<>"Not Needed",Settings!$J$15="Yes"),", "&N$1,""),3,400))))
A69: 2026-27 | B69: Durham ES | C69: EAS Elementary | D69: Yes | E69: PTA | G69: Accepted | H69: Not Received | I69: Not Received | J69: Accepted | K69: Accepted | L69: Accepted | M69: Not Received | N69: Not Received | O69: =IF($B69="","",COUNTIF(G69:N69,"Accepted")+COUNTIF(G69:N69,"Received")+COUNTIF(G69:N69,"Needs Correction")) | P69: =IF($B69="","",SUMPRODUCT(((G69:N69="Accepted")+(G69:N69="Not Needed"))*(Settings!$C$11:$J$11="Yes"))) | Q69: =IF($B69="","",SUMPRODUCT(((G69:N69="Accepted")+(G69:N69="Not Needed"))*(Settings!$C$15:$J$15="Yes"))) | R69: =IF($B69="","",IF($D69="No","No PTO/PTA",IF($D69<>"Yes","Not Yet Confirmed",IF($Q69>=Settings!$C$13,"Legalized",IF($P69>=Settings!$C$12,"Registered",IF($O69>0,"In Progress","Not Started")))))) | S69: =IF($B69="","",COUNTIF(G69:N69,"Received")) | T69: =IF($B69="","",COUNTIF(G69:N69,"Needs Correction")) | U69: =IF($B69="","",IF($D69<>"Yes","",IF($Q69>=Settings!$C$13,"None",MID(IF(AND(G69<>"Accepted",G69<>"Not Needed",Settings!$C$15="Yes"),", "&G$1,"")&IF(AND(H69<>"Accepted",H69<>"Not Needed",Settings!$D$15="Yes"),", "&H$1,"")&IF(AND(I69<>"Accepted",I69<>"Not Needed",Settings!$E$15="Yes"),", "&I$1,"")&IF(AND(J69<>"Accepted",J69<>"Not Needed",Settings!$F$15="Yes"),", "&J$1,"")&IF(AND(K69<>"Accepted",K69<>"Not Needed",Settings!$G$15="Yes"),", "&K$1,"")&IF(AND(L69<>"Accepted",L69<>"Not Needed",Settings!$H$15="Yes"),", "&L$1,"")&IF(AND(M69<>"Accepted",M69<>"Not Needed",Settings!$I$15="Yes"),", "&M$1,"")&IF(AND(N69<>"Accepted",N69<>"Not Needed",Settings!$J$15="Yes"),", "&N$1,""),3,400))))
A70: 2026-27 | B70: Elrod ES | C70: EAS Elementary | D70: Not Yet Confirmed | G70: Not Received | H70: Not Received | I70: Not Received | J70: Not Received | K70: Not Received | L70: Not Received | M70: Not Received | N70: Not Received | O70: =IF($B70="","",COUNTIF(G70:N70,"Accepted")+COUNTIF(G70:N70,"Received")+COUNTIF(G70:N70,"Needs Correction")) | P70: =IF($B70="","",SUMPRODUCT(((G70:N70="Accepted")+(G70:N70="Not Needed"))*(Settings!$C$11:$J$11="Yes"))) | Q70: =IF($B70="","",SUMPRODUCT(((G70:N70="Accepted")+(G70:N70="Not Needed"))*(Settings!$C$15:$J$15="Yes"))) | R70: =IF($B70="","",IF($D70="No","No PTO/PTA",IF($D70<>"Yes","Not Yet Confirmed",IF($Q70>=Settings!$C$13,"Legalized",IF($P70>=Settings!$C$12,"Registered",IF($O70>0,"In Progress","Not Started")))))) | S70: =IF($B70="","",COUNTIF(G70:N70,"Received")) | T70: =IF($B70="","",COUNTIF(G70:N70,"Needs Correction")) | U70: =IF($B70="","",IF($D70<>"Yes","",IF($Q70>=Settings!$C$13,"None",MID(IF(AND(G70<>"Accepted",G70<>"Not Needed",Settings!$C$15="Yes"),", "&G$1,"")&IF(AND(H70<>"Accepted",H70<>"Not Needed",Settings!$D$15="Yes"),", "&H$1,"")&IF(AND(I70<>"Accepted",I70<>"Not Needed",Settings!$E$15="Yes"),", "&I$1,"")&IF(AND(J70<>"Accepted",J70<>"Not Needed",Settings!$F$15="Yes"),", "&J$1,"")&IF(AND(K70<>"Accepted",K70<>"Not Needed",Settings!$G$15="Yes"),", "&K$1,"")&IF(AND(L70<>"Accepted",L70<>"Not Needed",Settings!$H$15="Yes"),", "&L$1,"")&IF(AND(M70<>"Accepted",M70<>"Not Needed",Settings!$I$15="Yes"),", "&M$1,"")&IF(AND(N70<>"Accepted",N70<>"Not Needed",Settings!$J$15="Yes"),", "&N$1,""),3,400))))
A71: 2026-27 | B71: Emerson ES | C71: EAS Elementary | D71: Not Yet Confirmed | G71: Not Received | H71: Not Received | I71: Not Received | J71: Not Received | K71: Not Received | L71: Not Received | M71: Not Received | N71: Not Received | O71: =IF($B71="","",COUNTIF(G71:N71,"Accepted")+COUNTIF(G71:N71,"Received")+COUNTIF(G71:N71,"Needs Correction")) | P71: =IF($B71="","",SUMPRODUCT(((G71:N71="Accepted")+(G71:N71="Not Needed"))*(Settings!$C$11:$J$11="Yes"))) | Q71: =IF($B71="","",SUMPRODUCT(((G71:N71="Accepted")+(G71:N71="Not Needed"))*(Settings!$C$15:$J$15="Yes"))) | R71: =IF($B71="","",IF($D71="No","No PTO/PTA",IF($D71<>"Yes","Not Yet Confirmed",IF($Q71>=Settings!$C$13,"Legalized",IF($P71>=Settings!$C$12,"Registered",IF($O71>0,"In Progress","Not Started")))))) | S71: =IF($B71="","",COUNTIF(G71:N71,"Received")) | T71: =IF($B71="","",COUNTIF(G71:N71,"Needs Correction")) | U71: =IF($B71="","",IF($D71<>"Yes","",IF($Q71>=Settings!$C$13,"None",MID(IF(AND(G71<>"Accepted",G71<>"Not Needed",Settings!$C$15="Yes"),", "&G$1,"")&IF(AND(H71<>"Accepted",H71<>"Not Needed",Settings!$D$15="Yes"),", "&H$1,"")&IF(AND(I71<>"Accepted",I71<>"Not Needed",Settings!$E$15="Yes"),", "&I$1,"")&IF(AND(J71<>"Accepted",J71<>"Not Needed",Settings!$F$15="Yes"),", "&J$1,"")&IF(AND(K71<>"Accepted",K71<>"Not Needed",Settings!$G$15="Yes"),", "&K$1,"")&IF(AND(L71<>"Accepted",L71<>"Not Needed",Settings!$H$15="Yes"),", "&L$1,"")&IF(AND(M71<>"Accepted",M71<>"Not Needed",Settings!$I$15="Yes"),", "&M$1,"")&IF(AND(N71<>"Accepted",N71<>"Not Needed",Settings!$J$15="Yes"),", "&N$1,""),3,400))))
A72: 2026-27 | B72: Farias ECC | C72: EAS Elementary | D72: Not Yet Confirmed | G72: Not Received | H72: Not Received | I72: Not Received | J72: Not Received | K72: Not Received | L72: Not Received | M72: Not Received | N72: Not Received | O72: =IF($B72="","",COUNTIF(G72:N72,"Accepted")+COUNTIF(G72:N72,"Received")+COUNTIF(G72:N72,"Needs Correction")) | P72: =IF($B72="","",SUMPRODUCT(((G72:N72="Accepted")+(G72:N72="Not Needed"))*(Settings!$C$11:$J$11="Yes"))) | Q72: =IF($B72="","",SUMPRODUCT(((G72:N72="Accepted")+(G72:N72="Not Needed"))*(Settings!$C$15:$J$15="Yes"))) | R72: =IF($B72="","",IF($D72="No","No PTO/PTA",IF($D72<>"Yes","Not Yet Confirmed",IF($Q72>=Settings!$C$13,"Legalized",IF($P72>=Settings!$C$12,"Registered",IF($O72>0,"In Progress","Not Started")))))) | S72: =IF($B72="","",COUNTIF(G72:N72,"Received")) | T72: =IF($B72="","",COUNTIF(G72:N72,"Needs Correction")) | U72: =IF($B72="","",IF($D72<>"Yes","",IF($Q72>=Settings!$C$13,"None",MID(IF(AND(G72<>"Accepted",G72<>"Not Needed",Settings!$C$15="Yes"),", "&G$1,"")&IF(AND(H72<>"Accepted",H72<>"Not Needed",Settings!$D$15="Yes"),", "&H$1,"")&IF(AND(I72<>"Accepted",I72<>"Not Needed",Settings!$E$15="Yes"),", "&I$1,"")&IF(AND(J72<>"Accepted",J72<>"Not Needed",Settings!$F$15="Yes"),", "&J$1,"")&IF(AND(K72<>"Accepted",K72<>"Not Needed",Settings!$G$15="Yes"),", "&K$1,"")&IF(AND(L72<>"Accepted",L72<>"Not Needed",Settings!$H$15="Yes"),", "&L$1,"")&IF(AND(M72<>"Accepted",M72<>"Not Needed",Settings!$I$15="Yes"),", "&M$1,"")&IF(AND(N72<>"Accepted",N72<>"Not Needed",Settings!$J$15="Yes"),", "&N$1,""),3,400))))
A73: 2026-27 | B73: Field ES | C73: EAS Elementary | D73: Not Yet Confirmed | G73: Not Received | H73: Not Received | I73: Not Received | J73: Not Received | K73: Not Received | L73: Not Received | M73: Not Received | N73: Not Received | O73: =IF($B73="","",COUNTIF(G73:N73,"Accepted")+COUNTIF(G73:N73,"Received")+COUNTIF(G73:N73,"Needs Correction")) | P73: =IF($B73="","",SUMPRODUCT(((G73:N73="Accepted")+(G73:N73="Not Needed"))*(Settings!$C$11:$J$11="Yes"))) | Q73: =IF($B73="","",SUMPRODUCT(((G73:N73="Accepted")+(G73:N73="Not Needed"))*(Settings!$C$15:$J$15="Yes"))) | R73: =IF($B73="","",IF($D73="No","No PTO/PTA",IF($D73<>"Yes","Not Yet Confirmed",IF($Q73>=Settings!$C$13,"Legalized",IF($P73>=Settings!$C$12,"Registered",IF($O73>0,"In Progress","Not Started")))))) | S73: =IF($B73="","",COUNTIF(G73:N73,"Received")) | T73: =IF($B73="","",COUNTIF(G73:N73,"Needs Correction")) | U73: =IF($B73="","",IF($D73<>"Yes","",IF($Q73>=Settings!$C$13,"None",MID(IF(AND(G73<>"Accepted",G73<>"Not Needed",Settings!$C$15="Yes"),", "&G$1,"")&IF(AND(H73<>"Accepted",H73<>"Not Needed",Settings!$D$15="Yes"),", "&H$1,"")&IF(AND(I73<>"Accepted",I73<>"Not Needed",Settings!$E$15="Yes"),", "&I$1,"")&IF(AND(J73<>"Accepted",J73<>"Not Needed",Settings!$F$15="Yes"),", "&J$1,"")&IF(AND(K73<>"Accepted",K73<>"Not Needed",Settings!$G$15="Yes"),", "&K$1,"")&IF(AND(L73<>"Accepted",L73<>"Not Needed",Settings!$H$15="Yes"),", "&L$1,"")&IF(AND(M73<>"Accepted",M73<>"Not Needed",Settings!$I$15="Yes"),", "&M$1,"")&IF(AND(N73<>"Accepted",N73<>"Not Needed",Settings!$J$15="Yes"),", "&N$1,""),3,400))))
A74: 2026-27 | B74: Fonwood ECC | C74: EAS Elementary | D74: Not Yet Confirmed | G74: Not Received | H74: Not Received | I74: Not Received | J74: Not Received | K74: Not Received | L74: Not Received | M74: Not Received | N74: Not Received | O74: =IF($B74="","",COUNTIF(G74:N74,"Accepted")+COUNTIF(G74:N74,"Received")+COUNTIF(G74:N74,"Needs Correction")) | P74: =IF($B74="","",SUMPRODUCT(((G74:N74="Accepted")+(G74:N74="Not Needed"))*(Settings!$C$11:$J$11="Yes"))) | Q74: =IF($B74="","",SUMPRODUCT(((G74:N74="Accepted")+(G74:N74="Not Needed"))*(Settings!$C$15:$J$15="Yes"))) | R74: =IF($B74="","",IF($D74="No","No PTO/PTA",IF($D74<>"Yes","Not Yet Confirmed",IF($Q74>=Settings!$C$13,"Legalized",IF($P74>=Settings!$C$12,"Registered",IF($O74>0,"In Progress","Not Started")))))) | S74: =IF($B74="","",COUNTIF(G74:N74,"Received")) | T74: =IF($B74="","",COUNTIF(G74:N74,"Needs Correction")) | U74: =IF($B74="","",IF($D74<>"Yes","",IF($Q74>=Settings!$C$13,"None",MID(IF(AND(G74<>"Accepted",G74<>"Not Needed",Settings!$C$15="Yes"),", "&G$1,"")&IF(AND(H74<>"Accepted",H74<>"Not Needed",Settings!$D$15="Yes"),", "&H$1,"")&IF(AND(I74<>"Accepted",I74<>"Not Needed",Settings!$E$15="Yes"),", "&I$1,"")&IF(AND(J74<>"Accepted",J74<>"Not Needed",Settings!$F$15="Yes"),", "&J$1,"")&IF(AND(K74<>"Accepted",K74<>"Not Needed",Settings!$G$15="Yes"),", "&K$1,"")&IF(AND(L74<>"Accepted",L74<>"Not Needed",Settings!$H$15="Yes"),", "&L$1,"")&IF(AND(M74<>"Accepted",M74<>"Not Needed",Settings!$I$15="Yes"),", "&M$1,"")&IF(AND(N74<>"Accepted",N74<>"Not Needed",Settings!$J$15="Yes"),", "&N$1,""),3,400))))
A75: 2026-27 | B75: Garden Oaks | C75: EAS Elementary | D75: Not Yet Confirmed | G75: Not Received | H75: Not Received | I75: Not Received | J75: Not Received | K75: Not Received | L75: Not Received | M75: Not Received | N75: Not Received | O75: =IF($B75="","",COUNTIF(G75:N75,"Accepted")+COUNTIF(G75:N75,"Received")+COUNTIF(G75:N75,"Needs Correction")) | P75: =IF($B75="","",SUMPRODUCT(((G75:N75="Accepted")+(G75:N75="Not Needed"))*(Settings!$C$11:$J$11="Yes"))) | Q75: =IF($B75="","",SUMPRODUCT(((G75:N75="Accepted")+(G75:N75="Not Needed"))*(Settings!$C$15:$J$15="Yes"))) | R75: =IF($B75="","",IF($D75="No","No PTO/PTA",IF($D75<>"Yes","Not Yet Confirmed",IF($Q75>=Settings!$C$13,"Legalized",IF($P75>=Settings!$C$12,"Registered",IF($O75>0,"In Progress","Not Started")))))) | S75: =IF($B75="","",COUNTIF(G75:N75,"Received")) | T75: =IF($B75="","",COUNTIF(G75:N75,"Needs Correction")) | U75: =IF($B75="","",IF($D75<>"Yes","",IF($Q75>=Settings!$C$13,"None",MID(IF(AND(G75<>"Accepted",G75<>"Not Needed",Settings!$C$15="Yes"),", "&G$1,"")&IF(AND(H75<>"Accepted",H75<>"Not Needed",Settings!$D$15="Yes"),", "&H$1,"")&IF(AND(I75<>"Accepted",I75<>"Not Needed",Settings!$E$15="Yes"),", "&I$1,"")&IF(AND(J75<>"Accepted",J75<>"Not Needed",Settings!$F$15="Yes"),", "&J$1,"")&IF(AND(K75<>"Accepted",K75<>"Not Needed",Settings!$G$15="Yes"),", "&K$1,"")&IF(AND(L75<>"Accepted",L75<>"Not Needed",Settings!$H$15="Yes"),", "&L$1,"")&IF(AND(M75<>"Accepted",M75<>"Not Needed",Settings!$I$15="Yes"),", "&M$1,"")&IF(AND(N75<>"Accepted",N75<>"Not Needed",Settings!$J$15="Yes"),", "&N$1,""),3,400))))
A76: 2026-27 | B76: Garden Villas ES | C76: EAS Elementary | D76: Not Yet Confirmed | G76: Not Received | H76: Not Received | I76: Not Received | J76: Not Received | K76: Not Received | L76: Not Received | M76: Not Received | N76: Not Received | O76: =IF($B76="","",COUNTIF(G76:N76,"Accepted")+COUNTIF(G76:N76,"Received")+COUNTIF(G76:N76,"Needs Correction")) | P76: =IF($B76="","",SUMPRODUCT(((G76:N76="Accepted")+(G76:N76="Not Needed"))*(Settings!$C$11:$J$11="Yes"))) | Q76: =IF($B76="","",SUMPRODUCT(((G76:N76="Accepted")+(G76:N76="Not Needed"))*(Settings!$C$15:$J$15="Yes"))) | R76: =IF($B76="","",IF($D76="No","No PTO/PTA",IF($D76<>"Yes","Not Yet Confirmed",IF($Q76>=Settings!$C$13,"Legalized",IF($P76>=Settings!$C$12,"Registered",IF($O76>0,"In Progress","Not Started")))))) | S76: =IF($B76="","",COUNTIF(G76:N76,"Received")) | T76: =IF($B76="","",COUNTIF(G76:N76,"Needs Correction")) | U76: =IF($B76="","",IF($D76<>"Yes","",IF($Q76>=Settings!$C$13,"None",MID(IF(AND(G76<>"Accepted",G76<>"Not Needed",Settings!$C$15="Yes"),", "&G$1,"")&IF(AND(H76<>"Accepted",H76<>"Not Needed",Settings!$D$15="Yes"),", "&H$1,"")&IF(AND(I76<>"Accepted",I76<>"Not Needed",Settings!$E$15="Yes"),", "&I$1,"")&IF(AND(J76<>"Accepted",J76<>"Not Needed",Settings!$F$15="Yes"),", "&J$1,"")&IF(AND(K76<>"Accepted",K76<>"Not Needed",Settings!$G$15="Yes"),", "&K$1,"")&IF(AND(L76<>"Accepted",L76<>"Not Needed",Settings!$H$15="Yes"),", "&L$1,"")&IF(AND(M76<>"Accepted",M76<>"Not Needed",Settings!$I$15="Yes"),", "&M$1,"")&IF(AND(N76<>"Accepted",N76<>"Not Needed",Settings!$J$15="Yes"),", "&N$1,""),3,400))))
A77: 2026-27 | B77: Harvard ES | C77: EAS Elementary | D77: Yes | E77: PTA | G77: Accepted | H77: Not Received | I77: Not Received | J77: Not Received | K77: Accepted | L77: Accepted | M77: Not Received | N77: Not Received | O77: =IF($B77="","",COUNTIF(G77:N77,"Accepted")+COUNTIF(G77:N77,"Received")+COUNTIF(G77:N77,"Needs Correction")) | P77: =IF($B77="","",SUMPRODUCT(((G77:N77="Accepted")+(G77:N77="Not Needed"))*(Settings!$C$11:$J$11="Yes"))) | Q77: =IF($B77="","",SUMPRODUCT(((G77:N77="Accepted")+(G77:N77="Not Needed"))*(Settings!$C$15:$J$15="Yes"))) | R77: =IF($B77="","",IF($D77="No","No PTO/PTA",IF($D77<>"Yes","Not Yet Confirmed",IF($Q77>=Settings!$C$13,"Legalized",IF($P77>=Settings!$C$12,"Registered",IF($O77>0,"In Progress","Not Started")))))) | S77: =IF($B77="","",COUNTIF(G77:N77,"Received")) | T77: =IF($B77="","",COUNTIF(G77:N77,"Needs Correction")) | U77: =IF($B77="","",IF($D77<>"Yes","",IF($Q77>=Settings!$C$13,"None",MID(IF(AND(G77<>"Accepted",G77<>"Not Needed",Settings!$C$15="Yes"),", "&G$1,"")&IF(AND(H77<>"Accepted",H77<>"Not Needed",Settings!$D$15="Yes"),", "&H$1,"")&IF(AND(I77<>"Accepted",I77<>"Not Needed",Settings!$E$15="Yes"),", "&I$1,"")&IF(AND(J77<>"Accepted",J77<>"Not Needed",Settings!$F$15="Yes"),", "&J$1,"")&IF(AND(K77<>"Accepted",K77<>"Not Needed",Settings!$G$15="Yes"),", "&K$1,"")&IF(AND(L77<>"Accepted",L77<>"Not Needed",Settings!$H$15="Yes"),", "&L$1,"")&IF(AND(M77<>"Accepted",M77<>"Not Needed",Settings!$I$15="Yes"),", "&M$1,"")&IF(AND(N77<>"Accepted",N77<>"Not Needed",Settings!$J$15="Yes"),", "&N$1,""),3,400))))
A78: 2026-27 | B78: Helms ES | C78: EAS Elementary | D78: Yes | E78: PTA | G78: Accepted | H78: Not Received | I78: Not Received | J78: Not Received | K78: Accepted | L78: Accepted | M78: Not Received | N78: Not Received | O78: =IF($B78="","",COUNTIF(G78:N78,"Accepted")+COUNTIF(G78:N78,"Received")+COUNTIF(G78:N78,"Needs Correction")) | P78: =IF($B78="","",SUMPRODUCT(((G78:N78="Accepted")+(G78:N78="Not Needed"))*(Settings!$C$11:$J$11="Yes"))) | Q78: =IF($B78="","",SUMPRODUCT(((G78:N78="Accepted")+(G78:N78="Not Needed"))*(Settings!$C$15:$J$15="Yes"))) | R78: =IF($B78="","",IF($D78="No","No PTO/PTA",IF($D78<>"Yes","Not Yet Confirmed",IF($Q78>=Settings!$C$13,"Legalized",IF($P78>=Settings!$C$12,"Registered",IF($O78>0,"In Progress","Not Started")))))) | S78: =IF($B78="","",COUNTIF(G78:N78,"Received")) | T78: =IF($B78="","",COUNTIF(G78:N78,"Needs Correction")) | U78: =IF($B78="","",IF($D78<>"Yes","",IF($Q78>=Settings!$C$13,"None",MID(IF(AND(G78<>"Accepted",G78<>"Not Needed",Settings!$C$15="Yes"),", "&G$1,"")&IF(AND(H78<>"Accepted",H78<>"Not Needed",Settings!$D$15="Yes"),", "&H$1,"")&IF(AND(I78<>"Accepted",I78<>"Not Needed",Settings!$E$15="Yes"),", "&I$1,"")&IF(AND(J78<>"Accepted",J78<>"Not Needed",Settings!$F$15="Yes"),", "&J$1,"")&IF(AND(K78<>"Accepted",K78<>"Not Needed",Settings!$G$15="Yes"),", "&K$1,"")&IF(AND(L78<>"Accepted",L78<>"Not Needed",Settings!$H$15="Yes"),", "&L$1,"")&IF(AND(M78<>"Accepted",M78<>"Not Needed",Settings!$I$15="Yes"),", "&M$1,"")&IF(AND(N78<>"Accepted",N78<>"Not Needed",Settings!$J$15="Yes"),", "&N$1,""),3,400))))
A79: 2026-27 | B79: Henderson JP ES | C79: EAS Elementary | D79: Not Yet Confirmed | G79: Not Received | H79: Not Received | I79: Not Received | J79: Not Received | K79: Not Received | L79: Not Received | M79: Not Received | N79: Not Received | O79: =IF($B79="","",COUNTIF(G79:N79,"Accepted")+COUNTIF(G79:N79,"Received")+COUNTIF(G79:N79,"Needs Correction")) | P79: =IF($B79="","",SUMPRODUCT(((G79:N79="Accepted")+(G79:N79="Not Needed"))*(Settings!$C$11:$J$11="Yes"))) | Q79: =IF($B79="","",SUMPRODUCT(((G79:N79="Accepted")+(G79:N79="Not Needed"))*(Settings!$C$15:$J$15="Yes"))) | R79: =IF($B79="","",IF($D79="No","No PTO/PTA",IF($D79<>"Yes","Not Yet Confirmed",IF($Q79>=Settings!$C$13,"Legalized",IF($P79>=Settings!$C$12,"Registered",IF($O79>0,"In Progress","Not Started")))))) | S79: =IF($B79="","",COUNTIF(G79:N79,"Received")) | T79: =IF($B79="","",COUNTIF(G79:N79,"Needs Correction")) | U79: =IF($B79="","",IF($D79<>"Yes","",IF($Q79>=Settings!$C$13,"None",MID(IF(AND(G79<>"Accepted",G79<>"Not Needed",Settings!$C$15="Yes"),", "&G$1,"")&IF(AND(H79<>"Accepted",H79<>"Not Needed",Settings!$D$15="Yes"),", "&H$1,"")&IF(AND(I79<>"Accepted",I79<>"Not Needed",Settings!$E$15="Yes"),", "&I$1,"")&IF(AND(J79<>"Accepted",J79<>"Not Needed",Settings!$F$15="Yes"),", "&J$1,"")&IF(AND(K79<>"Accepted",K79<>"Not Needed",Settings!$G$15="Yes"),", "&K$1,"")&IF(AND(L79<>"Accepted",L79<>"Not Needed",Settings!$H$15="Yes"),", "&L$1,"")&IF(AND(M79<>"Accepted",M79<>"Not Needed",Settings!$I$15="Yes"),", "&M$1,"")&IF(AND(N79<>"Accepted",N79<>"Not Needed",Settings!$J$15="Yes"),", "&N$1,""),3,400))))
A80: 2026-27 | B80: Herod ES | C80: EAS Elementary | D80: Not Yet Confirmed | G80: Not Received | H80: Not Received | I80: Not Received | J80: Not Received | K80: Not Received | L80: Not Received | M80: Not Received | N80: Not Received | O80: =IF($B80="","",COUNTIF(G80:N80,"Accepted")+COUNTIF(G80:N80,"Received")+COUNTIF(G80:N80,"Needs Correction")) | P80: =IF($B80="","",SUMPRODUCT(((G80:N80="Accepted")+(G80:N80="Not Needed"))*(Settings!$C$11:$J$11="Yes"))) | Q80: =IF($B80="","",SUMPRODUCT(((G80:N80="Accepted")+(G80:N80="Not Needed"))*(Settings!$C$15:$J$15="Yes"))) | R80: =IF($B80="","",IF($D80="No","No PTO/PTA",IF($D80<>"Yes","Not Yet Confirmed",IF($Q80>=Settings!$C$13,"Legalized",IF($P80>=Settings!$C$12,"Registered",IF($O80>0,"In Progress","Not Started")))))) | S80: =IF($B80="","",COUNTIF(G80:N80,"Received")) | T80: =IF($B80="","",COUNTIF(G80:N80,"Needs Correction")) | U80: =IF($B80="","",IF($D80<>"Yes","",IF($Q80>=Settings!$C$13,"None",MID(IF(AND(G80<>"Accepted",G80<>"Not Needed",Settings!$C$15="Yes"),", "&G$1,"")&IF(AND(H80<>"Accepted",H80<>"Not Needed",Settings!$D$15="Yes"),", "&H$1,"")&IF(AND(I80<>"Accepted",I80<>"Not Needed",Settings!$E$15="Yes"),", "&I$1,"")&IF(AND(J80<>"Accepted",J80<>"Not Needed",Settings!$F$15="Yes"),", "&J$1,"")&IF(AND(K80<>"Accepted",K80<>"Not Needed",Settings!$G$15="Yes"),", "&K$1,"")&IF(AND(L80<>"Accepted",L80<>"Not Needed",Settings!$H$15="Yes"),", "&L$1,"")&IF(AND(M80<>"Accepted",M80<>"Not Needed",Settings!$I$15="Yes"),", "&M$1,"")&IF(AND(N80<>"Accepted",N80<>"Not Needed",Settings!$J$15="Yes"),", "&N$1,""),3,400))))
A81: 2026-27 | B81: Herrera ES | C81: EAS Elementary | D81: Not Yet Confirmed | G81: Not Received | H81: Not Received | I81: Not Received | J81: Not Received | K81: Not Received | L81: Not Received | M81: Not Received | N81: Not Received | O81: =IF($B81="","",COUNTIF(G81:N81,"Accepted")+COUNTIF(G81:N81,"Received")+COUNTIF(G81:N81,"Needs Correction")) | P81: =IF($B81="","",SUMPRODUCT(((G81:N81="Accepted")+(G81:N81="Not Needed"))*(Settings!$C$11:$J$11="Yes"))) | Q81: =IF($B81="","",SUMPRODUCT(((G81:N81="Accepted")+(G81:N81="Not Needed"))*(Settings!$C$15:$J$15="Yes"))) | R81: =IF($B81="","",IF($D81="No","No PTO/PTA",IF($D81<>"Yes","Not Yet Confirmed",IF($Q81>=Settings!$C$13,"Legalized",IF($P81>=Settings!$C$12,"Registered",IF($O81>0,"In Progress","Not Started")))))) | S81: =IF($B81="","",COUNTIF(G81:N81,"Received")) | T81: =IF($B81="","",COUNTIF(G81:N81,"Needs Correction")) | U81: =IF($B81="","",IF($D81<>"Yes","",IF($Q81>=Settings!$C$13,"None",MID(IF(AND(G81<>"Accepted",G81<>"Not Needed",Settings!$C$15="Yes"),", "&G$1,"")&IF(AND(H81<>"Accepted",H81<>"Not Needed",Settings!$D$15="Yes"),", "&H$1,"")&IF(AND(I81<>"Accepted",I81<>"Not Needed",Settings!$E$15="Yes"),", "&I$1,"")&IF(AND(J81<>"Accepted",J81<>"Not Needed",Settings!$F$15="Yes"),", "&J$1,"")&IF(AND(K81<>"Accepted",K81<>"Not Needed",Settings!$G$15="Yes"),", "&K$1,"")&IF(AND(L81<>"Accepted",L81<>"Not Needed",Settings!$H$15="Yes"),", "&L$1,"")&IF(AND(M81<>"Accepted",M81<>"Not Needed",Settings!$I$15="Yes"),", "&M$1,"")&IF(AND(N81<>"Accepted",N81<>"Not Needed",Settings!$J$15="Yes"),", "&N$1,""),3,400))))
A82: 2026-27 | B82: Hines-Caldwell ES | C82: EAS Elementary | D82: Not Yet Confirmed | G82: Not Received | H82: Not Received | I82: Not Received | J82: Not Received | K82: Not Received | L82: Not Received | M82: Not Received | N82: Not Received | O82: =IF($B82="","",COUNTIF(G82:N82,"Accepted")+COUNTIF(G82:N82,"Received")+COUNTIF(G82:N82,"Needs Correction")) | P82: =IF($B82="","",SUMPRODUCT(((G82:N82="Accepted")+(G82:N82="Not Needed"))*(Settings!$C$11:$J$11="Yes"))) | Q82: =IF($B82="","",SUMPRODUCT(((G82:N82="Accepted")+(G82:N82="Not Needed"))*(Settings!$C$15:$J$15="Yes"))) | R82: =IF($B82="","",IF($D82="No","No PTO/PTA",IF($D82<>"Yes","Not Yet Confirmed",IF($Q82>=Settings!$C$13,"Legalized",IF($P82>=Settings!$C$12,"Registered",IF($O82>0,"In Progress","Not Started")))))) | S82: =IF($B82="","",COUNTIF(G82:N82,"Received")) | T82: =IF($B82="","",COUNTIF(G82:N82,"Needs Correction")) | U82: =IF($B82="","",IF($D82<>"Yes","",IF($Q82>=Settings!$C$13,"None",MID(IF(AND(G82<>"Accepted",G82<>"Not Needed",Settings!$C$15="Yes"),", "&G$1,"")&IF(AND(H82<>"Accepted",H82<>"Not Needed",Settings!$D$15="Yes"),", "&H$1,"")&IF(AND(I82<>"Accepted",I82<>"Not Needed",Settings!$E$15="Yes"),", "&I$1,"")&IF(AND(J82<>"Accepted",J82<>"Not Needed",Settings!$F$15="Yes"),", "&J$1,"")&IF(AND(K82<>"Accepted",K82<>"Not Needed",Settings!$G$15="Yes"),", "&K$1,"")&IF(AND(L82<>"Accepted",L82<>"Not Needed",Settings!$H$15="Yes"),", "&L$1,"")&IF(AND(M82<>"Accepted",M82<>"Not Needed",Settings!$I$15="Yes"),", "&M$1,"")&IF(AND(N82<>"Accepted",N82<>"Not Needed",Settings!$J$15="Yes"),", "&N$1,""),3,400))))
A83: 2026-27 | B83: Horn ES | C83: EAS Elementary | D83: Not Yet Confirmed | G83: Not Received | H83: Not Received | I83: Not Received | J83: Not Received | K83: Not Received | L83: Not Received | M83: Not Received | N83: Not Received | O83: =IF($B83="","",COUNTIF(G83:N83,"Accepted")+COUNTIF(G83:N83,"Received")+COUNTIF(G83:N83,"Needs Correction")) | P83: =IF($B83="","",SUMPRODUCT(((G83:N83="Accepted")+(G83:N83="Not Needed"))*(Settings!$C$11:$J$11="Yes"))) | Q83: =IF($B83="","",SUMPRODUCT(((G83:N83="Accepted")+(G83:N83="Not Needed"))*(Settings!$C$15:$J$15="Yes"))) | R83: =IF($B83="","",IF($D83="No","No PTO/PTA",IF($D83<>"Yes","Not Yet Confirmed",IF($Q83>=Settings!$C$13,"Legalized",IF($P83>=Settings!$C$12,"Registered",IF($O83>0,"In Progress","Not Started")))))) | S83: =IF($B83="","",COUNTIF(G83:N83,"Received")) | T83: =IF($B83="","",COUNTIF(G83:N83,"Needs Correction")) | U83: =IF($B83="","",IF($D83<>"Yes","",IF($Q83>=Settings!$C$13,"None",MID(IF(AND(G83<>"Accepted",G83<>"Not Needed",Settings!$C$15="Yes"),", "&G$1,"")&IF(AND(H83<>"Accepted",H83<>"Not Needed",Settings!$D$15="Yes"),", "&H$1,"")&IF(AND(I83<>"Accepted",I83<>"Not Needed",Settings!$E$15="Yes"),", "&I$1,"")&IF(AND(J83<>"Accepted",J83<>"Not Needed",Settings!$F$15="Yes"),", "&J$1,"")&IF(AND(K83<>"Accepted",K83<>"Not Needed",Settings!$G$15="Yes"),", "&K$1,"")&IF(AND(L83<>"Accepted",L83<>"Not Needed",Settings!$H$15="Yes"),", "&L$1,"")&IF(AND(M83<>"Accepted",M83<>"Not Needed",Settings!$I$15="Yes"),", "&M$1,"")&IF(AND(N83<>"Accepted",N83<>"Not Needed",Settings!$J$15="Yes"),", "&N$1,""),3,400))))
A84: 2026-27 | B84: Kolter ES | C84: EAS Elementary | D84: Not Yet Confirmed | G84: Not Received | H84: Not Received | I84: Not Received | J84: Not Received | K84: Not Received | L84: Not Received | M84: Not Received | N84: Not Received | O84: =IF($B84="","",COUNTIF(G84:N84,"Accepted")+COUNTIF(G84:N84,"Received")+COUNTIF(G84:N84,"Needs Correction")) | P84: =IF($B84="","",SUMPRODUCT(((G84:N84="Accepted")+(G84:N84="Not Needed"))*(Settings!$C$11:$J$11="Yes"))) | Q84: =IF($B84="","",SUMPRODUCT(((G84:N84="Accepted")+(G84:N84="Not Needed"))*(Settings!$C$15:$J$15="Yes"))) | R84: =IF($B84="","",IF($D84="No","No PTO/PTA",IF($D84<>"Yes","Not Yet Confirmed",IF($Q84>=Settings!$C$13,"Legalized",IF($P84>=Settings!$C$12,"Registered",IF($O84>0,"In Progress","Not Started")))))) | S84: =IF($B84="","",COUNTIF(G84:N84,"Received")) | T84: =IF($B84="","",COUNTIF(G84:N84,"Needs Correction")) | U84: =IF($B84="","",IF($D84<>"Yes","",IF($Q84>=Settings!$C$13,"None",MID(IF(AND(G84<>"Accepted",G84<>"Not Needed",Settings!$C$15="Yes"),", "&G$1,"")&IF(AND(H84<>"Accepted",H84<>"Not Needed",Settings!$D$15="Yes"),", "&H$1,"")&IF(AND(I84<>"Accepted",I84<>"Not Needed",Settings!$E$15="Yes"),", "&I$1,"")&IF(AND(J84<>"Accepted",J84<>"Not Needed",Settings!$F$15="Yes"),", "&J$1,"")&IF(AND(K84<>"Accepted",K84<>"Not Needed",Settings!$G$15="Yes"),", "&K$1,"")&IF(AND(L84<>"Accepted",L84<>"Not Needed",Settings!$H$15="Yes"),", "&L$1,"")&IF(AND(M84<>"Accepted",M84<>"Not Needed",Settings!$I$15="Yes"),", "&M$1,"")&IF(AND(N84<>"Accepted",N84<>"Not Needed",Settings!$J$15="Yes"),", "&N$1,""),3,400))))
A85: 2026-27 | B85: Lantrip ES | C85: EAS Elementary | D85: Not Yet Confirmed | G85: Not Received | H85: Not Received | I85: Not Received | J85: Not Received | K85: Not Received | L85: Not Received | M85: Not Received | N85: Not Received | O85: =IF($B85="","",COUNTIF(G85:N85,"Accepted")+COUNTIF(G85:N85,"Received")+COUNTIF(G85:N85,"Needs Correction")) | P85: =IF($B85="","",SUMPRODUCT(((G85:N85="Accepted")+(G85:N85="Not Needed"))*(Settings!$C$11:$J$11="Yes"))) | Q85: =IF($B85="","",SUMPRODUCT(((G85:N85="Accepted")+(G85:N85="Not Needed"))*(Settings!$C$15:$J$15="Yes"))) | R85: =IF($B85="","",IF($D85="No","No PTO/PTA",IF($D85<>"Yes","Not Yet Confirmed",IF($Q85>=Settings!$C$13,"Legalized",IF($P85>=Settings!$C$12,"Registered",IF($O85>0,"In Progress","Not Started")))))) | S85: =IF($B85="","",COUNTIF(G85:N85,"Received")) | T85: =IF($B85="","",COUNTIF(G85:N85,"Needs Correction")) | U85: =IF($B85="","",IF($D85<>"Yes","",IF($Q85>=Settings!$C$13,"None",MID(IF(AND(G85<>"Accepted",G85<>"Not Needed",Settings!$C$15="Yes"),", "&G$1,"")&IF(AND(H85<>"Accepted",H85<>"Not Needed",Settings!$D$15="Yes"),", "&H$1,"")&IF(AND(I85<>"Accepted",I85<>"Not Needed",Settings!$E$15="Yes"),", "&I$1,"")&IF(AND(J85<>"Accepted",J85<>"Not Needed",Settings!$F$15="Yes"),", "&J$1,"")&IF(AND(K85<>"Accepted",K85<>"Not Needed",Settings!$G$15="Yes"),", "&K$1,"")&IF(AND(L85<>"Accepted",L85<>"Not Needed",Settings!$H$15="Yes"),", "&L$1,"")&IF(AND(M85<>"Accepted",M85<>"Not Needed",Settings!$I$15="Yes"),", "&M$1,"")&IF(AND(N85<>"Accepted",N85<>"Not Needed",Settings!$J$15="Yes"),", "&N$1,""),3,400))))
A86: 2026-27 | B86: Laurenzo ECC | C86: EAS Elementary | D86: Not Yet Confirmed | G86: Not Received | H86: Not Received | I86: Not Received | J86: Not Received | K86: Not Received | L86: Not Received | M86: Not Received | N86: Not Received | O86: =IF($B86="","",COUNTIF(G86:N86,"Accepted")+COUNTIF(G86:N86,"Received")+COUNTIF(G86:N86,"Needs Correction")) | P86: =IF($B86="","",SUMPRODUCT(((G86:N86="Accepted")+(G86:N86="Not Needed"))*(Settings!$C$11:$J$11="Yes"))) | Q86: =IF($B86="","",SUMPRODUCT(((G86:N86="Accepted")+(G86:N86="Not Needed"))*(Settings!$C$15:$J$15="Yes"))) | R86: =IF($B86="","",IF($D86="No","No PTO/PTA",IF($D86<>"Yes","Not Yet Confirmed",IF($Q86>=Settings!$C$13,"Legalized",IF($P86>=Settings!$C$12,"Registered",IF($O86>0,"In Progress","Not Started")))))) | S86: =IF($B86="","",COUNTIF(G86:N86,"Received")) | T86: =IF($B86="","",COUNTIF(G86:N86,"Needs Correction")) | U86: =IF($B86="","",IF($D86<>"Yes","",IF($Q86>=Settings!$C$13,"None",MID(IF(AND(G86<>"Accepted",G86<>"Not Needed",Settings!$C$15="Yes"),", "&G$1,"")&IF(AND(H86<>"Accepted",H86<>"Not Needed",Settings!$D$15="Yes"),", "&H$1,"")&IF(AND(I86<>"Accepted",I86<>"Not Needed",Settings!$E$15="Yes"),", "&I$1,"")&IF(AND(J86<>"Accepted",J86<>"Not Needed",Settings!$F$15="Yes"),", "&J$1,"")&IF(AND(K86<>"Accepted",K86<>"Not Needed",Settings!$G$15="Yes"),", "&K$1,"")&IF(AND(L86<>"Accepted",L86<>"Not Needed",Settings!$H$15="Yes"),", "&L$1,"")&IF(AND(M86<>"Accepted",M86<>"Not Needed",Settings!$I$15="Yes"),", "&M$1,"")&IF(AND(N86<>"Accepted",N86<>"Not Needed",Settings!$J$15="Yes"),", "&N$1,""),3,400))))
A87: 2026-27 | B87: Love ES | C87: EAS Elementary | D87: Not Yet Confirmed | G87: Not Received | H87: Not Received | I87: Not Received | J87: Not Received | K87: Not Received | L87: Not Received | M87: Not Received | N87: Not Received | O87: =IF($B87="","",COUNTIF(G87:N87,"Accepted")+COUNTIF(G87:N87,"Received")+COUNTIF(G87:N87,"Needs Correction")) | P87: =IF($B87="","",SUMPRODUCT(((G87:N87="Accepted")+(G87:N87="Not Needed"))*(Settings!$C$11:$J$11="Yes"))) | Q87: =IF($B87="","",SUMPRODUCT(((G87:N87="Accepted")+(G87:N87="Not Needed"))*(Settings!$C$15:$J$15="Yes"))) | R87: =IF($B87="","",IF($D87="No","No PTO/PTA",IF($D87<>"Yes","Not Yet Confirmed",IF($Q87>=Settings!$C$13,"Legalized",IF($P87>=Settings!$C$12,"Registered",IF($O87>0,"In Progress","Not Started")))))) | S87: =IF($B87="","",COUNTIF(G87:N87,"Received")) | T87: =IF($B87="","",COUNTIF(G87:N87,"Needs Correction")) | U87: =IF($B87="","",IF($D87<>"Yes","",IF($Q87>=Settings!$C$13,"None",MID(IF(AND(G87<>"Accepted",G87<>"Not Needed",Settings!$C$15="Yes"),", "&G$1,"")&IF(AND(H87<>"Accepted",H87<>"Not Needed",Settings!$D$15="Yes"),", "&H$1,"")&IF(AND(I87<>"Accepted",I87<>"Not Needed",Settings!$E$15="Yes"),", "&I$1,"")&IF(AND(J87<>"Accepted",J87<>"Not Needed",Settings!$F$15="Yes"),", "&J$1,"")&IF(AND(K87<>"Accepted",K87<>"Not Needed",Settings!$G$15="Yes"),", "&K$1,"")&IF(AND(L87<>"Accepted",L87<>"Not Needed",Settings!$H$15="Yes"),", "&L$1,"")&IF(AND(M87<>"Accepted",M87<>"Not Needed",Settings!$I$15="Yes"),", "&M$1,"")&IF(AND(N87<>"Accepted",N87<>"Not Needed",Settings!$J$15="Yes"),", "&N$1,""),3,400))))
A88: 2026-27 | B88: Lovett ES | C88: EAS Elementary | D88: Not Yet Confirmed | G88: Not Received | H88: Not Received | I88: Not Received | J88: Not Received | K88: Not Received | L88: Not Received | M88: Not Received | N88: Not Received | O88: =IF($B88="","",COUNTIF(G88:N88,"Accepted")+COUNTIF(G88:N88,"Received")+COUNTIF(G88:N88,"Needs Correction")) | P88: =IF($B88="","",SUMPRODUCT(((G88:N88="Accepted")+(G88:N88="Not Needed"))*(Settings!$C$11:$J$11="Yes"))) | Q88: =IF($B88="","",SUMPRODUCT(((G88:N88="Accepted")+(G88:N88="Not Needed"))*(Settings!$C$15:$J$15="Yes"))) | R88: =IF($B88="","",IF($D88="No","No PTO/PTA",IF($D88<>"Yes","Not Yet Confirmed",IF($Q88>=Settings!$C$13,"Legalized",IF($P88>=Settings!$C$12,"Registered",IF($O88>0,"In Progress","Not Started")))))) | S88: =IF($B88="","",COUNTIF(G88:N88,"Received")) | T88: =IF($B88="","",COUNTIF(G88:N88,"Needs Correction")) | U88: =IF($B88="","",IF($D88<>"Yes","",IF($Q88>=Settings!$C$13,"None",MID(IF(AND(G88<>"Accepted",G88<>"Not Needed",Settings!$C$15="Yes"),", "&G$1,"")&IF(AND(H88<>"Accepted",H88<>"Not Needed",Settings!$D$15="Yes"),", "&H$1,"")&IF(AND(I88<>"Accepted",I88<>"Not Needed",Settings!$E$15="Yes"),", "&I$1,"")&IF(AND(J88<>"Accepted",J88<>"Not Needed",Settings!$F$15="Yes"),", "&J$1,"")&IF(AND(K88<>"Accepted",K88<>"Not Needed",Settings!$G$15="Yes"),", "&K$1,"")&IF(AND(L88<>"Accepted",L88<>"Not Needed",Settings!$H$15="Yes"),", "&L$1,"")&IF(AND(M88<>"Accepted",M88<>"Not Needed",Settings!$I$15="Yes"),", "&M$1,"")&IF(AND(N88<>"Accepted",N88<>"Not Needed",Settings!$J$15="Yes"),", "&N$1,""),3,400))))
A89: 2026-27 | B89: Lyons ES | C89: EAS Elementary | D89: Not Yet Confirmed | G89: Not Received | H89: Not Received | I89: Not Received | J89: Not Received | K89: Not Received | L89: Not Received | M89: Not Received | N89: Not Received | O89: =IF($B89="","",COUNTIF(G89:N89,"Accepted")+COUNTIF(G89:N89,"Received")+COUNTIF(G89:N89,"Needs Correction")) | P89: =IF($B89="","",SUMPRODUCT(((G89:N89="Accepted")+(G89:N89="Not Needed"))*(Settings!$C$11:$J$11="Yes"))) | Q89: =IF($B89="","",SUMPRODUCT(((G89:N89="Accepted")+(G89:N89="Not Needed"))*(Settings!$C$15:$J$15="Yes"))) | R89: =IF($B89="","",IF($D89="No","No PTO/PTA",IF($D89<>"Yes","Not Yet Confirmed",IF($Q89>=Settings!$C$13,"Legalized",IF($P89>=Settings!$C$12,"Registered",IF($O89>0,"In Progress","Not Started")))))) | S89: =IF($B89="","",COUNTIF(G89:N89,"Received")) | T89: =IF($B89="","",COUNTIF(G89:N89,"Needs Correction")) | U89: =IF($B89="","",IF($D89<>"Yes","",IF($Q89>=Settings!$C$13,"None",MID(IF(AND(G89<>"Accepted",G89<>"Not Needed",Settings!$C$15="Yes"),", "&G$1,"")&IF(AND(H89<>"Accepted",H89<>"Not Needed",Settings!$D$15="Yes"),", "&H$1,"")&IF(AND(I89<>"Accepted",I89<>"Not Needed",Settings!$E$15="Yes"),", "&I$1,"")&IF(AND(J89<>"Accepted",J89<>"Not Needed",Settings!$F$15="Yes"),", "&J$1,"")&IF(AND(K89<>"Accepted",K89<>"Not Needed",Settings!$G$15="Yes"),", "&K$1,"")&IF(AND(L89<>"Accepted",L89<>"Not Needed",Settings!$H$15="Yes"),", "&L$1,"")&IF(AND(M89<>"Accepted",M89<>"Not Needed",Settings!$I$15="Yes"),", "&M$1,"")&IF(AND(N89<>"Accepted",N89<>"Not Needed",Settings!$J$15="Yes"),", "&N$1,""),3,400))))
A90: 2026-27 | B90: MacGregor ES | C90: EAS Elementary | D90: Not Yet Confirmed | G90: Not Received | H90: Not Received | I90: Not Received | J90: Not Received | K90: Not Received | L90: Not Received | M90: Not Received | N90: Not Received | O90: =IF($B90="","",COUNTIF(G90:N90,"Accepted")+COUNTIF(G90:N90,"Received")+COUNTIF(G90:N90,"Needs Correction")) | P90: =IF($B90="","",SUMPRODUCT(((G90:N90="Accepted")+(G90:N90="Not Needed"))*(Settings!$C$11:$J$11="Yes"))) | Q90: =IF($B90="","",SUMPRODUCT(((G90:N90="Accepted")+(G90:N90="Not Needed"))*(Settings!$C$15:$J$15="Yes"))) | R90: =IF($B90="","",IF($D90="No","No PTO/PTA",IF($D90<>"Yes","Not Yet Confirmed",IF($Q90>=Settings!$C$13,"Legalized",IF($P90>=Settings!$C$12,"Registered",IF($O90>0,"In Progress","Not Started")))))) | S90: =IF($B90="","",COUNTIF(G90:N90,"Received")) | T90: =IF($B90="","",COUNTIF(G90:N90,"Needs Correction")) | U90: =IF($B90="","",IF($D90<>"Yes","",IF($Q90>=Settings!$C$13,"None",MID(IF(AND(G90<>"Accepted",G90<>"Not Needed",Settings!$C$15="Yes"),", "&G$1,"")&IF(AND(H90<>"Accepted",H90<>"Not Needed",Settings!$D$15="Yes"),", "&H$1,"")&IF(AND(I90<>"Accepted",I90<>"Not Needed",Settings!$E$15="Yes"),", "&I$1,"")&IF(AND(J90<>"Accepted",J90<>"Not Needed",Settings!$F$15="Yes"),", "&J$1,"")&IF(AND(K90<>"Accepted",K90<>"Not Needed",Settings!$G$15="Yes"),", "&K$1,"")&IF(AND(L90<>"Accepted",L90<>"Not Needed",Settings!$H$15="Yes"),", "&L$1,"")&IF(AND(M90<>"Accepted",M90<>"Not Needed",Settings!$I$15="Yes"),", "&M$1,"")&IF(AND(N90<>"Accepted",N90<>"Not Needed",Settings!$J$15="Yes"),", "&N$1,""),3,400))))
... A96: 2026-27 | B96: Neff ECC | C96: EAS Elementary | D96: Not Yet Confirmed | G96: Not Received | H96: Not Received | I96: Not Received | J96: Not Received | K96: Not Received | L96: Not Received | M96: Not Received | N96: Not Received | O96: =IF($B96="","",COUNTIF(G96:N96,"Accepted")+COUNTIF(G96:N96,"Received")+COUNTIF(G96:N96,"Needs Correction")) | P96: =IF($B96="","",SUMPRODUCT(((G96:N96="Accepted")+(G96:N96="Not Needed"))*(Settings!$C$11:$J$11="Yes"))) | Q96: =IF($B96="","",SUMPRODUCT(((G96:N96="Accepted")+(G96:N96="Not Needed"))*(Settings!$C$15:$J$15="Yes"))) | R96: =IF($B96="","",IF($D96="No","No PTO/PTA",IF($D96<>"Yes","Not Yet Confirmed",IF($Q96>=Settings!$C$13,"Legalized",IF($P96>=Settings!$C$12,"Registered",IF($O96>0,"In Progress","Not Started")))))) | S96: =IF($B96="","",COUNTIF(G96:N96,"Received")) | T96: =IF($B96="","",COUNTIF(G96:N96,"Needs Correction")) | U96: =IF($B96="","",IF($D96<>"Yes","",IF($Q96>=Settings!$C$13,"None",MID(IF(AND(G96<>"Accepted",G96<>"Not Needed",Settings!$C$15="Yes"),", "&G$1,"")&IF(AND(H96<>"Accepted",H96<>"Not Needed",Settings!$D$15="Yes"),", "&H$1,"")&IF(AND(I96<>"Accepted",I96<>"Not Needed",Settings!$E$15="Yes"),", "&I$1,"")&IF(AND(J96<>"Accepted",J96<>"Not Needed",Settings!$F$15="Yes"),", "&J$1,"")&IF(AND(K96<>"Accepted",K96<>"Not Needed",Settings!$G$15="Yes"),", "&K$1,"")&IF(AND(L96<>"Accepted",L96<>"Not Needed",Settings!$H$15="Yes"),", "&L$1,"")&IF(AND(M96<>"Accepted",M96<>"Not Needed",Settings!$I$15="Yes"),", "&M$1,"")&IF(AND(N96<>"Accepted",N96<>"Not Needed",Settings!$J$15="Yes"),", "&N$1,""),3,400))))
A97: 2026-27 | B97: Oak Forest ES | C97: EAS Elementary | D97: Yes | E97: PTA | G97: Accepted | H97: Not Received | I97: Not Received | J97: Accepted | K97: Accepted | L97: Accepted | M97: Not Received | N97: Not Received | O97: =IF($B97="","",COUNTIF(G97:N97,"Accepted")+COUNTIF(G97:N97,"Received")+COUNTIF(G97:N97,"Needs Correction")) | P97: =IF($B97="","",SUMPRODUCT(((G97:N97="Accepted")+(G97:N97="Not Needed"))*(Settings!$C$11:$J$11="Yes"))) | Q97: =IF($B97="","",SUMPRODUCT(((G97:N97="Accepted")+(G97:N97="Not Needed"))*(Settings!$C$15:$J$15="Yes"))) | R97: =IF($B97="","",IF($D97="No","No PTO/PTA",IF($D97<>"Yes","Not Yet Confirmed",IF($Q97>=Settings!$C$13,"Legalized",IF($P97>=Settings!$C$12,"Registered",IF($O97>0,"In Progress","Not Started")))))) | S97: =IF($B97="","",COUNTIF(G97:N97,"Received")) | T97: =IF($B97="","",COUNTIF(G97:N97,"Needs Correction")) | U97: =IF($B97="","",IF($D97<>"Yes","",IF($Q97>=Settings!$C$13,"None",MID(IF(AND(G97<>"Accepted",G97<>"Not Needed",Settings!$C$15="Yes"),", "&G$1,"")&IF(AND(H97<>"Accepted",H97<>"Not Needed",Settings!$D$15="Yes"),", "&H$1,"")&IF(AND(I97<>"Accepted",I97<>"Not Needed",Settings!$E$15="Yes"),", "&I$1,"")&IF(AND(J97<>"Accepted",J97<>"Not Needed",Settings!$F$15="Yes"),", "&J$1,"")&IF(AND(K97<>"Accepted",K97<>"Not Needed",Settings!$G$15="Yes"),", "&K$1,"")&IF(AND(L97<>"Accepted",L97<>"Not Needed",Settings!$H$15="Yes"),", "&L$1,"")&IF(AND(M97<>"Accepted",M97<>"Not Needed",Settings!$I$15="Yes"),", "&M$1,"")&IF(AND(N97<>"Accepted",N97<>"Not Needed",Settings!$J$15="Yes"),", "&N$1,""),3,400))))
A98: 2026-27 | B98: Park Place ES | C98: EAS Elementary | D98: Not Yet Confirmed | G98: Not Received | H98: Not Received | I98: Not Received | J98: Not Received | K98: Not Received | L98: Not Received | M98: Not Received | N98: Not Received | O98: =IF($B98="","",COUNTIF(G98:N98,"Accepted")+COUNTIF(G98:N98,"Received")+COUNTIF(G98:N98,"Needs Correction")) | P98: =IF($B98="","",SUMPRODUCT(((G98:N98="Accepted")+(G98:N98="Not Needed"))*(Settings!$C$11:$J$11="Yes"))) | Q98: =IF($B98="","",SUMPRODUCT(((G98:N98="Accepted")+(G98:N98="Not Needed"))*(Settings!$C$15:$J$15="Yes"))) | R98: =IF($B98="","",IF($D98="No","No PTO/PTA",IF($D98<>"Yes","Not Yet Confirmed",IF($Q98>=Settings!$C$13,"Legalized",IF($P98>=Settings!$C$12,"Registered",IF($O98>0,"In Progress","Not Started")))))) | S98: =IF($B98="","",COUNTIF(G98:N98,"Received")) | T98: =IF($B98="","",COUNTIF(G98:N98,"Needs Correction")) | U98: =IF($B98="","",IF($D98<>"Yes","",IF($Q98>=Settings!$C$13,"None",MID(IF(AND(G98<>"Accepted",G98<>"Not Needed",Settings!$C$15="Yes"),", "&G$1,"")&IF(AND(H98<>"Accepted",H98<>"Not Needed",Settings!$D$15="Yes"),", "&H$1,"")&IF(AND(I98<>"Accepted",I98<>"Not Needed",Settings!$E$15="Yes"),", "&I$1,"")&IF(AND(J98<>"Accepted",J98<>"Not Needed",Settings!$F$15="Yes"),", "&J$1,"")&IF(AND(K98<>"Accepted",K98<>"Not Needed",Settings!$G$15="Yes"),", "&K$1,"")&IF(AND(L98<>"Accepted",L98<>"Not Needed",Settings!$H$15="Yes"),", "&L$1,"")&IF(AND(M98<>"Accepted",M98<>"Not Needed",Settings!$I$15="Yes"),", "&M$1,"")&IF(AND(N98<>"Accepted",N98<>"Not Needed",Settings!$J$15="Yes"),", "&N$1,""),3,400))))
A99: 2026-27 | B99: Parker ES | C99: EAS Elementary | D99: Not Yet Confirmed | G99: Not Received | H99: Not Received | I99: Not Received | J99: Not Received | K99: Not Received | L99: Not Received | M99: Not Received | N99: Not Received | O99: =IF($B99="","",COUNTIF(G99:N99,"Accepted")+COUNTIF(G99:N99,"Received")+COUNTIF(G99:N99,"Needs Correction")) | P99: =IF($B99="","",SUMPRODUCT(((G99:N99="Accepted")+(G99:N99="Not Needed"))*(Settings!$C$11:$J$11="Yes"))) | Q99: =IF($B99="","",SUMPRODUCT(((G99:N99="Accepted")+(G99:N99="Not Needed"))*(Settings!$C$15:$J$15="Yes"))) | R99: =IF($B99="","",IF($D99="No","No PTO/PTA",IF($D99<>"Yes","Not Yet Confirmed",IF($Q99>=Settings!$C$13,"Legalized",IF($P99>=Settings!$C$12,"Registered",IF($O99>0,"In Progress","Not Started")))))) | S99: =IF($B99="","",COUNTIF(G99:N99,"Received")) | T99: =IF($B99="","",COUNTIF(G99:N99,"Needs Correction")) | U99: =IF($B99="","",IF($D99<>"Yes","",IF($Q99>=Settings!$C$13,"None",MID(IF(AND(G99<>"Accepted",G99<>"Not Needed",Settings!$C$15="Yes"),", "&G$1,"")&IF(AND(H99<>"Accepted",H99<>"Not Needed",Settings!$D$15="Yes"),", "&H$1,"")&IF(AND(I99<>"Accepted",I99<>"Not Needed",Settings!$E$15="Yes"),", "&I$1,"")&IF(AND(J99<>"Accepted",J99<>"Not Needed",Settings!$F$15="Yes"),", "&J$1,"")&IF(AND(K99<>"Accepted",K99<>"Not Needed",Settings!$G$15="Yes"),", "&K$1,"")&IF(AND(L99<>"Accepted",L99<>"Not Needed",Settings!$H$15="Yes"),", "&L$1,"")&IF(AND(M99<>"Accepted",M99<>"Not Needed",Settings!$I$15="Yes"),", "&M$1,"")&IF(AND(N99<>"Accepted",N99<>"Not Needed",Settings!$J$15="Yes"),", "&N$1,""),3,400))))
A100: 2026-27 | B100: Patterson ES | C100: EAS Elementary | D100: Not Yet Confirmed | G100: Not Received | H100: Not Received | I100: Not Received | J100: Not Received | K100: Not Received | L100: Not Received | M100: Not Received | N100: Not Received | O100: =IF($B100="","",COUNTIF(G100:N100,"Accepted")+COUNTIF(G100:N100,"Received")+COUNTIF(G100:N100,"Needs Correction")) | P100: =IF($B100="","",SUMPRODUCT(((G100:N100="Accepted")+(G100:N100="Not Needed"))*(Settings!$C$11:$J$11="Yes"))) | Q100: =IF($B100="","",SUMPRODUCT(((G100:N100="Accepted")+(G100:N100="Not Needed"))*(Settings!$C$15:$J$15="Yes"))) | R100: =IF($B100="","",IF($D100="No","No PTO/PTA",IF($D100<>"Yes","Not Yet Confirmed",IF($Q100>=Settings!$C$13,"Legalized",IF($P100>=Settings!$C$12,"Registered",IF($O100>0,"In Progress","Not Started")))))) | S100: =IF($B100="","",COUNTIF(G100:N100,"Received")) | T100: =IF($B100="","",COUNTIF(G100:N100,"Needs Correction")) | U100: =IF($B100="","",IF($D100<>"Yes","",IF($Q100>=Settings!$C$13,"None",MID(IF(AND(G100<>"Accepted",G100<>"Not Needed",Settings!$C$15="Yes"),", "&G$1,"")&IF(AND(H100<>"Accepted",H100<>"Not Needed",Settings!$D$15="Yes"),", "&H$1,"")&IF(AND(I100<>"Accepted",I100<>"Not Needed",Settings!$E$15="Yes"),", "&I$1,"")&IF(AND(J100<>"Accepted",J100<>"Not Needed",Settings!$F$15="Yes"),", "&J$1,"")&IF(AND(K100<>"Accepted",K100<>"Not Needed",Settings!$G$15="Yes"),", "&K$1,"")&IF(AND(L100<>"Accepted",L100<>"Not Needed",Settings!$H$15="Yes"),", "&L$1,"")&IF(AND(M100<>"Accepted",M100<>"Not Needed",Settings!$I$15="Yes"),", "&M$1,"")&IF(AND(N100<>"Accepted",N100<>"Not Needed",Settings!$J$15="Yes"),", "&N$1,""),3,400))))
A101: 2026-27 | B101: Piney Point ES | C101: EAS Elementary | D101: Not Yet Confirmed | G101: Not Received | H101: Not Received | I101: Not Received | J101: Not Received | K101: Not Received | L101: Not Received | M101: Not Received | N101: Not Received | O101: =IF($B101="","",COUNTIF(G101:N101,"Accepted")+COUNTIF(G101:N101,"Received")+COUNTIF(G101:N101,"Needs Correction")) | P101: =IF($B101="","",SUMPRODUCT(((G101:N101="Accepted")+(G101:N101="Not Needed"))*(Settings!$C$11:$J$11="Yes"))) | Q101: =IF($B101="","",SUMPRODUCT(((G101:N101="Accepted")+(G101:N101="Not Needed"))*(Settings!$C$15:$J$15="Yes"))) | R101: =IF($B101="","",IF($D101="No","No PTO/PTA",IF($D101<>"Yes","Not Yet Confirmed",IF($Q101>=Settings!$C$13,"Legalized",IF($P101>=Settings!$C$12,"Registered",IF($O101>0,"In Progress","Not Started")))))) | S101: =IF($B101="","",COUNTIF(G101:N101,"Received")) | T101: =IF($B101="","",COUNTIF(G101:N101,"Needs Correction")) | U101: =IF($B101="","",IF($D101<>"Yes","",IF($Q101>=Settings!$C$13,"None",MID(IF(AND(G101<>"Accepted",G101<>"Not Needed",Settings!$C$15="Yes"),", "&G$1,"")&IF(AND(H101<>"Accepted",H101<>"Not Needed",Settings!$D$15="Yes"),", "&H$1,"")&IF(AND(I101<>"Accepted",I101<>"Not Needed",Settings!$E$15="Yes"),", "&I$1,"")&IF(AND(J101<>"Accepted",J101<>"Not Needed",Settings!$F$15="Yes"),", "&J$1,"")&IF(AND(K101<>"Accepted",K101<>"Not Needed",Settings!$G$15="Yes"),", "&K$1,"")&IF(AND(L101<>"Accepted",L101<>"Not Needed",Settings!$H$15="Yes"),", "&L$1,"")&IF(AND(M101<>"Accepted",M101<>"Not Needed",Settings!$I$15="Yes"),", "&M$1,"")&IF(AND(N101<>"Accepted",N101<>"Not Needed",Settings!$J$15="Yes"),", "&N$1,""),3,400))))
A102: 2026-27 | B102: Poe ES | C102: EAS Elementary | D102: Not Yet Confirmed | G102: Not Received | H102: Not Received | I102: Not Received | J102: Not Received | K102: Not Received | L102: Not Received | M102: Not Received | N102: Not Received | O102: =IF($B102="","",COUNTIF(G102:N102,"Accepted")+COUNTIF(G102:N102,"Received")+COUNTIF(G102:N102,"Needs Correction")) | P102: =IF($B102="","",SUMPRODUCT(((G102:N102="Accepted")+(G102:N102="Not Needed"))*(Settings!$C$11:$J$11="Yes"))) | Q102: =IF($B102="","",SUMPRODUCT(((G102:N102="Accepted")+(G102:N102="Not Needed"))*(Settings!$C$15:$J$15="Yes"))) | R102: =IF($B102="","",IF($D102="No","No PTO/PTA",IF($D102<>"Yes","Not Yet Confirmed",IF($Q102>=Settings!$C$13,"Legalized",IF($P102>=Settings!$C$12,"Registered",IF($O102>0,"In Progress","Not Started")))))) | S102: =IF($B102="","",COUNTIF(G102:N102,"Received")) | T102: =IF($B102="","",COUNTIF(G102:N102,"Needs Correction")) | U102: =IF($B102="","",IF($D102<>"Yes","",IF($Q102>=Settings!$C$13,"None",MID(IF(AND(G102<>"Accepted",G102<>"Not Needed",Settings!$C$15="Yes"),", "&G$1,"")&IF(AND(H102<>"Accepted",H102<>"Not Needed",Settings!$D$15="Yes"),", "&H$1,"")&IF(AND(I102<>"Accepted",I102<>"Not Needed",Settings!$E$15="Yes"),", "&I$1,"")&IF(AND(J102<>"Accepted",J102<>"Not Needed",Settings!$F$15="Yes"),", "&J$1,"")&IF(AND(K102<>"Accepted",K102<>"Not Needed",Settings!$G$15="Yes"),", "&K$1,"")&IF(AND(L102<>"Accepted",L102<>"Not Needed",Settings!$H$15="Yes"),", "&L$1,"")&IF(AND(M102<>"Accepted",M102<>"Not Needed",Settings!$I$15="Yes"),", "&M$1,"")&IF(AND(N102<>"Accepted",N102<>"Not Needed",Settings!$J$15="Yes"),", "&N$1,""),3,400))))
A103: 2026-27 | B103: Red ES | C103: EAS Elementary | D103: Not Yet Confirmed | G103: Not Received | H103: Not Received | I103: Not Received | J103: Not Received | K103: Not Received | L103: Not Received | M103: Not Received | N103: Not Received | O103: =IF($B103="","",COUNTIF(G103:N103,"Accepted")+COUNTIF(G103:N103,"Received")+COUNTIF(G103:N103,"Needs Correction")) | P103: =IF($B103="","",SUMPRODUCT(((G103:N103="Accepted")+(G103:N103="Not Needed"))*(Settings!$C$11:$J$11="Yes"))) | Q103: =IF($B103="","",SUMPRODUCT(((G103:N103="Accepted")+(G103:N103="Not Needed"))*(Settings!$C$15:$J$15="Yes"))) | R103: =IF($B103="","",IF($D103="No","No PTO/PTA",IF($D103<>"Yes","Not Yet Confirmed",IF($Q103>=Settings!$C$13,"Legalized",IF($P103>=Settings!$C$12,"Registered",IF($O103>0,"In Progress","Not Started")))))) | S103: =IF($B103="","",COUNTIF(G103:N103,"Received")) | T103: =IF($B103="","",COUNTIF(G103:N103,"Needs Correction")) | U103: =IF($B103="","",IF($D103<>"Yes","",IF($Q103>=Settings!$C$13,"None",MID(IF(AND(G103<>"Accepted",G103<>"Not Needed",Settings!$C$15="Yes"),", "&G$1,"")&IF(AND(H103<>"Accepted",H103<>"Not Needed",Settings!$D$15="Yes"),", "&H$1,"")&IF(AND(I103<>"Accepted",I103<>"Not Needed",Settings!$E$15="Yes"),", "&I$1,"")&IF(AND(J103<>"Accepted",J103<>"Not Needed",Settings!$F$15="Yes"),", "&J$1,"")&IF(AND(K103<>"Accepted",K103<>"Not Needed",Settings!$G$15="Yes"),", "&K$1,"")&IF(AND(L103<>"Accepted",L103<>"Not Needed",Settings!$H$15="Yes"),", "&L$1,"")&IF(AND(M103<>"Accepted",M103<>"Not Needed",Settings!$I$15="Yes"),", "&M$1,"")&IF(AND(N103<>"Accepted",N103<>"Not Needed",Settings!$J$15="Yes"),", "&N$1,""),3,400))))
A104: 2026-27 | B104: Rice School K-8 | C104: EAS Elementary | D104: Not Yet Confirmed | G104: Not Received | H104: Not Received | I104: Not Received | J104: Not Received | K104: Not Received | L104: Not Received | M104: Not Received | N104: Not Received | O104: =IF($B104="","",COUNTIF(G104:N104,"Accepted")+COUNTIF(G104:N104,"Received")+COUNTIF(G104:N104,"Needs Correction")) | P104: =IF($B104="","",SUMPRODUCT(((G104:N104="Accepted")+(G104:N104="Not Needed"))*(Settings!$C$11:$J$11="Yes"))) | Q104: =IF($B104="","",SUMPRODUCT(((G104:N104="Accepted")+(G104:N104="Not Needed"))*(Settings!$C$15:$J$15="Yes"))) | R104: =IF($B104="","",IF($D104="No","No PTO/PTA",IF($D104<>"Yes","Not Yet Confirmed",IF($Q104>=Settings!$C$13,"Legalized",IF($P104>=Settings!$C$12,"Registered",IF($O104>0,"In Progress","Not Started")))))) | S104: =IF($B104="","",COUNTIF(G104:N104,"Received")) | T104: =IF($B104="","",COUNTIF(G104:N104,"Needs Correction")) | U104: =IF($B104="","",IF($D104<>"Yes","",IF($Q104>=Settings!$C$13,"None",MID(IF(AND(G104<>"Accepted",G104<>"Not Needed",Settings!$C$15="Yes"),", "&G$1,"")&IF(AND(H104<>"Accepted",H104<>"Not Needed",Settings!$D$15="Yes"),", "&H$1,"")&IF(AND(I104<>"Accepted",I104<>"Not Needed",Settings!$E$15="Yes"),", "&I$1,"")&IF(AND(J104<>"Accepted",J104<>"Not Needed",Settings!$F$15="Yes"),", "&J$1,"")&IF(AND(K104<>"Accepted",K104<>"Not Needed",Settings!$G$15="Yes"),", "&K$1,"")&IF(AND(L104<>"Accepted",L104<>"Not Needed",Settings!$H$15="Yes"),", "&L$1,"")&IF(AND(M104<>"Accepted",M104<>"Not Needed",Settings!$I$15="Yes"),", "&M$1,"")&IF(AND(N104<>"Accepted",N104<>"Not Needed",Settings!$J$15="Yes"),", "&N$1,""),3,400))))
A105: 2026-27 | B105: River Oaks ES | C105: EAS Elementary | D105: Not Yet Confirmed | G105: Not Received | H105: Not Received | I105: Not Received | J105: Not Received | K105: Not Received | L105: Not Received | M105: Not Received | N105: Not Received | O105: =IF($B105="","",COUNTIF(G105:N105,"Accepted")+COUNTIF(G105:N105,"Received")+COUNTIF(G105:N105,"Needs Correction")) | P105: =IF($B105="","",SUMPRODUCT(((G105:N105="Accepted")+(G105:N105="Not Needed"))*(Settings!$C$11:$J$11="Yes"))) | Q105: =IF($B105="","",SUMPRODUCT(((G105:N105="Accepted")+(G105:N105="Not Needed"))*(Settings!$C$15:$J$15="Yes"))) | R105: =IF($B105="","",IF($D105="No","No PTO/PTA",IF($D105<>"Yes","Not Yet Confirmed",IF($Q105>=Settings!$C$13,"Legalized",IF($P105>=Settings!$C$12,"Registered",IF($O105>0,"In Progress","Not Started")))))) | S105: =IF($B105="","",COUNTIF(G105:N105,"Received")) | T105: =IF($B105="","",COUNTIF(G105:N105,"Needs Correction")) | U105: =IF($B105="","",IF($D105<>"Yes","",IF($Q105>=Settings!$C$13,"None",MID(IF(AND(G105<>"Accepted",G105<>"Not Needed",Settings!$C$15="Yes"),", "&G$1,"")&IF(AND(H105<>"Accepted",H105<>"Not Needed",Settings!$D$15="Yes"),", "&H$1,"")&IF(AND(I105<>"Accepted",I105<>"Not Needed",Settings!$E$15="Yes"),", "&I$1,"")&IF(AND(J105<>"Accepted",J105<>"Not Needed",Settings!$F$15="Yes"),", "&J$1,"")&IF(AND(K105<>"Accepted",K105<>"Not Needed",Settings!$G$15="Yes"),", "&K$1,"")&IF(AND(L105<>"Accepted",L105<>"Not Needed",Settings!$H$15="Yes"),", "&L$1,"")&IF(AND(M105<>"Accepted",M105<>"Not Needed",Settings!$I$15="Yes"),", "&M$1,"")&IF(AND(N105<>"Accepted",N105<>"Not Needed",Settings!$J$15="Yes"),", "&N$1,""),3,400))))
A106: 2026-27 | B106: Roberts ES | C106: EAS Elementary | D106: Not Yet Confirmed | G106: Not Received | H106: Not Received | I106: Not Received | J106: Not Received | K106: Not Received | L106: Not Received | M106: Not Received | N106: Not Received | O106: =IF($B106="","",COUNTIF(G106:N106,"Accepted")+COUNTIF(G106:N106,"Received")+COUNTIF(G106:N106,"Needs Correction")) | P106: =IF($B106="","",SUMPRODUCT(((G106:N106="Accepted")+(G106:N106="Not Needed"))*(Settings!$C$11:$J$11="Yes"))) | Q106: =IF($B106="","",SUMPRODUCT(((G106:N106="Accepted")+(G106:N106="Not Needed"))*(Settings!$C$15:$J$15="Yes"))) | R106: =IF($B106="","",IF($D106="No","No PTO/PTA",IF($D106<>"Yes","Not Yet Confirmed",IF($Q106>=Settings!$C$13,"Legalized",IF($P106>=Settings!$C$12,"Registered",IF($O106>0,"In Progress","Not Started")))))) | S106: =IF($B106="","",COUNTIF(G106:N106,"Received")) | T106: =IF($B106="","",COUNTIF(G106:N106,"Needs Correction")) | U106: =IF($B106="","",IF($D106<>"Yes","",IF($Q106>=Settings!$C$13,"None",MID(IF(AND(G106<>"Accepted",G106<>"Not Needed",Settings!$C$15="Yes"),", "&G$1,"")&IF(AND(H106<>"Accepted",H106<>"Not Needed",Settings!$D$15="Yes"),", "&H$1,"")&IF(AND(I106<>"Accepted",I106<>"Not Needed",Settings!$E$15="Yes"),", "&I$1,"")&IF(AND(J106<>"Accepted",J106<>"Not Needed",Settings!$F$15="Yes"),", "&J$1,"")&IF(AND(K106<>"Accepted",K106<>"Not Needed",Settings!$G$15="Yes"),", "&K$1,"")&IF(AND(L106<>"Accepted",L106<>"Not Needed",Settings!$H$15="Yes"),", "&L$1,"")&IF(AND(M106<>"Accepted",M106<>"Not Needed",Settings!$I$15="Yes"),", "&M$1,"")&IF(AND(N106<>"Accepted",N106<>"Not Needed",Settings!$J$15="Yes"),", "&N$1,""),3,400))))
A107: 2026-27 | B107: Rogers T H | C107: EAS Elementary | D107: Not Yet Confirmed | G107: Not Received | H107: Not Received | I107: Not Received | J107: Not Received | K107: Not Received | L107: Not Received | M107: Not Received | N107: Not Received | O107: =IF($B107="","",COUNTIF(G107:N107,"Accepted")+COUNTIF(G107:N107,"Received")+COUNTIF(G107:N107,"Needs Correction")) | P107: =IF($B107="","",SUMPRODUCT(((G107:N107="Accepted")+(G107:N107="Not Needed"))*(Settings!$C$11:$J$11="Yes"))) | Q107: =IF($B107="","",SUMPRODUCT(((G107:N107="Accepted")+(G107:N107="Not Needed"))*(Settings!$C$15:$J$15="Yes"))) | R107: =IF($B107="","",IF($D107="No","No PTO/PTA",IF($D107<>"Yes","Not Yet Confirmed",IF($Q107>=Settings!$C$13,"Legalized",IF($P107>=Settings!$C$12,"Registered",IF($O107>0,"In Progress","Not Started")))))) | S107: =IF($B107="","",COUNTIF(G107:N107,"Received")) | T107: =IF($B107="","",COUNTIF(G107:N107,"Needs Correction")) | U107: =IF($B107="","",IF($D107<>"Yes","",IF($Q107>=Settings!$C$13,"None",MID(IF(AND(G107<>"Accepted",G107<>"Not Needed",Settings!$C$15="Yes"),", "&G$1,"")&IF(AND(H107<>"Accepted",H107<>"Not Needed",Settings!$D$15="Yes"),", "&H$1,"")&IF(AND(I107<>"Accepted",I107<>"Not Needed",Settings!$E$15="Yes"),", "&I$1,"")&IF(AND(J107<>"Accepted",J107<>"Not Needed",Settings!$F$15="Yes"),", "&J$1,"")&IF(AND(K107<>"Accepted",K107<>"Not Needed",Settings!$G$15="Yes"),", "&K$1,"")&IF(AND(L107<>"Accepted",L107<>"Not Needed",Settings!$H$15="Yes"),", "&L$1,"")&IF(AND(M107<>"Accepted",M107<>"Not Needed",Settings!$I$15="Yes"),", "&M$1,"")&IF(AND(N107<>"Accepted",N107<>"Not Needed",Settings!$J$15="Yes"),", "&N$1,""),3,400))))
A108: 2026-27 | B108: Roosevelt ES | C108: EAS Elementary | D108: Not Yet Confirmed | G108: Not Received | H108: Not Received | I108: Not Received | J108: Not Received | K108: Not Received | L108: Not Received | M108: Not Received | N108: Not Received | O108: =IF($B108="","",COUNTIF(G108:N108,"Accepted")+COUNTIF(G108:N108,"Received")+COUNTIF(G108:N108,"Needs Correction")) | P108: =IF($B108="","",SUMPRODUCT(((G108:N108="Accepted")+(G108:N108="Not Needed"))*(Settings!$C$11:$J$11="Yes"))) | Q108: =IF($B108="","",SUMPRODUCT(((G108:N108="Accepted")+(G108:N108="Not Needed"))*(Settings!$C$15:$J$15="Yes"))) | R108: =IF($B108="","",IF($D108="No","No PTO/PTA",IF($D108<>"Yes","Not Yet Confirmed",IF($Q108>=Settings!$C$13,"Legalized",IF($P108>=Settings!$C$12,"Registered",IF($O108>0,"In Progress","Not Started")))))) | S108: =IF($B108="","",COUNTIF(G108:N108,"Received")) | T108: =IF($B108="","",COUNTIF(G108:N108,"Needs Correction")) | U108: =IF($B108="","",IF($D108<>"Yes","",IF($Q108>=Settings!$C$13,"None",MID(IF(AND(G108<>"Accepted",G108<>"Not Needed",Settings!$C$15="Yes"),", "&G$1,"")&IF(AND(H108<>"Accepted",H108<>"Not Needed",Settings!$D$15="Yes"),", "&H$1,"")&IF(AND(I108<>"Accepted",I108<>"Not Needed",Settings!$E$15="Yes"),", "&I$1,"")&IF(AND(J108<>"Accepted",J108<>"Not Needed",Settings!$F$15="Yes"),", "&J$1,"")&IF(AND(K108<>"Accepted",K108<>"Not Needed",Settings!$G$15="Yes"),", "&K$1,"")&IF(AND(L108<>"Accepted",L108<>"Not Needed",Settings!$H$15="Yes"),", "&L$1,"")&IF(AND(M108<>"Accepted",M108<>"Not Needed",Settings!$I$15="Yes"),", "&M$1,"")&IF(AND(N108<>"Accepted",N108<>"Not Needed",Settings!$J$15="Yes"),", "&N$1,""),3,400))))
A109: 2026-27 | B109: Scarborough ES | C109: EAS Elementary | D109: Not Yet Confirmed | G109: Not Received | H109: Not Received | I109: Not Received | J109: Not Received | K109: Not Received | L109: Not Received | M109: Not Received | N109: Not Received | O109: =IF($B109="","",COUNTIF(G109:N109,"Accepted")+COUNTIF(G109:N109,"Received")+COUNTIF(G109:N109,"Needs Correction")) | P109: =IF($B109="","",SUMPRODUCT(((G109:N109="Accepted")+(G109:N109="Not Needed"))*(Settings!$C$11:$J$11="Yes"))) | Q109: =IF($B109="","",SUMPRODUCT(((G109:N109="Accepted")+(G109:N109="Not Needed"))*(Settings!$C$15:$J$15="Yes"))) | R109: =IF($B109="","",IF($D109="No","No PTO/PTA",IF($D109<>"Yes","Not Yet Confirmed",IF($Q109>=Settings!$C$13,"Legalized",IF($P109>=Settings!$C$12,"Registered",IF($O109>0,"In Progress","Not Started")))))) | S109: =IF($B109="","",COUNTIF(G109:N109,"Received")) | T109: =IF($B109="","",COUNTIF(G109:N109,"Needs Correction")) | U109: =IF($B109="","",IF($D109<>"Yes","",IF($Q109>=Settings!$C$13,"None",MID(IF(AND(G109<>"Accepted",G109<>"Not Needed",Settings!$C$15="Yes"),", "&G$1,"")&IF(AND(H109<>"Accepted",H109<>"Not Needed",Settings!$D$15="Yes"),", "&H$1,"")&IF(AND(I109<>"Accepted",I109<>"Not Needed",Settings!$E$15="Yes"),", "&I$1,"")&IF(AND(J109<>"Accepted",J109<>"Not Needed",Settings!$F$15="Yes"),", "&J$1,"")&IF(AND(K109<>"Accepted",K109<>"Not Needed",Settings!$G$15="Yes"),", "&K$1,"")&IF(AND(L109<>"Accepted",L109<>"Not Needed",Settings!$H$15="Yes"),", "&L$1,"")&IF(AND(M109<>"Accepted",M109<>"Not Needed",Settings!$I$15="Yes"),", "&M$1,"")&IF(AND(N109<>"Accepted",N109<>"Not Needed",Settings!$J$15="Yes"),", "&N$1,""),3,400))))
... A115: 2026-27 | B115: Sutton ES | C115: EAS Elementary | D115: Not Yet Confirmed | G115: Not Received | H115: Not Received | I115: Not Received | J115: Not Received | K115: Not Received | L115: Not Received | M115: Not Received | N115: Not Received | O115: =IF($B115="","",COUNTIF(G115:N115,"Accepted")+COUNTIF(G115:N115,"Received")+COUNTIF(G115:N115,"Needs Correction")) | P115: =IF($B115="","",SUMPRODUCT(((G115:N115="Accepted")+(G115:N115="Not Needed"))*(Settings!$C$11:$J$11="Yes"))) | Q115: =IF($B115="","",SUMPRODUCT(((G115:N115="Accepted")+(G115:N115="Not Needed"))*(Settings!$C$15:$J$15="Yes"))) | R115: =IF($B115="","",IF($D115="No","No PTO/PTA",IF($D115<>"Yes","Not Yet Confirmed",IF($Q115>=Settings!$C$13,"Legalized",IF($P115>=Settings!$C$12,"Registered",IF($O115>0,"In Progress","Not Started")))))) | S115: =IF($B115="","",COUNTIF(G115:N115,"Received")) | T115: =IF($B115="","",COUNTIF(G115:N115,"Needs Correction")) | U115: =IF($B115="","",IF($D115<>"Yes","",IF($Q115>=Settings!$C$13,"None",MID(IF(AND(G115<>"Accepted",G115<>"Not Needed",Settings!$C$15="Yes"),", "&G$1,"")&IF(AND(H115<>"Accepted",H115<>"Not Needed",Settings!$D$15="Yes"),", "&H$1,"")&IF(AND(I115<>"Accepted",I115<>"Not Needed",Settings!$E$15="Yes"),", "&I$1,"")&IF(AND(J115<>"Accepted",J115<>"Not Needed",Settings!$F$15="Yes"),", "&J$1,"")&IF(AND(K115<>"Accepted",K115<>"Not Needed",Settings!$G$15="Yes"),", "&K$1,"")&IF(AND(L115<>"Accepted",L115<>"Not Needed",Settings!$H$15="Yes"),", "&L$1,"")&IF(AND(M115<>"Accepted",M115<>"Not Needed",Settings!$I$15="Yes"),", "&M$1,"")&IF(AND(N115<>"Accepted",N115<>"Not Needed",Settings!$J$15="Yes"),", "&N$1,""),3,400))))
A116: 2026-27 | B116: Tijerina ES | C116: EAS Elementary | D116: Yes | E116: PTA | G116: Accepted | H116: Not Received | I116: Not Received | J116: Not Received | K116: Accepted | L116: Accepted | M116: Not Received | N116: Not Received | O116: =IF($B116="","",COUNTIF(G116:N116,"Accepted")+COUNTIF(G116:N116,"Received")+COUNTIF(G116:N116,"Needs Correction")) | P116: =IF($B116="","",SUMPRODUCT(((G116:N116="Accepted")+(G116:N116="Not Needed"))*(Settings!$C$11:$J$11="Yes"))) | Q116: =IF($B116="","",SUMPRODUCT(((G116:N116="Accepted")+(G116:N116="Not Needed"))*(Settings!$C$15:$J$15="Yes"))) | R116: =IF($B116="","",IF($D116="No","No PTO/PTA",IF($D116<>"Yes","Not Yet Confirmed",IF($Q116>=Settings!$C$13,"Legalized",IF($P116>=Settings!$C$12,"Registered",IF($O116>0,"In Progress","Not Started")))))) | S116: =IF($B116="","",COUNTIF(G116:N116,"Received")) | T116: =IF($B116="","",COUNTIF(G116:N116,"Needs Correction")) | U116: =IF($B116="","",IF($D116<>"Yes","",IF($Q116>=Settings!$C$13,"None",MID(IF(AND(G116<>"Accepted",G116<>"Not Needed",Settings!$C$15="Yes"),", "&G$1,"")&IF(AND(H116<>"Accepted",H116<>"Not Needed",Settings!$D$15="Yes"),", "&H$1,"")&IF(AND(I116<>"Accepted",I116<>"Not Needed",Settings!$E$15="Yes"),", "&I$1,"")&IF(AND(J116<>"Accepted",J116<>"Not Needed",Settings!$F$15="Yes"),", "&J$1,"")&IF(AND(K116<>"Accepted",K116<>"Not Needed",Settings!$G$15="Yes"),", "&K$1,"")&IF(AND(L116<>"Accepted",L116<>"Not Needed",Settings!$H$15="Yes"),", "&L$1,"")&IF(AND(M116<>"Accepted",M116<>"Not Needed",Settings!$I$15="Yes"),", "&M$1,"")&IF(AND(N116<>"Accepted",N116<>"Not Needed",Settings!$J$15="Yes"),", "&N$1,""),3,400))))
A117: 2026-27 | B117: Travis ES | C117: EAS Elementary | D117: Yes | E117: PTA | G117: Accepted | H117: Not Received | I117: Not Received | J117: Accepted | K117: Accepted | L117: Accepted | M117: Not Received | N117: Not Received | O117: =IF($B117="","",COUNTIF(G117:N117,"Accepted")+COUNTIF(G117:N117,"Received")+COUNTIF(G117:N117,"Needs Correction")) | P117: =IF($B117="","",SUMPRODUCT(((G117:N117="Accepted")+(G117:N117="Not Needed"))*(Settings!$C$11:$J$11="Yes"))) | Q117: =IF($B117="","",SUMPRODUCT(((G117:N117="Accepted")+(G117:N117="Not Needed"))*(Settings!$C$15:$J$15="Yes"))) | R117: =IF($B117="","",IF($D117="No","No PTO/PTA",IF($D117<>"Yes","Not Yet Confirmed",IF($Q117>=Settings!$C$13,"Legalized",IF($P117>=Settings!$C$12,"Registered",IF($O117>0,"In Progress","Not Started")))))) | S117: =IF($B117="","",COUNTIF(G117:N117,"Received")) | T117: =IF($B117="","",COUNTIF(G117:N117,"Needs Correction")) | U117: =IF($B117="","",IF($D117<>"Yes","",IF($Q117>=Settings!$C$13,"None",MID(IF(AND(G117<>"Accepted",G117<>"Not Needed",Settings!$C$15="Yes"),", "&G$1,"")&IF(AND(H117<>"Accepted",H117<>"Not Needed",Settings!$D$15="Yes"),", "&H$1,"")&IF(AND(I117<>"Accepted",I117<>"Not Needed",Settings!$E$15="Yes"),", "&I$1,"")&IF(AND(J117<>"Accepted",J117<>"Not Needed",Settings!$F$15="Yes"),", "&J$1,"")&IF(AND(K117<>"Accepted",K117<>"Not Needed",Settings!$G$15="Yes"),", "&K$1,"")&IF(AND(L117<>"Accepted",L117<>"Not Needed",Settings!$H$15="Yes"),", "&L$1,"")&IF(AND(M117<>"Accepted",M117<>"Not Needed",Settings!$I$15="Yes"),", "&M$1,"")&IF(AND(N117<>"Accepted",N117<>"Not Needed",Settings!$J$15="Yes"),", "&N$1,""),3,400))))
A118: 2026-27 | B118: Twain ES | C118: EAS Elementary | D118: Not Yet Confirmed | G118: Not Received | H118: Not Received | I118: Not Received | J118: Not Received | K118: Not Received | L118: Not Received | M118: Not Received | N118: Not Received | O118: =IF($B118="","",COUNTIF(G118:N118,"Accepted")+COUNTIF(G118:N118,"Received")+COUNTIF(G118:N118,"Needs Correction")) | P118: =IF($B118="","",SUMPRODUCT(((G118:N118="Accepted")+(G118:N118="Not Needed"))*(Settings!$C$11:$J$11="Yes"))) | Q118: =IF($B118="","",SUMPRODUCT(((G118:N118="Accepted")+(G118:N118="Not Needed"))*(Settings!$C$15:$J$15="Yes"))) | R118: =IF($B118="","",IF($D118="No","No PTO/PTA",IF($D118<>"Yes","Not Yet Confirmed",IF($Q118>=Settings!$C$13,"Legalized",IF($P118>=Settings!$C$12,"Registered",IF($O118>0,"In Progress","Not Started")))))) | S118: =IF($B118="","",COUNTIF(G118:N118,"Received")) | T118: =IF($B118="","",COUNTIF(G118:N118,"Needs Correction")) | U118: =IF($B118="","",IF($D118<>"Yes","",IF($Q118>=Settings!$C$13,"None",MID(IF(AND(G118<>"Accepted",G118<>"Not Needed",Settings!$C$15="Yes"),", "&G$1,"")&IF(AND(H118<>"Accepted",H118<>"Not Needed",Settings!$D$15="Yes"),", "&H$1,"")&IF(AND(I118<>"Accepted",I118<>"Not Needed",Settings!$E$15="Yes"),", "&I$1,"")&IF(AND(J118<>"Accepted",J118<>"Not Needed",Settings!$F$15="Yes"),", "&J$1,"")&IF(AND(K118<>"Accepted",K118<>"Not Needed",Settings!$G$15="Yes"),", "&K$1,"")&IF(AND(L118<>"Accepted",L118<>"Not Needed",Settings!$H$15="Yes"),", "&L$1,"")&IF(AND(M118<>"Accepted",M118<>"Not Needed",Settings!$I$15="Yes"),", "&M$1,"")&IF(AND(N118<>"Accepted",N118<>"Not Needed",Settings!$J$15="Yes"),", "&N$1,""),3,400))))
A119: 2026-27 | B119: West University ES | C119: EAS Elementary | D119: Not Yet Confirmed | G119: Not Received | H119: Not Received | I119: Not Received | J119: Not Received | K119: Not Received | L119: Not Received | M119: Not Received | N119: Not Received | O119: =IF($B119="","",COUNTIF(G119:N119,"Accepted")+COUNTIF(G119:N119,"Received")+COUNTIF(G119:N119,"Needs Correction")) | P119: =IF($B119="","",SUMPRODUCT(((G119:N119="Accepted")+(G119:N119="Not Needed"))*(Settings!$C$11:$J$11="Yes"))) | Q119: =IF($B119="","",SUMPRODUCT(((G119:N119="Accepted")+(G119:N119="Not Needed"))*(Settings!$C$15:$J$15="Yes"))) | R119: =IF($B119="","",IF($D119="No","No PTO/PTA",IF($D119<>"Yes","Not Yet Confirmed",IF($Q119>=Settings!$C$13,"Legalized",IF($P119>=Settings!$C$12,"Registered",IF($O119>0,"In Progress","Not Started")))))) | S119: =IF($B119="","",COUNTIF(G119:N119,"Received")) | T119: =IF($B119="","",COUNTIF(G119:N119,"Needs Correction")) | U119: =IF($B119="","",IF($D119<>"Yes","",IF($Q119>=Settings!$C$13,"None",MID(IF(AND(G119<>"Accepted",G119<>"Not Needed",Settings!$C$15="Yes"),", "&G$1,"")&IF(AND(H119<>"Accepted",H119<>"Not Needed",Settings!$D$15="Yes"),", "&H$1,"")&IF(AND(I119<>"Accepted",I119<>"Not Needed",Settings!$E$15="Yes"),", "&I$1,"")&IF(AND(J119<>"Accepted",J119<>"Not Needed",Settings!$F$15="Yes"),", "&J$1,"")&IF(AND(K119<>"Accepted",K119<>"Not Needed",Settings!$G$15="Yes"),", "&K$1,"")&IF(AND(L119<>"Accepted",L119<>"Not Needed",Settings!$H$15="Yes"),", "&L$1,"")&IF(AND(M119<>"Accepted",M119<>"Not Needed",Settings!$I$15="Yes"),", "&M$1,"")&IF(AND(N119<>"Accepted",N119<>"Not Needed",Settings!$J$15="Yes"),", "&N$1,""),3,400))))
A120: 2026-27 | B120: Wharton K-8 | C120: EAS Elementary | D120: Not Yet Confirmed | G120: Not Received | H120: Not Received | I120: Not Received | J120: Not Received | K120: Not Received | L120: Not Received | M120: Not Received | N120: Not Received | O120: =IF($B120="","",COUNTIF(G120:N120,"Accepted")+COUNTIF(G120:N120,"Received")+COUNTIF(G120:N120,"Needs Correction")) | P120: =IF($B120="","",SUMPRODUCT(((G120:N120="Accepted")+(G120:N120="Not Needed"))*(Settings!$C$11:$J$11="Yes"))) | Q120: =IF($B120="","",SUMPRODUCT(((G120:N120="Accepted")+(G120:N120="Not Needed"))*(Settings!$C$15:$J$15="Yes"))) | R120: =IF($B120="","",IF($D120="No","No PTO/PTA",IF($D120<>"Yes","Not Yet Confirmed",IF($Q120>=Settings!$C$13,"Legalized",IF($P120>=Settings!$C$12,"Registered",IF($O120>0,"In Progress","Not Started")))))) | S120: =IF($B120="","",COUNTIF(G120:N120,"Received")) | T120: =IF($B120="","",COUNTIF(G120:N120,"Needs Correction")) | U120: =IF($B120="","",IF($D120<>"Yes","",IF($Q120>=Settings!$C$13,"None",MID(IF(AND(G120<>"Accepted",G120<>"Not Needed",Settings!$C$15="Yes"),", "&G$1,"")&IF(AND(H120<>"Accepted",H120<>"Not Needed",Settings!$D$15="Yes"),", "&H$1,"")&IF(AND(I120<>"Accepted",I120<>"Not Needed",Settings!$E$15="Yes"),", "&I$1,"")&IF(AND(J120<>"Accepted",J120<>"Not Needed",Settings!$F$15="Yes"),", "&J$1,"")&IF(AND(K120<>"Accepted",K120<>"Not Needed",Settings!$G$15="Yes"),", "&K$1,"")&IF(AND(L120<>"Accepted",L120<>"Not Needed",Settings!$H$15="Yes"),", "&L$1,"")&IF(AND(M120<>"Accepted",M120<>"Not Needed",Settings!$I$15="Yes"),", "&M$1,"")&IF(AND(N120<>"Accepted",N120<>"Not Needed",Settings!$J$15="Yes"),", "&N$1,""),3,400))))
A121: 2026-27 | B121: White M ES | C121: EAS Elementary | D121: Not Yet Confirmed | G121: Not Received | H121: Not Received | I121: Not Received | J121: Not Received | K121: Not Received | L121: Not Received | M121: Not Received | N121: Not Received | O121: =IF($B121="","",COUNTIF(G121:N121,"Accepted")+COUNTIF(G121:N121,"Received")+COUNTIF(G121:N121,"Needs Correction")) | P121: =IF($B121="","",SUMPRODUCT(((G121:N121="Accepted")+(G121:N121="Not Needed"))*(Settings!$C$11:$J$11="Yes"))) | Q121: =IF($B121="","",SUMPRODUCT(((G121:N121="Accepted")+(G121:N121="Not Needed"))*(Settings!$C$15:$J$15="Yes"))) | R121: =IF($B121="","",IF($D121="No","No PTO/PTA",IF($D121<>"Yes","Not Yet Confirmed",IF($Q121>=Settings!$C$13,"Legalized",IF($P121>=Settings!$C$12,"Registered",IF($O121>0,"In Progress","Not Started")))))) | S121: =IF($B121="","",COUNTIF(G121:N121,"Received")) | T121: =IF($B121="","",COUNTIF(G121:N121,"Needs Correction")) | U121: =IF($B121="","",IF($D121<>"Yes","",IF($Q121>=Settings!$C$13,"None",MID(IF(AND(G121<>"Accepted",G121<>"Not Needed",Settings!$C$15="Yes"),", "&G$1,"")&IF(AND(H121<>"Accepted",H121<>"Not Needed",Settings!$D$15="Yes"),", "&H$1,"")&IF(AND(I121<>"Accepted",I121<>"Not Needed",Settings!$E$15="Yes"),", "&I$1,"")&IF(AND(J121<>"Accepted",J121<>"Not Needed",Settings!$F$15="Yes"),", "&J$1,"")&IF(AND(K121<>"Accepted",K121<>"Not Needed",Settings!$G$15="Yes"),", "&K$1,"")&IF(AND(L121<>"Accepted",L121<>"Not Needed",Settings!$H$15="Yes"),", "&L$1,"")&IF(AND(M121<>"Accepted",M121<>"Not Needed",Settings!$I$15="Yes"),", "&M$1,"")&IF(AND(N121<>"Accepted",N121<>"Not Needed",Settings!$J$15="Yes"),", "&N$1,""),3,400))))
A122: 2026-27 | B122: Baylor College MS | C122: EAS Secondary | D122: Not Yet Confirmed | G122: Not Received | H122: Not Received | I122: Not Received | J122: Not Received | K122: Not Received | L122: Not Received | M122: Not Received | N122: Not Received | O122: =IF($B122="","",COUNTIF(G122:N122,"Accepted")+COUNTIF(G122:N122,"Received")+COUNTIF(G122:N122,"Needs Correction")) | P122: =IF($B122="","",SUMPRODUCT(((G122:N122="Accepted")+(G122:N122="Not Needed"))*(Settings!$C$11:$J$11="Yes"))) | Q122: =IF($B122="","",SUMPRODUCT(((G122:N122="Accepted")+(G122:N122="Not Needed"))*(Settings!$C$15:$J$15="Yes"))) | R122: =IF($B122="","",IF($D122="No","No PTO/PTA",IF($D122<>"Yes","Not Yet Confirmed",IF($Q122>=Settings!$C$13,"Legalized",IF($P122>=Settings!$C$12,"Registered",IF($O122>0,"In Progress","Not Started")))))) | S122: =IF($B122="","",COUNTIF(G122:N122,"Received")) | T122: =IF($B122="","",COUNTIF(G122:N122,"Needs Correction")) | U122: =IF($B122="","",IF($D122<>"Yes","",IF($Q122>=Settings!$C$13,"None",MID(IF(AND(G122<>"Accepted",G122<>"Not Needed",Settings!$C$15="Yes"),", "&G$1,"")&IF(AND(H122<>"Accepted",H122<>"Not Needed",Settings!$D$15="Yes"),", "&H$1,"")&IF(AND(I122<>"Accepted",I122<>"Not Needed",Settings!$E$15="Yes"),", "&I$1,"")&IF(AND(J122<>"Accepted",J122<>"Not Needed",Settings!$F$15="Yes"),", "&J$1,"")&IF(AND(K122<>"Accepted",K122<>"Not Needed",Settings!$G$15="Yes"),", "&K$1,"")&IF(AND(L122<>"Accepted",L122<>"Not Needed",Settings!$H$15="Yes"),", "&L$1,"")&IF(AND(M122<>"Accepted",M122<>"Not Needed",Settings!$I$15="Yes"),", "&M$1,"")&IF(AND(N122<>"Accepted",N122<>"Not Needed",Settings!$J$15="Yes"),", "&N$1,""),3,400))))
A123: 2026-27 | B123: BCM Biotech Acad at Rusk | C123: EAS Secondary | D123: Not Yet Confirmed | G123: Not Received | H123: Not Received | I123: Not Received | J123: Not Received | K123: Not Received | L123: Not Received | M123: Not Received | N123: Not Received | O123: =IF($B123="","",COUNTIF(G123:N123,"Accepted")+COUNTIF(G123:N123,"Received")+COUNTIF(G123:N123,"Needs Correction")) | P123: =IF($B123="","",SUMPRODUCT(((G123:N123="Accepted")+(G123:N123="Not Needed"))*(Settings!$C$11:$J$11="Yes"))) | Q123: =IF($B123="","",SUMPRODUCT(((G123:N123="Accepted")+(G123:N123="Not Needed"))*(Settings!$C$15:$J$15="Yes"))) | R123: =IF($B123="","",IF($D123="No","No PTO/PTA",IF($D123<>"Yes","Not Yet Confirmed",IF($Q123>=Settings!$C$13,"Legalized",IF($P123>=Settings!$C$12,"Registered",IF($O123>0,"In Progress","Not Started")))))) | S123: =IF($B123="","",COUNTIF(G123:N123,"Received")) | T123: =IF($B123="","",COUNTIF(G123:N123,"Needs Correction")) | U123: =IF($B123="","",IF($D123<>"Yes","",IF($Q123>=Settings!$C$13,"None",MID(IF(AND(G123<>"Accepted",G123<>"Not Needed",Settings!$C$15="Yes"),", "&G$1,"")&IF(AND(H123<>"Accepted",H123<>"Not Needed",Settings!$D$15="Yes"),", "&H$1,"")&IF(AND(I123<>"Accepted",I123<>"Not Needed",Settings!$E$15="Yes"),", "&I$1,"")&IF(AND(J123<>"Accepted",J123<>"Not Needed",Settings!$F$15="Yes"),", "&J$1,"")&IF(AND(K123<>"Accepted",K123<>"Not Needed",Settings!$G$15="Yes"),", "&K$1,"")&IF(AND(L123<>"Accepted",L123<>"Not Needed",Settings!$H$15="Yes"),", "&L$1,"")&IF(AND(M123<>"Accepted",M123<>"Not Needed",Settings!$I$15="Yes"),", "&M$1,"")&IF(AND(N123<>"Accepted",N123<>"Not Needed",Settings!$J$15="Yes"),", "&N$1,""),3,400))))
A124: 2026-27 | B124: Bellaire HS | C124: EAS Secondary | D124: Not Yet Confirmed | G124: Not Received | H124: Not Received | I124: Not Received | J124: Not Received | K124: Not Received | L124: Not Received | M124: Not Received | N124: Not Received | O124: =IF($B124="","",COUNTIF(G124:N124,"Accepted")+COUNTIF(G124:N124,"Received")+COUNTIF(G124:N124,"Needs Correction")) | P124: =IF($B124="","",SUMPRODUCT(((G124:N124="Accepted")+(G124:N124="Not Needed"))*(Settings!$C$11:$J$11="Yes"))) | Q124: =IF($B124="","",SUMPRODUCT(((G124:N124="Accepted")+(G124:N124="Not Needed"))*(Settings!$C$15:$J$15="Yes"))) | R124: =IF($B124="","",IF($D124="No","No PTO/PTA",IF($D124<>"Yes","Not Yet Confirmed",IF($Q124>=Settings!$C$13,"Legalized",IF($P124>=Settings!$C$12,"Registered",IF($O124>0,"In Progress","Not Started")))))) | S124: =IF($B124="","",COUNTIF(G124:N124,"Received")) | T124: =IF($B124="","",COUNTIF(G124:N124,"Needs Correction")) | U124: =IF($B124="","",IF($D124<>"Yes","",IF($Q124>=Settings!$C$13,"None",MID(IF(AND(G124<>"Accepted",G124<>"Not Needed",Settings!$C$15="Yes"),", "&G$1,"")&IF(AND(H124<>"Accepted",H124<>"Not Needed",Settings!$D$15="Yes"),", "&H$1,"")&IF(AND(I124<>"Accepted",I124<>"Not Needed",Settings!$E$15="Yes"),", "&I$1,"")&IF(AND(J124<>"Accepted",J124<>"Not Needed",Settings!$F$15="Yes"),", "&J$1,"")&IF(AND(K124<>"Accepted",K124<>"Not Needed",Settings!$G$15="Yes"),", "&K$1,"")&IF(AND(L124<>"Accepted",L124<>"Not Needed",Settings!$H$15="Yes"),", "&L$1,"")&IF(AND(M124<>"Accepted",M124<>"Not Needed",Settings!$I$15="Yes"),", "&M$1,"")&IF(AND(N124<>"Accepted",N124<>"Not Needed",Settings!$J$15="Yes"),", "&N$1,""),3,400))))
A125: 2026-27 | B125: Black MS | C125: EAS Secondary | D125: Not Yet Confirmed | G125: Not Received | H125: Not Received | I125: Not Received | J125: Not Received | K125: Not Received | L125: Not Received | M125: Not Received | N125: Not Received | O125: =IF($B125="","",COUNTIF(G125:N125,"Accepted")+COUNTIF(G125:N125,"Received")+COUNTIF(G125:N125,"Needs Correction")) | P125: =IF($B125="","",SUMPRODUCT(((G125:N125="Accepted")+(G125:N125="Not Needed"))*(Settings!$C$11:$J$11="Yes"))) | Q125: =IF($B125="","",SUMPRODUCT(((G125:N125="Accepted")+(G125:N125="Not Needed"))*(Settings!$C$15:$J$15="Yes"))) | R125: =IF($B125="","",IF($D125="No","No PTO/PTA",IF($D125<>"Yes","Not Yet Confirmed",IF($Q125>=Settings!$C$13,"Legalized",IF($P125>=Settings!$C$12,"Registered",IF($O125>0,"In Progress","Not Started")))))) | S125: =IF($B125="","",COUNTIF(G125:N125,"Received")) | T125: =IF($B125="","",COUNTIF(G125:N125,"Needs Correction")) | U125: =IF($B125="","",IF($D125<>"Yes","",IF($Q125>=Settings!$C$13,"None",MID(IF(AND(G125<>"Accepted",G125<>"Not Needed",Settings!$C$15="Yes"),", "&G$1,"")&IF(AND(H125<>"Accepted",H125<>"Not Needed",Settings!$D$15="Yes"),", "&H$1,"")&IF(AND(I125<>"Accepted",I125<>"Not Needed",Settings!$E$15="Yes"),", "&I$1,"")&IF(AND(J125<>"Accepted",J125<>"Not Needed",Settings!$F$15="Yes"),", "&J$1,"")&IF(AND(K125<>"Accepted",K125<>"Not Needed",Settings!$G$15="Yes"),", "&K$1,"")&IF(AND(L125<>"Accepted",L125<>"Not Needed",Settings!$H$15="Yes"),", "&L$1,"")&IF(AND(M125<>"Accepted",M125<>"Not Needed",Settings!$I$15="Yes"),", "&M$1,"")&IF(AND(N125<>"Accepted",N125<>"Not Needed",Settings!$J$15="Yes"),", "&N$1,""),3,400))))
A126: 2026-27 | B126: Burbank MS | C126: EAS Secondary | D126: Not Yet Confirmed | G126: Not Received | H126: Not Received | I126: Not Received | J126: Not Received | K126: Not Received | L126: Not Received | M126: Not Received | N126: Not Received | O126: =IF($B126="","",COUNTIF(G126:N126,"Accepted")+COUNTIF(G126:N126,"Received")+COUNTIF(G126:N126,"Needs Correction")) | P126: =IF($B126="","",SUMPRODUCT(((G126:N126="Accepted")+(G126:N126="Not Needed"))*(Settings!$C$11:$J$11="Yes"))) | Q126: =IF($B126="","",SUMPRODUCT(((G126:N126="Accepted")+(G126:N126="Not Needed"))*(Settings!$C$15:$J$15="Yes"))) | R126: =IF($B126="","",IF($D126="No","No PTO/PTA",IF($D126<>"Yes","Not Yet Confirmed",IF($Q126>=Settings!$C$13,"Legalized",IF($P126>=Settings!$C$12,"Registered",IF($O126>0,"In Progress","Not Started")))))) | S126: =IF($B126="","",COUNTIF(G126:N126,"Received")) | T126: =IF($B126="","",COUNTIF(G126:N126,"Needs Correction")) | U126: =IF($B126="","",IF($D126<>"Yes","",IF($Q126>=Settings!$C$13,"None",MID(IF(AND(G126<>"Accepted",G126<>"Not Needed",Settings!$C$15="Yes"),", "&G$1,"")&IF(AND(H126<>"Accepted",H126<>"Not Needed",Settings!$D$15="Yes"),", "&H$1,"")&IF(AND(I126<>"Accepted",I126<>"Not Needed",Settings!$E$15="Yes"),", "&I$1,"")&IF(AND(J126<>"Accepted",J126<>"Not Needed",Settings!$F$15="Yes"),", "&J$1,"")&IF(AND(K126<>"Accepted",K126<>"Not Needed",Settings!$G$15="Yes"),", "&K$1,"")&IF(AND(L126<>"Accepted",L126<>"Not Needed",Settings!$H$15="Yes"),", "&L$1,"")&IF(AND(M126<>"Accepted",M126<>"Not Needed",Settings!$I$15="Yes"),", "&M$1,"")&IF(AND(N126<>"Accepted",N126<>"Not Needed",Settings!$J$15="Yes"),", "&N$1,""),3,400))))
A127: 2026-27 | B127: Carnegie HS | C127: EAS Secondary | D127: Not Yet Confirmed | G127: Not Received | H127: Not Received | I127: Not Received | J127: Not Received | K127: Not Received | L127: Not Received | M127: Not Received | N127: Not Received | O127: =IF($B127="","",COUNTIF(G127:N127,"Accepted")+COUNTIF(G127:N127,"Received")+COUNTIF(G127:N127,"Needs Correction")) | P127: =IF($B127="","",SUMPRODUCT(((G127:N127="Accepted")+(G127:N127="Not Needed"))*(Settings!$C$11:$J$11="Yes"))) | Q127: =IF($B127="","",SUMPRODUCT(((G127:N127="Accepted")+(G127:N127="Not Needed"))*(Settings!$C$15:$J$15="Yes"))) | R127: =IF($B127="","",IF($D127="No","No PTO/PTA",IF($D127<>"Yes","Not Yet Confirmed",IF($Q127>=Settings!$C$13,"Legalized",IF($P127>=Settings!$C$12,"Registered",IF($O127>0,"In Progress","Not Started")))))) | S127: =IF($B127="","",COUNTIF(G127:N127,"Received")) | T127: =IF($B127="","",COUNTIF(G127:N127,"Needs Correction")) | U127: =IF($B127="","",IF($D127<>"Yes","",IF($Q127>=Settings!$C$13,"None",MID(IF(AND(G127<>"Accepted",G127<>"Not Needed",Settings!$C$15="Yes"),", "&G$1,"")&IF(AND(H127<>"Accepted",H127<>"Not Needed",Settings!$D$15="Yes"),", "&H$1,"")&IF(AND(I127<>"Accepted",I127<>"Not Needed",Settings!$E$15="Yes"),", "&I$1,"")&IF(AND(J127<>"Accepted",J127<>"Not Needed",Settings!$F$15="Yes"),", "&J$1,"")&IF(AND(K127<>"Accepted",K127<>"Not Needed",Settings!$G$15="Yes"),", "&K$1,"")&IF(AND(L127<>"Accepted",L127<>"Not Needed",Settings!$H$15="Yes"),", "&L$1,"")&IF(AND(M127<>"Accepted",M127<>"Not Needed",Settings!$I$15="Yes"),", "&M$1,"")&IF(AND(N127<>"Accepted",N127<>"Not Needed",Settings!$J$15="Yes"),", "&N$1,""),3,400))))
A128: 2026-27 | B128: DeBakey HS | C128: EAS Secondary | D128: Not Yet Confirmed | G128: Not Received | H128: Not Received | I128: Not Received | J128: Not Received | K128: Not Received | L128: Not Received | M128: Not Received | N128: Not Received | O128: =IF($B128="","",COUNTIF(G128:N128,"Accepted")+COUNTIF(G128:N128,"Received")+COUNTIF(G128:N128,"Needs Correction")) | P128: =IF($B128="","",SUMPRODUCT(((G128:N128="Accepted")+(G128:N128="Not Needed"))*(Settings!$C$11:$J$11="Yes"))) | Q128: =IF($B128="","",SUMPRODUCT(((G128:N128="Accepted")+(G128:N128="Not Needed"))*(Settings!$C$15:$J$15="Yes"))) | R128: =IF($B128="","",IF($D128="No","No PTO/PTA",IF($D128<>"Yes","Not Yet Confirmed",IF($Q128>=Settings!$C$13,"Legalized",IF($P128>=Settings!$C$12,"Registered",IF($O128>0,"In Progress","Not Started")))))) | S128: =IF($B128="","",COUNTIF(G128:N128,"Received")) | T128: =IF($B128="","",COUNTIF(G128:N128,"Needs Correction")) | U128: =IF($B128="","",IF($D128<>"Yes","",IF($Q128>=Settings!$C$13,"None",MID(IF(AND(G128<>"Accepted",G128<>"Not Needed",Settings!$C$15="Yes"),", "&G$1,"")&IF(AND(H128<>"Accepted",H128<>"Not Needed",Settings!$D$15="Yes"),", "&H$1,"")&IF(AND(I128<>"Accepted",I128<>"Not Needed",Settings!$E$15="Yes"),", "&I$1,"")&IF(AND(J128<>"Accepted",J128<>"Not Needed",Settings!$F$15="Yes"),", "&J$1,"")&IF(AND(K128<>"Accepted",K128<>"Not Needed",Settings!$G$15="Yes"),", "&K$1,"")&IF(AND(L128<>"Accepted",L128<>"Not Needed",Settings!$H$15="Yes"),", "&L$1,"")&IF(AND(M128<>"Accepted",M128<>"Not Needed",Settings!$I$15="Yes"),", "&M$1,"")&IF(AND(N128<>"Accepted",N128<>"Not Needed",Settings!$J$15="Yes"),", "&N$1,""),3,400))))
A129: 2026-27 | B129: East EC HS | C129: EAS Secondary | D129: No | G129: Not Received | H129: Not Received | I129: Not Received | J129: Not Received | K129: Not Received | L129: Not Received | M129: Not Received | N129: Not Received | O129: =IF($B129="","",COUNTIF(G129:N129,"Accepted")+COUNTIF(G129:N129,"Received")+COUNTIF(G129:N129,"Needs Correction")) | P129: =IF($B129="","",SUMPRODUCT(((G129:N129="Accepted")+(G129:N129="Not Needed"))*(Settings!$C$11:$J$11="Yes"))) | Q129: =IF($B129="","",SUMPRODUCT(((G129:N129="Accepted")+(G129:N129="Not Needed"))*(Settings!$C$15:$J$15="Yes"))) | R129: =IF($B129="","",IF($D129="No","No PTO/PTA",IF($D129<>"Yes","Not Yet Confirmed",IF($Q129>=Settings!$C$13,"Legalized",IF($P129>=Settings!$C$12,"Registered",IF($O129>0,"In Progress","Not Started")))))) | S129: =IF($B129="","",COUNTIF(G129:N129,"Received")) | T129: =IF($B129="","",COUNTIF(G129:N129,"Needs Correction")) | U129: =IF($B129="","",IF($D129<>"Yes","",IF($Q129>=Settings!$C$13,"None",MID(IF(AND(G129<>"Accepted",G129<>"Not Needed",Settings!$C$15="Yes"),", "&G$1,"")&IF(AND(H129<>"Accepted",H129<>"Not Needed",Settings!$D$15="Yes"),", "&H$1,"")&IF(AND(I129<>"Accepted",I129<>"Not Needed",Settings!$E$15="Yes"),", "&I$1,"")&IF(AND(J129<>"Accepted",J129<>"Not Needed",Settings!$F$15="Yes"),", "&J$1,"")&IF(AND(K129<>"Accepted",K129<>"Not Needed",Settings!$G$15="Yes"),", "&K$1,"")&IF(AND(L129<>"Accepted",L129<>"Not Needed",Settings!$H$15="Yes"),", "&L$1,"")&IF(AND(M129<>"Accepted",M129<>"Not Needed",Settings!$I$15="Yes"),", "&M$1,"")&IF(AND(N129<>"Accepted",N129<>"Not Needed",Settings!$J$15="Yes"),", "&N$1,""),3,400))))
A130: 2026-27 | B130: Eastwood Acad HS | C130: EAS Secondary | D130: Not Yet Confirmed | G130: Not Received | H130: Not Received | I130: Not Received | J130: Not Received | K130: Not Received | L130: Not Received | M130: Not Received | N130: Not Received | O130: =IF($B130="","",COUNTIF(G130:N130,"Accepted")+COUNTIF(G130:N130,"Received")+COUNTIF(G130:N130,"Needs Correction")) | P130: =IF($B130="","",SUMPRODUCT(((G130:N130="Accepted")+(G130:N130="Not Needed"))*(Settings!$C$11:$J$11="Yes"))) | Q130: =IF($B130="","",SUMPRODUCT(((G130:N130="Accepted")+(G130:N130="Not Needed"))*(Settings!$C$15:$J$15="Yes"))) | R130: =IF($B130="","",IF($D130="No","No PTO/PTA",IF($D130<>"Yes","Not Yet Confirmed",IF($Q130>=Settings!$C$13,"Legalized",IF($P130>=Settings!$C$12,"Registered",IF($O130>0,"In Progress","Not Started")))))) | S130: =IF($B130="","",COUNTIF(G130:N130,"Received")) | T130: =IF($B130="","",COUNTIF(G130:N130,"Needs Correction")) | U130: =IF($B130="","",IF($D130<>"Yes","",IF($Q130>=Settings!$C$13,"None",MID(IF(AND(G130<>"Accepted",G130<>"Not Needed",Settings!$C$15="Yes"),", "&G$1,"")&IF(AND(H130<>"Accepted",H130<>"Not Needed",Settings!$D$15="Yes"),", "&H$1,"")&IF(AND(I130<>"Accepted",I130<>"Not Needed",Settings!$E$15="Yes"),", "&I$1,"")&IF(AND(J130<>"Accepted",J130<>"Not Needed",Settings!$F$15="Yes"),", "&J$1,"")&IF(AND(K130<>"Accepted",K130<>"Not Needed",Settings!$G$15="Yes"),", "&K$1,"")&IF(AND(L130<>"Accepted",L130<>"Not Needed",Settings!$H$15="Yes"),", "&L$1,"")&IF(AND(M130<>"Accepted",M130<>"Not Needed",Settings!$I$15="Yes"),", "&M$1,"")&IF(AND(N130<>"Accepted",N130<>"Not Needed",Settings!$J$15="Yes"),", "&N$1,""),3,400))))
A131: 2026-27 | B131: Hamilton MS | C131: EAS Secondary | D131: Yes | E131: PTA | G131: Accepted | H131: Not Received | I131: Not Received | J131: Accepted | K131: Accepted | L131: Accepted | M131: Not Received | N131: Not Received | O131: =IF($B131="","",COUNTIF(G131:N131,"Accepted")+COUNTIF(G131:N131,"Received")+COUNTIF(G131:N131,"Needs Correction")) | P131: =IF($B131="","",SUMPRODUCT(((G131:N131="Accepted")+(G131:N131="Not Needed"))*(Settings!$C$11:$J$11="Yes"))) | Q131: =IF($B131="","",SUMPRODUCT(((G131:N131="Accepted")+(G131:N131="Not Needed"))*(Settings!$C$15:$J$15="Yes"))) | R131: =IF($B131="","",IF($D131="No","No PTO/PTA",IF($D131<>"Yes","Not Yet Confirmed",IF($Q131>=Settings!$C$13,"Legalized",IF($P131>=Settings!$C$12,"Registered",IF($O131>0,"In Progress","Not Started")))))) | S131: =IF($B131="","",COUNTIF(G131:N131,"Received")) | T131: =IF($B131="","",COUNTIF(G131:N131,"Needs Correction")) | U131: =IF($B131="","",IF($D131<>"Yes","",IF($Q131>=Settings!$C$13,"None",MID(IF(AND(G131<>"Accepted",G131<>"Not Needed",Settings!$C$15="Yes"),", "&G$1,"")&IF(AND(H131<>"Accepted",H131<>"Not Needed",Settings!$D$15="Yes"),", "&H$1,"")&IF(AND(I131<>"Accepted",I131<>"Not Needed",Settings!$E$15="Yes"),", "&I$1,"")&IF(AND(J131<>"Accepted",J131<>"Not Needed",Settings!$F$15="Yes"),", "&J$1,"")&IF(AND(K131<>"Accepted",K131<>"Not Needed",Settings!$G$15="Yes"),", "&K$1,"")&IF(AND(L131<>"Accepted",L131<>"Not Needed",Settings!$H$15="Yes"),", "&L$1,"")&IF(AND(M131<>"Accepted",M131<>"Not Needed",Settings!$I$15="Yes"),", "&M$1,"")&IF(AND(N131<>"Accepted",N131<>"Not Needed",Settings!$J$15="Yes"),", "&N$1,""),3,400))))
A132: 2026-27 | B132: Heights HS | C132: EAS Secondary | D132: Not Yet Confirmed | G132: Not Received | H132: Not Received | I132: Not Received | J132: Not Received | K132: Not Received | L132: Not Received | M132: Not Received | N132: Not Received | O132: =IF($B132="","",COUNTIF(G132:N132,"Accepted")+COUNTIF(G132:N132,"Received")+COUNTIF(G132:N132,"Needs Correction")) | P132: =IF($B132="","",SUMPRODUCT(((G132:N132="Accepted")+(G132:N132="Not Needed"))*(Settings!$C$11:$J$11="Yes"))) | Q132: =IF($B132="","",SUMPRODUCT(((G132:N132="Accepted")+(G132:N132="Not Needed"))*(Settings!$C$15:$J$15="Yes"))) | R132: =IF($B132="","",IF($D132="No","No PTO/PTA",IF($D132<>"Yes","Not Yet Confirmed",IF($Q132>=Settings!$C$13,"Legalized",IF($P132>=Settings!$C$12,"Registered",IF($O132>0,"In Progress","Not Started")))))) | S132: =IF($B132="","",COUNTIF(G132:N132,"Received")) | T132: =IF($B132="","",COUNTIF(G132:N132,"Needs Correction")) | U132: =IF($B132="","",IF($D132<>"Yes","",IF($Q132>=Settings!$C$13,"None",MID(IF(AND(G132<>"Accepted",G132<>"Not Needed",Settings!$C$15="Yes"),", "&G$1,"")&IF(AND(H132<>"Accepted",H132<>"Not Needed",Settings!$D$15="Yes"),", "&H$1,"")&IF(AND(I132<>"Accepted",I132<>"Not Needed",Settings!$E$15="Yes"),", "&I$1,"")&IF(AND(J132<>"Accepted",J132<>"Not Needed",Settings!$F$15="Yes"),", "&J$1,"")&IF(AND(K132<>"Accepted",K132<>"Not Needed",Settings!$G$15="Yes"),", "&K$1,"")&IF(AND(L132<>"Accepted",L132<>"Not Needed",Settings!$H$15="Yes"),", "&L$1,"")&IF(AND(M132<>"Accepted",M132<>"Not Needed",Settings!$I$15="Yes"),", "&M$1,"")&IF(AND(N132<>"Accepted",N132<>"Not Needed",Settings!$J$15="Yes"),", "&N$1,""),3,400))))
A133: 2026-27 | B133: High School Ahead Acad MS | C133: EAS Secondary | D133: No | G133: Not Received | H133: Not Received | I133: Not Received | J133: Not Received | K133: Not Received | L133: Not Received | M133: Not Received | N133: Not Received | O133: =IF($B133="","",COUNTIF(G133:N133,"Accepted")+COUNTIF(G133:N133,"Received")+COUNTIF(G133:N133,"Needs Correction")) | P133: =IF($B133="","",SUMPRODUCT(((G133:N133="Accepted")+(G133:N133="Not Needed"))*(Settings!$C$11:$J$11="Yes"))) | Q133: =IF($B133="","",SUMPRODUCT(((G133:N133="Accepted")+(G133:N133="Not Needed"))*(Settings!$C$15:$J$15="Yes"))) | R133: =IF($B133="","",IF($D133="No","No PTO/PTA",IF($D133<>"Yes","Not Yet Confirmed",IF($Q133>=Settings!$C$13,"Legalized",IF($P133>=Settings!$C$12,"Registered",IF($O133>0,"In Progress","Not Started")))))) | S133: =IF($B133="","",COUNTIF(G133:N133,"Received")) | T133: =IF($B133="","",COUNTIF(G133:N133,"Needs Correction")) | U133: =IF($B133="","",IF($D133<>"Yes","",IF($Q133>=Settings!$C$13,"None",MID(IF(AND(G133<>"Accepted",G133<>"Not Needed",Settings!$C$15="Yes"),", "&G$1,"")&IF(AND(H133<>"Accepted",H133<>"Not Needed",Settings!$D$15="Yes"),", "&H$1,"")&IF(AND(I133<>"Accepted",I133<>"Not Needed",Settings!$E$15="Yes"),", "&I$1,"")&IF(AND(J133<>"Accepted",J133<>"Not Needed",Settings!$F$15="Yes"),", "&J$1,"")&IF(AND(K133<>"Accepted",K133<>"Not Needed",Settings!$G$15="Yes"),", "&K$1,"")&IF(AND(L133<>"Accepted",L133<>"Not Needed",Settings!$H$15="Yes"),", "&L$1,"")&IF(AND(M133<>"Accepted",M133<>"Not Needed",Settings!$I$15="Yes"),", "&M$1,"")&IF(AND(N133<>"Accepted",N133<>"Not Needed",Settings!$J$15="Yes"),", "&N$1,""),3,400))))
A134: 2026-27 | B134: Hogg MS | C134: EAS Secondary | D134: Yes | E134: PTA | G134: Accepted | H134: Not Received | I134: Not Received | J134: Accepted | K134: Accepted | L134: Accepted | M134: Not Received | N134: Not Received | O134: =IF($B134="","",COUNTIF(G134:N134,"Accepted")+COUNTIF(G134:N134,"Received")+COUNTIF(G134:N134,"Needs Correction")) | P134: =IF($B134="","",SUMPRODUCT(((G134:N134="Accepted")+(G134:N134="Not Needed"))*(Settings!$C$11:$J$11="Yes"))) | Q134: =IF($B134="","",SUMPRODUCT(((G134:N134="Accepted")+(G134:N134="Not Needed"))*(Settings!$C$15:$J$15="Yes"))) | R134: =IF($B134="","",IF($D134="No","No PTO/PTA",IF($D134<>"Yes","Not Yet Confirmed",IF($Q134>=Settings!$C$13,"Legalized",IF($P134>=Settings!$C$12,"Registered",IF($O134>0,"In Progress","Not Started")))))) | S134: =IF($B134="","",COUNTIF(G134:N134,"Received")) | T134: =IF($B134="","",COUNTIF(G134:N134,"Needs Correction")) | U134: =IF($B134="","",IF($D134<>"Yes","",IF($Q134>=Settings!$C$13,"None",MID(IF(AND(G134<>"Accepted",G134<>"Not Needed",Settings!$C$15="Yes"),", "&G$1,"")&IF(AND(H134<>"Accepted",H134<>"Not Needed",Settings!$D$15="Yes"),", "&H$1,"")&IF(AND(I134<>"Accepted",I134<>"Not Needed",Settings!$E$15="Yes"),", "&I$1,"")&IF(AND(J134<>"Accepted",J134<>"Not Needed",Settings!$F$15="Yes"),", "&J$1,"")&IF(AND(K134<>"Accepted",K134<>"Not Needed",Settings!$G$15="Yes"),", "&K$1,"")&IF(AND(L134<>"Accepted",L134<>"Not Needed",Settings!$H$15="Yes"),", "&L$1,"")&IF(AND(M134<>"Accepted",M134<>"Not Needed",Settings!$I$15="Yes"),", "&M$1,"")&IF(AND(N134<>"Accepted",N134<>"Not Needed",Settings!$J$15="Yes"),", "&N$1,""),3,400))))
A135: 2026-27 | B135: Lamar HS | C135: EAS Secondary | D135: Not Yet Confirmed | G135: Not Received | H135: Not Received | I135: Not Received | J135: Not Received | K135: Not Received | L135: Not Received | M135: Not Received | N135: Not Received | O135: =IF($B135="","",COUNTIF(G135:N135,"Accepted")+COUNTIF(G135:N135,"Received")+COUNTIF(G135:N135,"Needs Correction")) | P135: =IF($B135="","",SUMPRODUCT(((G135:N135="Accepted")+(G135:N135="Not Needed"))*(Settings!$C$11:$J$11="Yes"))) | Q135: =IF($B135="","",SUMPRODUCT(((G135:N135="Accepted")+(G135:N135="Not Needed"))*(Settings!$C$15:$J$15="Yes"))) | R135: =IF($B135="","",IF($D135="No","No PTO/PTA",IF($D135<>"Yes","Not Yet Confirmed",IF($Q135>=Settings!$C$13,"Legalized",IF($P135>=Settings!$C$12,"Registered",IF($O135>0,"In Progress","Not Started")))))) | S135: =IF($B135="","",COUNTIF(G135:N135,"Received")) | T135: =IF($B135="","",COUNTIF(G135:N135,"Needs Correction")) | U135: =IF($B135="","",IF($D135<>"Yes","",IF($Q135>=Settings!$C$13,"None",MID(IF(AND(G135<>"Accepted",G135<>"Not Needed",Settings!$C$15="Yes"),", "&G$1,"")&IF(AND(H135<>"Accepted",H135<>"Not Needed",Settings!$D$15="Yes"),", "&H$1,"")&IF(AND(I135<>"Accepted",I135<>"Not Needed",Settings!$E$15="Yes"),", "&I$1,"")&IF(AND(J135<>"Accepted",J135<>"Not Needed",Settings!$F$15="Yes"),", "&J$1,"")&IF(AND(K135<>"Accepted",K135<>"Not Needed",Settings!$G$15="Yes"),", "&K$1,"")&IF(AND(L135<>"Accepted",L135<>"Not Needed",Settings!$H$15="Yes"),", "&L$1,"")&IF(AND(M135<>"Accepted",M135<>"Not Needed",Settings!$I$15="Yes"),", "&M$1,"")&IF(AND(N135<>"Accepted",N135<>"Not Needed",Settings!$J$15="Yes"),", "&N$1,""),3,400))))
A136: 2026-27 | B136: Lanier MS | C136: EAS Secondary | D136: Not Yet Confirmed | G136: Not Received | H136: Not Received | I136: Not Received | J136: Not Received | K136: Not Received | L136: Not Received | M136: Not Received | N136: Not Received | O136: =IF($B136="","",COUNTIF(G136:N136,"Accepted")+COUNTIF(G136:N136,"Received")+COUNTIF(G136:N136,"Needs Correction")) | P136: =IF($B136="","",SUMPRODUCT(((G136:N136="Accepted")+(G136:N136="Not Needed"))*(Settings!$C$11:$J$11="Yes"))) | Q136: =IF($B136="","",SUMPRODUCT(((G136:N136="Accepted")+(G136:N136="Not Needed"))*(Settings!$C$15:$J$15="Yes"))) | R136: =IF($B136="","",IF($D136="No","No PTO/PTA",IF($D136<>"Yes","Not Yet Confirmed",IF($Q136>=Settings!$C$13,"Legalized",IF($P136>=Settings!$C$12,"Registered",IF($O136>0,"In Progress","Not Started")))))) | S136: =IF($B136="","",COUNTIF(G136:N136,"Received")) | T136: =IF($B136="","",COUNTIF(G136:N136,"Needs Correction")) | U136: =IF($B136="","",IF($D136<>"Yes","",IF($Q136>=Settings!$C$13,"None",MID(IF(AND(G136<>"Accepted",G136<>"Not Needed",Settings!$C$15="Yes"),", "&G$1,"")&IF(AND(H136<>"Accepted",H136<>"Not Needed",Settings!$D$15="Yes"),", "&H$1,"")&IF(AND(I136<>"Accepted",I136<>"Not Needed",Settings!$E$15="Yes"),", "&I$1,"")&IF(AND(J136<>"Accepted",J136<>"Not Needed",Settings!$F$15="Yes"),", "&J$1,"")&IF(AND(K136<>"Accepted",K136<>"Not Needed",Settings!$G$15="Yes"),", "&K$1,"")&IF(AND(L136<>"Accepted",L136<>"Not Needed",Settings!$H$15="Yes"),", "&L$1,"")&IF(AND(M136<>"Accepted",M136<>"Not Needed",Settings!$I$15="Yes"),", "&M$1,"")&IF(AND(N136<>"Accepted",N136<>"Not Needed",Settings!$J$15="Yes"),", "&N$1,""),3,400))))
A137: 2026-27 | B137: Leland YMCPA | C137: EAS Secondary | D137: Not Yet Confirmed | G137: Not Received | H137: Not Received | I137: Not Received | J137: Not Received | K137: Not Received | L137: Not Received | M137: Not Received | N137: Not Received | O137: =IF($B137="","",COUNTIF(G137:N137,"Accepted")+COUNTIF(G137:N137,"Received")+COUNTIF(G137:N137,"Needs Correction")) | P137: =IF($B137="","",SUMPRODUCT(((G137:N137="Accepted")+(G137:N137="Not Needed"))*(Settings!$C$11:$J$11="Yes"))) | Q137: =IF($B137="","",SUMPRODUCT(((G137:N137="Accepted")+(G137:N137="Not Needed"))*(Settings!$C$15:$J$15="Yes"))) | R137: =IF($B137="","",IF($D137="No","No PTO/PTA",IF($D137<>"Yes","Not Yet Confirmed",IF($Q137>=Settings!$C$13,"Legalized",IF($P137>=Settings!$C$12,"Registered",IF($O137>0,"In Progress","Not Started")))))) | S137: =IF($B137="","",COUNTIF(G137:N137,"Received")) | T137: =IF($B137="","",COUNTIF(G137:N137,"Needs Correction")) | U137: =IF($B137="","",IF($D137<>"Yes","",IF($Q137>=Settings!$C$13,"None",MID(IF(AND(G137<>"Accepted",G137<>"Not Needed",Settings!$C$15="Yes"),", "&G$1,"")&IF(AND(H137<>"Accepted",H137<>"Not Needed",Settings!$D$15="Yes"),", "&H$1,"")&IF(AND(I137<>"Accepted",I137<>"Not Needed",Settings!$E$15="Yes"),", "&I$1,"")&IF(AND(J137<>"Accepted",J137<>"Not Needed",Settings!$F$15="Yes"),", "&J$1,"")&IF(AND(K137<>"Accepted",K137<>"Not Needed",Settings!$G$15="Yes"),", "&K$1,"")&IF(AND(L137<>"Accepted",L137<>"Not Needed",Settings!$H$15="Yes"),", "&L$1,"")&IF(AND(M137<>"Accepted",M137<>"Not Needed",Settings!$I$15="Yes"),", "&M$1,"")&IF(AND(N137<>"Accepted",N137<>"Not Needed",Settings!$J$15="Yes"),", "&N$1,""),3,400))))
A138: 2026-27 | B138: Liberty HS | C138: EAS Secondary | D138: No | G138: Not Received | H138: Not Received | I138: Not Received | J138: Not Received | K138: Not Received | L138: Not Received | M138: Not Received | N138: Not Received | O138: =IF($B138="","",COUNTIF(G138:N138,"Accepted")+COUNTIF(G138:N138,"Received")+COUNTIF(G138:N138,"Needs Correction")) | P138: =IF($B138="","",SUMPRODUCT(((G138:N138="Accepted")+(G138:N138="Not Needed"))*(Settings!$C$11:$J$11="Yes"))) | Q138: =IF($B138="","",SUMPRODUCT(((G138:N138="Accepted")+(G138:N138="Not Needed"))*(Settings!$C$15:$J$15="Yes"))) | R138: =IF($B138="","",IF($D138="No","No PTO/PTA",IF($D138<>"Yes","Not Yet Confirmed",IF($Q138>=Settings!$C$13,"Legalized",IF($P138>=Settings!$C$12,"Registered",IF($O138>0,"In Progress","Not Started")))))) | S138: =IF($B138="","",COUNTIF(G138:N138,"Received")) | T138: =IF($B138="","",COUNTIF(G138:N138,"Needs Correction")) | U138: =IF($B138="","",IF($D138<>"Yes","",IF($Q138>=Settings!$C$13,"None",MID(IF(AND(G138<>"Accepted",G138<>"Not Needed",Settings!$C$15="Yes"),", "&G$1,"")&IF(AND(H138<>"Accepted",H138<>"Not Needed",Settings!$D$15="Yes"),", "&H$1,"")&IF(AND(I138<>"Accepted",I138<>"Not Needed",Settings!$E$15="Yes"),", "&I$1,"")&IF(AND(J138<>"Accepted",J138<>"Not Needed",Settings!$F$15="Yes"),", "&J$1,"")&IF(AND(K138<>"Accepted",K138<>"Not Needed",Settings!$G$15="Yes"),", "&K$1,"")&IF(AND(L138<>"Accepted",L138<>"Not Needed",Settings!$H$15="Yes"),", "&L$1,"")&IF(AND(M138<>"Accepted",M138<>"Not Needed",Settings!$I$15="Yes"),", "&M$1,"")&IF(AND(N138<>"Accepted",N138<>"Not Needed",Settings!$J$15="Yes"),", "&N$1,""),3,400))))
...

Sheet Officers
A1: Response ID | B1: Submitted | C1: School Year | D1: Campus | E1: Match | F1: Officer # | G1: Name | H1: Position | I1: Email | J1: Phone | K1: Organization | L1: Org Type | M1: Submitted By | N1: Submitter Email | O1: Submitter Phone | P1: Additional Info | Q1: Added To Register | R1: Notes

Sheet Submission Log
A1: Received | B1: Submitted By | C1: Campus | D1: Document Type | E1: File Name | F1: File Link | G1: School Year | H1: Notes

Sheet Officer Form Paste

Sheet C1 Assignments
A1: Campus | B1: C1 Coordinator

Sheet Dashboard Sign-ins
A1: Name | B1: Role | C1: Passcode status | D1: Email
A2: FACE Staff | B2: Staff

Sheet Settings
A1: Settings
A2: Blue cells are yours to change. Dropdowns on the other sheets read the lists at the bottom of this sheet.
A4: School year
A5: Current school year | C5: 2026-27
A6: School year starts in month (1-12) | C6: 7 | D6: Assumption: a document received in July or later counts toward the school year that starts that July. Change if HISD's registration window differs.
A8: Requirement definitions (column order matches Campus Register columns G to N)
A9: Requirement | C9: Bylaws | D9: Officer Information | E9: Training Certificate | F9: Budget or Financial Report | G9: Proof of 501c Status | H9: Bank Verification Letter | I9: Articles of Incorporation | J9: Insurance
A10: Cycle | C10: Annual | D10: Annual | E10: Annual | F10: Annual | G10: Annual | H10: Annual | I10: One-time | J10: Annual
A11: Counts toward Registered? | C11: Yes | D11: Yes | E11: Yes | F11: No | G11: No | H11: No | I11: No | J11: No
A12: Items required to be Registered | C12: =COUNTIF(C11:J11,"Yes") | D12: Registered = training certificate, the organization's bylaws and the officer information form.
A13: Items required to be Legalized | C13: =COUNTIF(C15:J15,"Yes") | D13: Legalized = training certificate, the organization's bylaws, the officer information form, annual budget report or meeting minutes showing budget approval, proof of 501(c) status and bank account verification letter from financial institution listing two authorized account signers. Not Needed counts like Accepted.
A14: Cycle is used when a new school year starts: The one-time item (Articles of Incorporation) carries forward; everything else resets to Not Received. To change which items count toward Registered, change row 11; to change which are needed to be Legalized, change row 15.
A15: Needed to be Legalized? | C15: Yes | D15: Yes | E15: Yes | F15: Yes | G15: Yes | H15: Yes | I15: No | J15: No
A16: Lists used by dropdowns
A17: Has PTO or PTA | B17: Org Type | C17: Item Status | D17: Campus Status | E17: Area Office | G17: The five 2026-27 Area Offices.
A18: Yes | B18: PTA | C18: Not Received | D18: Legalized | E18: NES Elementary
A19: No | B19: PTO | C19: Received | D19: Registered | E19: NES Secondary
A20: Not Yet Confirmed | B20: SPO | C20: Accepted | D20: In Progress | E20: EAS Elementary
B21: PAC | C21: Needs Correction | D21: Not Started | E21: EAS Secondary
C22: Not Needed | D22: No PTO/PTA | E22: Programs/Charters
D23: Not Yet Confirmed

Sheet Area Office Campuses
A1: Campus | B1: Area Office | C1: Unit | D1: Name in the register | E1: Texas PTA | F1: Texas PTA status
A2: Almeda ES | B2: NES Elementary
A3: Anderson ES | B3: NES Elementary
A4: Arabic Immersion | B4: EAS Elementary
A5: Ashford ES | B5: NES Elementary
A6: Askew ES | B6: NES Elementary
A7: Atherton ES | B7: NES Elementary
A8: Attucks MS | B8: EAS Secondary
A9: Austin HS | B9: NES Secondary
A10: Baker Montessori | B10: EAS Elementary
A11: Barrick ES | B11: NES Elementary
A12: Bastian ES | B12: NES Elementary
A13: Baylor College MS | B13: EAS Secondary
... A22: Blackshear ES | B22: NES Elementary
A23: Bonham ES | B23: NES Elementary | E23: No (charter withdrawn) | F23: Charter Withdrawn
A24: Bonner ES | B24: NES Elementary
A25: Braeburn ES | B25: EAS Elementary
A26: Briargrove ES | B26: EAS Elementary
A27: Briarmeadow | B27: EAS Elementary
A28: Brookline ES | B28: NES Elementary
A29: Browning ES | B29: NES Elementary | E29: Yes | F29: Inactive
A30: Bruce ES | B30: NES Elementary
A31: Burbank ES | B31: EAS Elementary
A32: Burbank MS | B32: EAS Secondary
A33: Burnet ES | B33: NES Elementary
A34: Bush ES | B34: EAS Elementary
A35: Cage ES | B35: NES Elementary
A36: Carnegie HS | B36: EAS Secondary
A37: Carrillo ES | B37: NES Elementary
A38: Challenge EC HS | B38: 1882
A39: Chavez HS | B39: EAS Secondary
A40: Chrysalis MS | B40: NES Secondary
A41: Clifton MS | B41: NES Secondary
... A60: Dogan ES | B60: NES Elementary
A61: Durham ES | B61: EAS Elementary | E61: Yes | F61: Inactive
A62: Durkee ES | B62: NES Elementary
A63: East EC HS | B63: EAS Secondary
A64: Eastwood Acad HS | B64: EAS Secondary
A65: Edison MS | B65: NES Secondary
A66: Eliot ES | B66: NES Elementary
A67: Elmore ES | B67: NES Elementary
A68: Elrod ES | B68: EAS Elementary
A69: Emerson ES | B69: EAS Elementary
A70: Energized ECC | B70: COSO
A71: Energized ES | B71: COSO
A72: Energized for STEM Academy HS | B72: COSO
A73: Energized for STEM Academy MS | B73: COSO
... A98: Halpin ECC | B98: EAS Elementary
A99: Hamilton MS | B99: EAS Secondary | E99: Yes | F99: Active
A100: Harris JR ES | B100: NES Elementary
A101: Harris RP ES | B101: NES Elementary
A102: Hartman MS | B102: NES Secondary
A103: Hartsfield ES | B103: NES Elementary
A104: Harvard ES | B104: EAS Elementary | E104: Yes | F104: Active
A105: HCC Lifeskills | B105: OOA
A106: Heights HS | B106: EAS Secondary
A107: Helms ES | B107: EAS Elementary | E107: Yes | F107: Inactive
A108: Henderson JP ES | B108: EAS Elementary
A109: Henry MS | B109: NES Secondary
A110: Herod ES | B110: EAS Elementary
A111: Herrera ES | B111: EAS Elementary
A112: High School Ahead Acad MS | B112: EAS Secondary
A113: Highland Heights ES | B113: NES Elementary
A114: Hilliard ES | B114: NES Elementary
A115: Hines-Caldwell ES | B115: EAS Elementary
A116: Hobby ES | B116: NES Elementary
A117: Hogg MS | B117: EAS Secondary | E117: Yes | F117: Good Standing
A118: Holland MS | B118: NES Secondary
A119: Horn ES | B119: EAS Elementary
A120: Houston MSTC HS | B120: NES Secondary
A121: HSLJ | B121: EAS Secondary
A122: Isaacs ES | B122: NES Elementary
A123: Janowski ES | B123: EAS Elementary
A124: Jefferson ES | B124: NES Elementary
A125: JJAEP | B125: COSO
A126: Jones HS | B126: EAS Secondary
A127: Kashmere Gardens ES | B127: NES Elementary
A128: Kashmere HS | B128: NES Secondary
A129: Kelso ES | B129: NES Elementary
A130: Kennedy ES | B130: NES Elementary
A131: Ketelsen ES | B131: NES Elementary | E131: Yes | F131: Inactive
A132: Key MS | B132: NES Secondary
A133: Kinder HSPVA | B133: 1882
A134: Kolter ES | B134: EAS Elementary
A135: Lamar HS | B135: EAS Secondary
A136: Lanier MS | B136: EAS Secondary
A137: Lantrip ES | B137: EAS Elementary
A138: Laurenzo ECC | B138: EAS Elementary
A139: Law ES | B139: NES Elementary
A140: Lawson MS | B140: NES Secondary
A141: Leland YMCPA | B141: EAS Secondary
A142: Lewis ES | B142: NES Elementary
A143: Liberty HS | B143: EAS Secondary
... A176: Northline ES | B176: NES Elementary
A177: Northside HS | B177: NES Secondary | E177: No (charter withdrawn) | F177: Charter Withdrawn
A178: Oak Forest ES | B178: EAS Elementary | E178: Yes | F178: Good Standing
A179: Oates ES | B179: NES Elementary
A180: Ortiz MS | B180: NES Secondary
A181: Osborne ES | B181: NES Elementary
A182: Paige ES | B182: NES Elementary
...

Sheet No PTO-PTA List
A1: Campus Name | B1: Division | C1: FACE Coordinator 1 | D1: PTO/PTA | E1: Name in the register | F1: Status
A2: Almeda ES | B2: South | C2: Karen Aubrey | D2: No | F2: No PTO/PTA: Almeda ES
A3: Attucks MS | B3: South | C3: Karen Aubrey | D3: No | F3: No PTO/PTA: Attucks MS
A4: Austin HS | B4: Central | C4: Kenya Washington | D4: No | F4: No PTO/PTA: Austin HS
A5: Bastian ES | B5: South | C5: Karen Aubrey | D5: No | F5: No PTO/PTA: Bastian ES
A6: Bell ES | B6: West | C6: Eunice Vela | D6: No | F6: No PTO/PTA: Bell ES
A7: Benavidez ES | B7: West | C7: Andreina Savelli | D7: No | F7: No PTO/PTA: Benavidez ES
A8: Benbrook ES | B8: North | C8: Eunice Vela | D8: No | F8: No PTO/PTA: Benbrook ES
A9: Brookline ES | B9: South | C9: Kenya Washington | D9: No | F9: No PTO/PTA: Brookline ES
A10: Bruce ES | B10: Central | C10: Kathleen Ruiz | D10: No | F10: No PTO/PTA: Bruce ES
A11: Burnet ES | B11: Central | C11: Kathleen Ruiz | D11: No | F11: No PTO/PTA: Burnet ES
A12: Cage ES | B12: Central | C12: Kenya Washington | D12: No | F12: No PTO/PTA: Cage ES
A13: Chavez HS | B13: South | C13: Kathleen Ruiz | D13: No | F13: No PTO/PTA: Chavez HS
... A120: Young ES | B120: South | C120: Karen Aubrey | D120: No | F120: No PTO/PTA: Young ES

Sheet Texas PTA Paste
A1: Updated on THU, October 15, 2026 at 8:48 AM
D2: Membership | J2: Feature Eligibility | M2: Path to Good Standing- Standards of Continuing Affiliation (SOA) All PTAs should be in Good Standing by November 1st
A3: School District | B3: PTA | C3: Texas PTA ID | D3: Membership Goal | E3: To Increase Local | F3: 26-27 Current Membership Count | G3: 25-26 | H3: 24-25 | I3: Student Enrollment | J3: Reflections Eligible | K3: JoinPTA.org Activation? | L3: Online RDC | M3: PTA Status | N3: Retention Plan Status | O3: Retention Plan Status More Information | P3: Good Standing Date | Q3: SOA Officers | R3: SOA Membership | S3: SOA Bylaws | T3: SOA Standing Rules | U3: SOA 990 | V3: Active Status Date (Must be active by 12/1/26 to vote) | W3: Bylaws Approved
A4: Houston ISD | B4: Alexander Hamilton Middle School | C4: 2312957 | D4: 32 | E4: -21 | F4: 51 | G4: 29 | H4: 0 | I4: 964 | J4: X | K4: √ | L4: √ | M4: Good Standing | O4: 1st Year PTA | P4: 10/14/2026 | Q4: √ | R4: √ | S4: √ | T4: √ | U4: √ | V4: 8/10/2026 | W4: 12/1/2025
A5: Houston ISD | B5: Bonham Elementary | C5: 2302410 | D5: 1 | E5: 1 | F5: 0 | G5: 0 | H5: 29 | I5: 767 | J5: X | K5: X | L5: X | M5: Charter Withdrawal | Q5: X | R5: X | S5: X | T5: √ | U5: X | W5: 10/13/2021
A6: Houston ISD | B6: Browning Elementary | C6: 2312892 | D6: 28 | E6: 26 | F6: 0 | G6: 25 | H6: 20 | I6: 317 | J6: √ | K6: √ | L6: √ | M6: Inactive | Q6: √ | R6: X | S6: √ | T6: √ | U6: X | W6: 5/12/2025
A7: Houston ISD | B7: Durham Elementary | C7: 4784 | D7: 312 | E7: 263 | F7: 21 | G7: 283 | H7: 317 | I7: 498 | J7: √ | K7: √ | L7: √ | M7: Good Standing | P7: 10/14/2026 | Q7: √ | R7: √ | S7: √ | T7: √ | U7: √ | V7: 10/9/2026 | W7: 3/21/2025
A8: Houston ISD | B8: Harvard Elementary | C8: 4888 | D8: 91 | E8: 30 | F8: 53 | G8: 82 | H8: 205 | I8: 663 | J8: √ | K8: √ | L8: √ | M8: Active | Q8: √ | R8: √ | S8: √ | T8: √ | U8: X | V8: 8/17/2026 | W8: 7/8/2024
A9: Houston ISD | B9: Helms Elementary | C9: 4892 | D9: 338 | E9: 308 | F9: 0 | G9: 307 | H9: 180 | I9: 523 | J9: √ | K9: √ | L9: √ | M9: Inactive | Q9: √ | R9: X | S9: √ | T9: √ | U9: X | W9: 1/8/2026
A10: Houston ISD | B10: Hogg Middle School | C10: 2283554 | D10: 237 | E10: -71 | F10: 287 | G10: 215 | H10: 157 | I10: 1149 | J10: √ | K10: √ | L10: √ | M10: Good Standing | P10: 9/24/2026 | Q10: √ | R10: √ | S10: √ | T10: √ | U10: √ | V10: 9/24/2026 | W10: 3/30/2026
A11: Houston ISD | B11: Ketelsen | C11: 2312525 | D11: 26 | E11: 15 | F11: 9 | G11: 23 | H11: 20 | I11: 340 | J11: √ | K11: √ | L11: √ | M11: Inactive | Q11: √ | R11: X | S11: X | T11: √ | U11: √ | W11: 9/15/2022
A12: Houston ISD | B12: Northside High School | C12: 2311869 | D12: 2 | E12: 2 | F12: 0 | G12: 1 | H12: 22 | I12: 922 | J12: X | K12: X | L12: X | M12: Charter Withdrawal | Q12: X | R12: X | S12: X | T12: √ | U12: X | W12: 9/27/2021
A13: Houston ISD | B13: Oak Forest Elementary | C13: 5124 | D13: 744 | E13: -12 | F13: 689 | G13: 676 | H13: 639 | I13: 996 | J13: √ | K13: √ | L13: √ | M13: Good Standing | P13: 9/9/2026 | Q13: √ | R13: √ | S13: √ | T13: √ | U13: √ | V13: 9/3/2026 | W13: 6/2/26
A14: Houston ISD | B14: South Early Community | C14: 2223725 | D14: 71 | E14: 65 | F14: 0 | G14: 64 | H14: 21 | I14: 525 | J14: √ | K14: √ | L14: √ | M14: Inactive | Q14: √ | R14: X | S14: √ | T14: √ | U14: X | W14: 9/11/2024
A15: Houston ISD | B15: Tijerina Elementary | C15: 5328 | D15: 29 | E15: 27 | F15: 0 | G15: 26 | H15: 20 | I15: 282 | J15: √ | K15: √ | L15: √ | M15: Inactive | Q15: X | R15: X | S15: √ | T15: √ | U15: X | W15: 3/7/2024
A16: Houston ISD | B16: Wainwright Elementary | C16: 5340 | D16: 1 | E16: 1 | F16: 0 | G16: 0 | H16: 20 | I16: 316 | J16: X | K16: X | L16: X | M16: Charter Withdrawal | Q16: X | R16: X | S16: X | T16: √ | U16: X | W16: 10/13/2021
A17: Houston ISD | B17: William B. Travis Elementary | C17: 5332 | D17: 368 | E17: -77 | F17: 412 | G17: 334 | H17: 317 | I17: 782 | J17: √ | K17: √ | L17: √ | M17: Good Standing | P17: 9/9/2026 | Q17: √ | R17: √ | S17: √ | T17: √ | U17: √ | V17: 8/1/2026 | W17: 8/11/2025

Sheet Texas PTA
A1: Campus | B1: Texas PTA Name | C1: Texas PTA ID | D1: PTA Status | E1: Good Standing Date | F1: SOA Officers | G1: SOA Membership | H1: SOA Bylaws | I1: SOA Standing Rules | J1: SOA 990 | K1: JoinPTA Activation | L1: Current Members | M1: Membership Goal | N1: Active Status Date | O1: Bylaws Approved | P1: Note | Q1: Texas PTA Updated | R1: Imported
A2: Hamilton MS | B2: Alexander Hamilton Middle School | C2: 2312957 | D2: Good Standing | E2: 10/14/2026 | F2: Yes | G2: Yes | H2: Yes | I2: Yes | J2: Yes | K2: Yes | L2: 51 | M2: 32 | N2: 8/10/2026 | O2: 12/1/2025 | Q2: THU, October 15, 2026 at 8:48 AM | R2: 2026-10-26 04:30
A3: Browning ES | B3: Browning Elementary | C3: 2312892 | D3: Inactive | F3: Yes | G3: No | H3: Yes | I3: Yes | J3: No | K3: Yes | L3: 0 | M3: 28 | O3: 5/12/2025 | Q3: THU, October 15, 2026 at 8:48 AM | R3: 2026-10-26 04:30
A4: Durham ES | B4: Durham Elementary | C4: 4784 | D4: Good Standing | E4: 10/14/2026 | F4: Yes | G4: Yes | H4: Yes | I4: Yes | J4: Yes | K4: Yes | L4: 21 | M4: 312 | N4: 10/9/2026 | O4: 3/21/2025 | Q4: THU, October 15, 2026 at 8:48 AM | R4: 2026-10-26 04:30
A5: Harvard ES | B5: Harvard Elementary | C5: 4888 | D5: Active | F5: Yes | G5: Yes | H5: Yes | I5: Yes | J5: No | K5: Yes | L5: 53 | M5: 91 | N5: 8/17/2026 | O5: 7/8/2024 | Q5: THU, October 15, 2026 at 8:48 AM | R5: 2026-10-26 04:30
A6: Helms ES | B6: Helms Elementary | C6: 4892 | D6: Inactive | F6: Yes | G6: No | H6: Yes | I6: Yes | J6: No | K6: Yes | L6: 0 | M6: 338 | O6: 1/8/2026 | Q6: THU, October 15, 2026 at 8:48 AM | R6: 2026-10-26 04:30
A7: Hogg MS | B7: Hogg Middle School | C7: 2283554 | D7: Good Standing | E7: 9/24/2026 | F7: Yes | G7: Yes | H7: Yes | I7: Yes | J7: Yes | K7: Yes | L7: 287 | M7: 237 | N7: 9/24/2026 | O7: 3/30/2026 | Q7: THU, October 15, 2026 at 8:48 AM | R7: 2026-10-26 04:30
A8: Ketelsen ES | B8: Ketelsen | C8: 2312525 | D8: Inactive | F8: Yes | G8: No | H8: No | I8: Yes | J8: Yes | K8: Yes | L8: 9 | M8: 26 | O8: 9/15/2022 | Q8: THU, October 15, 2026 at 8:48 AM | R8: 2026-10-26 04:30
A9: Oak Forest ES | B9: Oak Forest Elementary | C9: 5124 | D9: Good Standing | E9: 9/9/2026 | F9: Yes | G9: Yes | H9: Yes | I9: Yes | J9: Yes | K9: Yes | L9: 689 | M9: 744 | N9: 9/3/2026 | O9: 6/2/26 | Q9: THU, October 15, 2026 at 8:48 AM | R9: 2026-10-26 04:30
A10: South EC HS | B10: South Early Community | C10: 2223725 | D10: Inactive | F10: Yes | G10: No | H10: Yes | I10: Yes | J10: No | K10: Yes | L10: 0 | M10: 71 | O10: 9/11/2024 | Q10: THU, October 15, 2026 at 8:48 AM | R10: 2026-10-26 04:30
A11: Tijerina ES | B11: Tijerina Elementary | C11: 5328 | D11: Inactive | F11: No | G11: No | H11: Yes | I11: Yes | J11: No | K11: Yes | L11: 0 | M11: 29 | O11: 3/7/2024 | Q11: THU, October 15, 2026 at 8:48 AM | R11: 2026-10-26 04:30
A12: Travis ES | B12: William B. Travis Elementary | C12: 5332 | D12: Good Standing | E12: 9/9/2026 | F12: Yes | G12: Yes | H12: Yes | I12: Yes | J12: Yes | K12: Yes | L12: 412 | M12: 368 | N12: 8/1/2026 | O12: 8/11/2025 | Q12: THU, October 15, 2026 at 8:48 AM | R12: 2026-10-26 04:30

Sheet Roster Match Notes
A1: Roster Match Notes
A2: Campus names in the TB PTO/PTA Tracker (used in the register) that are spelled differently in the Area Office assignments workbook. Rows marked Confirmed were checked and accepted. The two rows with no Area Office are not in the assignments workbook at all; they are left blank to fill in or delete later.
A4: Name in the tracker (used in the register) | B4: Name in the assignments workbook | C4: Area Office | D4: Note
A5: Henderson NQ ES | D5: Not in the assignments workbook (only JP Henderson ES is). Area Office left blank.
A6: Middle College HS - Gulfton | D6: Not in the assignments workbook (only MC Fraga EC HS is). Area Office left blank.
A7: Baylor College MS | B7: Baylor @ Ryan MS | C7: EAS Secondary | D7: Confirmed: Baylor College of Medicine Academy at Ryan.
A8: McReynolds MS | B8: Fleming/McReynolds (@ Leland MS ) | C8: NES Secondary | D8: Confirmed: the assignments workbook lists Fleming and McReynolds as one combined campus.
A9: Williams MS | B9: McWilliams MS | C9: NES Secondary | D9: Confirmed: McWilliams MS. No other tracker row maps to it.
A10: BCM Biotech Acad at Rusk | B10: BCM Biotech @ Rusk MS | C10: EAS Secondary | D10: Same campus, spelled differently.
A11: De Chaumes ES | B11: DeChaumes ES | C11: EAS Elementary | D11: Same campus, spelled differently.
A12: DeZavala ES | B12: De Zavala ES | C12: NES Elementary | D12: Same campus, spelled differently.
A13: East EC HS | B13: East Early HS | C13: EAS Secondary | D13: Same campus, spelled differently.
A14: Garden Oaks | B14: Garden Oaks K - 8 | C14: EAS Elementary | D14: Same campus, spelled differently.
A15: HAIS HS | B15: HAIS | C15: Programs/Charters | D15: Same campus, spelled differently.
A16: Henderson JP ES | B16: JP Henderson ES | C16: EAS Elementary | D16: Same campus, spelled differently.
A17: High School Ahead Acad MS | B17: High School Ahead MS | C17: EAS Secondary | D17: Same campus, spelled differently.
A18: Highland Heights ES | B18: Highland Height ES | C18: NES Elementary | D18: Same campus, spelled differently.
... A27: Woodson | B27: Woodson ES | C27: NES Elementary | D27: Same campus, spelled differently.
